Workbook

Sheet Como usar
B2: PLANILHA DE AVALIAÇÃO — MODELO QUANTITATIVO
B4: O QUE MUDOU
B5: As perguntas | C5: São as mesmas da planilha antiga. Nenhuma pergunta nova, exceto A6 (inconsistência plantada), que entra no lugar de 'Resposta dos concorrentes' — item que ficou 89% zerado no PS 2026-1S e nem estava na Base.
B6: A escala | C6: Toda nota agora é 0, 1, 2 ou 3. Acabaram os 0,7 / 1,2 / 2,8. Cada nível tem uma frase que o descreve na aba 'Base avaliação'. Se você não consegue apontar a frase, você não pode dar aquela nota.
B7: Os pesos | C7: Comunicação 30 · Raciocínio 25 · Acurácia 25 · Entrega 10 · Vídeo 10. O peso agora está no bloco, não escondido no teto de cada pergunta.
B8: A trava | C8: A célula só aceita 0/1/2/3. No PS passado, 8 das 27 linhas tinham nota acima do teto do critério.
B9: O peso do vídeo | C9: 0.1
B10: R3 e E4 | C10: Reescritos para premiar RELEVÂNCIA, não volume. Antes, análise extra tangencial pontuava 2 e fazer o pedido direito pontuava 0 — invertido. Agora tangente é 0 e entregar o pedido completo é 1. Em E4, contagem de gráficos saiu: o que vale é o recurso sustentar uma afirmação.
B12: AS 5 REGRAS
B13: 1. Evidência obrigatória | C13: Ao lado da nota de cada bloco há uma coluna de evidência. Escreva o número do slide ou a minutagem do vídeo. É isso que torna a nota revisável e permite dar feedback ao candidato depois. NA PRÁTICA: preencha ao menos para todo 3 e todo 0 são as notas que afirmam algo forte e que o 2º avaliador contesta. O 2 é o meio-termo e raramente vira discussão. Veja a linha 6 (Modelo) para o formato.
B14: 2. Corrija por critério | C14: Avalie TODOS os candidatos no C1, depois todos no C2, e assim por diante. Nunca candidato por candidato. Comparar 27 respostas da mesma pergunta lado a lado é muito mais consistente e é o que evita que uma boa impressão geral contamine as 20 notas.
B15: 3. Dois avaliadores | C15: Todo candidato precisa de 2 avaliações independentes. No PS 2026-1S só 37% tiveram. Se a diferença entre as duas notas finais passar de 1,0, a aba Consolidado acende alerta: vai para conversa de calibração ou terceiro avaliador.
B16: 4. Calibre antes de abrir | C16: Antes do PS começar: peguem 3 entregas do PS anterior (uma boa, uma média, uma ruim), todo mundo avalia, comparem e discutam as divergências. Uma hora de reunião. É a maior alavanca de consistência que existe e não custa nada.
B17: 5. Corte definido antes | C17: Número de vagas e nota mínima decididos ANTES de ver as notas. Desempate escrito: 1º acurácia · 2º comunicação · 3º entrevista.
B19: A NOTA QUANDO DUAS PESSOAS CORRIGEM
B20: Sim, é a média | C20: Se um avaliador dá 6,0 e o outro 7,0, a nota do candidato é 6,50. A aba Consolidado faz isso sozinha (AVERAGEIF por nome). Não arredonde na mão.
B21: Onde a vírgula pode aparecer | C21: Só na MÉDIA ENTRE PESSOAS, nunca dentro da cabeça de uma pessoa. Cada avaliador só digita 0, 1, 2 ou 3 — e a célula não aceita outra coisa. O 6,50 é o resultado de duas leituras independentes; o antigo 6,5 era uma pessoa sentindo que valia meio ponto. Mesmo número, confiabilidade completamente diferente.
B22: Quando a média NÃO vale | C22: Se a diferença passar de 1,0 (ex.: 5,8 e 7,2), a aba acende alerta e a média fica suspensa. Média de duas leituras que discordam muito não é consenso, é um número inventado no meio. Nesse caso: conversem, releiam juntos o critério que divergiu e refaçam — ou chamem um terceiro.
B23: Por que 1,0 é o limite | C23: Com escala de 0 a 3 e 20 critérios, dois avaliadores calibrados raramente passam de 1 ponto de diferença na nota final. Se passou, quase sempre é um critério só sendo lido de dois jeitos — e é isso que a conversa resolve. As colunas 'Nota aval. 1' e 'Nota aval. 2' mostram as duas notas lado a lado.
B25: ELEGIBILIDADE (estágio / intercâmbio / formatura)
B26: Não é eliminatório | C26: Conforme o diretor: é um warning, não um corte. Por isso NÃO entra na nota e NÃO tem peso. Fica só na aba Consolidado.
B27: Dois níveis | C27: 🔴 EVASÃO — sai do ar em até 2 semestres (intercâmbio confirmado, formatura próxima). 🟡 CARGA — continua, mas com menos tempo (estagiando agora, estágio começando no ano). Estagiar não é ir embora: é ter menos tempo. São riscos diferentes.
B28: Onde ela morde | C28: A flag não soma nem subtrai ponto e nunca elimina. Ela (i) obriga uma pergunta específica na entrevista e (ii) só desempata entre candidatos a menos de 0,3 ponto um do outro.
B29: Horas por semana | C29: VOLTEM COM ESSA PERGUNTA NO FORMULÁRIO. 2025.2 perguntava quantas horas o candidato dedicaria (todos responderam: mediana 8h, variando de 4 a 40) e ela sumiu em 2026.1. Tem variância real e mede o risco de CARGA muito melhor que 'estagiando sim/não' — porque os 13 aprovados de 2025.2 declararam plano de estágio, TODOS os 13. Uma flag que dispara em 100% da lista não separa nada.
B30: O que os dados já dizem | C30: Dos 13 aprovados em 2025.2, 4 apareceram como avaliadores em 2026.1 (Gustavo, Fred, Victor, AnaJu) — com planos de estágio variados, sem padrão. O único com formatura em 2026 não reaparece. É indício fraco (n=1), mas aponta para FORMATURA como a variável de risco real, não estágio. Por isso 🔴 EVASÃO e 🟡 CARGA são separados.
B31: Medir | C31: Registrem a flag de cada aprovado. Daqui a 2 ou 3 PS, cruzem com quem de fato continuou no clube. Aí vocês saberão se a hipótese é verdadeira — hoje ninguém sabe.
B33: O CASE E A IA
B34: O problema | C34: 3 dias em casa: acurácia deixa de discriminar. No PS 2026-1S, antes da IA virar padrão, 62% dos candidatos já tiravam ≥80% do teto em 'Loja 5' e 65% em 'SG&A'. Peso sem variância não muda ranking.
B35: Erro plantado (A6) | C35: Coloquem uma inconsistência de propósito no material: a DRE não fecha por X, ou o enunciado contradiz a tabela anexa. IA aceita o input como verdade e segue. Custa 10 minutos montando o case e é o melhor discriminador por esforço investido.
B36: Premissa ausente | C36: Não deem o critério de rateio do SG&A entre lojas. Aí não existe 'a resposta certa': pontua-se se declarou a premissa, se a carregou até a recomendação sem se contradizer e se testou outra.
B37: Propriedade na ENTREVISTA | C37: Não tente detectar IA no take-home. Nos primeiros 10 minutos da entrevista, o candidato refaz UMA conta da própria entrega, ao vivo, com um parâmetro alterado. Quem montou o modelo resolve em 3 minutos. Registre em Consolidado!K como OK / Não OK.

Sheet Base avaliação
B2: BASE DE AVALIAÇÃO — cada nível tem uma descrição. Sem descrição apontada, a nota não vale.
B4: COMUNICAÇÃO & ESTRUTURA — 30 pontos de 100
B5: C1 | C5: 10 pts | D5: A comunicação está clara e direto ao ponto.
C6: 3 | D6: A recomendação está escrita em UMA frase, nos 2 primeiros slides, com o número que a sustenta.
C7: 2 | D7: A recomendação é explícita e clara, mas só aparece depois da metade da entrega.
C8: 1 | D8: Dá pra inferir a recomendação, mas ela não está escrita em lugar nenhum.
C9: 0 | D9: Não há recomendação, ou há duas incompatíveis entre si.
D10: TESTE OPERACIONAL: Aponte o slide e a frase. Não conseguiu apontar? Não é 3.
B12: C2 | C12: 8 pts | D12: O desafio apresenta um formato que poderia ser apresentado a um cliente real.
C13: 3 | D13: Documento fechado (capa, estrutura, apêndice), sem rascunho visível. Um cliente receberia como está.
C14: 2 | D14: Estruturado, mas com pontas soltas: conta solta, slide inacabado, formatação inconsistente.
C15: 1 | D15: Responde as perguntas, mas em formato de lista ou rascunho.
C16: 0 | D16: Foto de papel, texto corrido no e-mail, ou arquivo sem estrutura nenhuma.
D17: TESTE OPERACIONAL: Você mandaria esse arquivo, sem editar nada, pro cliente do seu projeto?
B19: C3 | C19: 7 pts | D19: A apresentação apresenta um bom storytelling e envolve o leitor.
C20: 3 | D20: Lendo só os títulos, na ordem, a história fecha sozinha: contexto -> problema -> análise -> recomendação -> riscos.
C21: 2 | D21: A sequência é lógica, com 1 ou 2 saltos que obrigam o leitor a voltar.
C22: 1 | D22: Os blocos existem, mas soltos — um não puxa o outro.
C23: 0 | D23: Ordem aleatória, ou é só uma lista de respostas às perguntas.
D24: TESTE OPERACIONAL: Leia SÓ os títulos em voz alta. Se a recomendação não aparecer, é no máximo 1.
B26: C4 | C26: 5 pts | D26: O trabalho está visualmente bonito.
C27: 3 | D27: Padrão único de fonte, cor e alinhamento em toda a entrega. Nenhum slide com parágrafo corrido.
C28: 2 | D28: Consistente, com até 2 slides fora do padrão.
C29: 1 | D29: Formatação improvisada, mas legível.
C30: 0 | D30: Ilegível, desalinhado, ou é texto corrido.
D31: TESTE OPERACIONAL: Conte os slides fora do padrão. É uma contagem, não uma impressão.
B34: RACIOCÍNIO DE NEGÓCIO — 25 pontos de 100
B35: R1 | C35: 8 pts | D35: Sua recomendação leva em consideração ambas as partes qualitativas e quantitativas do case.
C36: 3 | D36: A recomendação cita o número que a sustenta E a razão de negócio; as duas partes se apoiam.
C37: 2 | D37: Cita as duas, mas uma é decorativa — o número não sustenta de fato a decisão.
C38: 1 | D38: Só quantitativa (número sem porquê) ou só qualitativa (opinião sem número).
C39: 0 | D39: Não há recomendação, ou ela contraria os próprios números apresentados.
D40: TESTE OPERACIONAL: Tape o número: a recomendação ainda se sustenta? Tape o argumento: ainda se sustenta?
B42: R2 | C42: 7 pts | D42: O trabalho apresenta uma discussão rica com diversos pontos de vista sobre a expansão.
C43: 3 | D43: Apresenta ao menos 2 caminhos, compara com critério explícito e justifica o que descartou.
C44: 2 | D44: Cita alternativas, mas não compara — escolhe sem justificar.
C45: 1 | D45: Menciona que existem alternativas, sem desenvolver nenhuma.
C46: 0 | D46: Caminho único, sem discussão.
D47: TESTE OPERACIONAL: Ele descartou alguma coisa por escrito? Se não descartou nada, não discutiu.
B49: R3 | C49: 5 pts | D49: Foi além do pedido e trouxe análises interessantes.
C50: 3 | D50: Trouxe algo não pedido que MUDA ou FORTALECE a recomendação.
C51: 2 | D51: Trouxe algo não pedido, correto e LIGADO À DECISÃO, mas que não altera a conclusão.
C52: 1 | D52: Não trouxe nada além, mas entregou o pedido de forma completa e correta.
C53: 0 | D53: O material extra NÃO SE CONECTA à decisão (tangenciou), ou o pedido ficou incompleto.
D54: TESTE OPERACIONAL: A análise extra responde a uma pergunta que o cliente deveria ter feito? Se não dá pra dizer qual decisão ela informa, é 0 — não 2. Volume não conta: três páginas de análise tangencial valem menos que nenhuma.
B56: R4 | C56: 5 pts | D56: Foi além das interpretações óbvias dos indicadores e agregou valor à análise.
C57: 3 | D57: Explica a CAUSA por trás do indicador e o que fazer com ela.
C58: 2 | D58: Compara o indicador com algo (outra loja, outro ano, benchmark) e tira conclusão.
C59: 1 | D59: Lê o indicador corretamente (ex.: a margem caiu).
C60: 0 | D60: Repete o número sem interpretar.
D61: TESTE OPERACIONAL: Ele respondeu 'por quê', 'comparado a quê', ou só 'quanto'?
B64: ACURÁCIA TÉCNICA — 25 pontos de 100
B65: ⚠ ESTE É O ÚNICO BLOCO QUE DEPENDE DO CASE. As ÂNCORAS (3/2/1/0) e os PESOS não mudam nunca — valem para qualquer case, todo semestre. O que muda a cada PS é só o TEXTO DA PERGUNTA de A1 a A4 e os valores da aba Gabarito. A1/A2 = contas com resposta única · A3 = a projeção pedida · A4 = a alternativa · A5 e A6 já são genéricos, não precisa reescrever. Se o case novo tiver 3 contas centrais em vez de 2, divida os 12 pontos de A1+A2 entre elas; se tiver 1, ela leva os 12. O total do bloco (25) e as âncoras é que não podem mudar.
B66: A1 | C66: 6 pts | D66: Calculou o resultado operacional anual dos QUATRO bairros no modelo de ARMÁRIOS INTELIGENTES, com o arredondamento dos bancos para cima? | E66: col. Z · BagHub 2026-2S · valores e tolerância na aba Gabarito
C67: 3 | D67: Valor dentro da tolerância definida na aba Gabarito E memória de cálculo visível.
C68: 2 | D68: Método correto, valor fora da tolerância (erro aritmético).
C69: 1 | D69: Identificou a lógica correta, não fechou o número.
C70: 0 | D70: Não respondeu, ou o método está errado.
D71: TESTE OPERACIONAL: Confira contra a aba Gabarito. Dois avaliadores têm que chegar no mesmo número.
B73: A2 | C73: 6 pts | D73: Calculou o resultado operacional anual dos QUATRO bairros no modelo de PONTOS PARCEIROS? | E73: col. AA · BagHub 2026-2S · receita e custo-base são iguais nos dois modelos
C74: 3 | D74: Valor dentro da tolerância definida na aba Gabarito E memória de cálculo visível.
C75: 2 | D75: Método correto, valor fora da tolerância (erro aritmético).
C76: 1 | D76: Identificou a lógica correta, não fechou o número.
C77: 0 | D77: Não respondeu, ou o método está errado.
D78: TESTE OPERACIONAL: Confira contra a aba Gabarito.
B80: A3 | C80: 4 pts | D80: [COMPARAÇÃO ENTRE MODELOS — este case não pede projeção] Comparou os dois modelos e o número da recomendação bate com a tabela que ele mesmo montou? | E80: ADAPTADO — o case não tem meta declarada, então a âncora foi repontuada na comparação de modelos
C81: 3 | D81: Calcula o ganho líquido dos parceiros (economia de bancos − acréscimo de operação) nos 4 bairros E o número citado na recomendação bate com a tabela dele.
C82: 2 | D82: Compara os dois modelos em parte dos bairros, ou nos quatro sem mostrar de onde vem a diferença.
C83: 1 | D83: Afirma que um modelo é melhor, sem número que sustente.
C84: 0 | D84: Não comparou os modelos.
D85: TESTE OPERACIONAL: Pegue o número que ele escreveu na recomendação e procure na tabela dele. Bate?
B87: A4 | C87: 3 pts | D87: Indicou a ordem de prioridade dos demais bairros, ou defendeu o modelo alternativo, com o impacto quantificado? | E87: col. AB · o gabarito autoriza Centro Histórico primeiro e armários, desde que justificados
C88: 3 | D88: Propõe alternativa com número estimado de impacto.
C89: 2 | D89: Propõe alternativa coerente com o case, sem quantificar.
C90: 1 | D90: Alternativa genérica — serviria pra qualquer empresa.
C91: 0 | D91: Não propôs, ou propõe algo que contraria o case.
D92: TESTE OPERACIONAL: A alternativa cita algo que só existe NESTE case? Se não, é 1.
B94: A5 | C94: 3 pts | D94: Analisou riscos e próximos passos de forma lógica e estruturada? | E94: col. AC (era 1 pt) — serve para qualquer case, não precisa reescrever
C95: 3 | D95: Riscos específicos da recomendação DELE, com mitigação e prazo.
C96: 2 | D96: Riscos específicos, sem mitigação.
C97: 1 | D97: Riscos genéricos (crise, concorrência, câmbio).
C98: 0 | D98: Não fez.
D99: TESTE OPERACIONAL: O risco listado some se a recomendação mudar? Se não some, é genérico.
B101: A6 | C101: 3 pts | D101: [PREMISSAS — este case não tem inconsistência plantada] Explicitou as premissas que o enunciado deixa em aberto ou adverte contra? | E101: ADAPTADO — nada foi plantado no BagHub; plantar de verdade no case de 2027-1S
C102: 3 | D102: Nomeia ao menos uma premissa E diz como tratou (ex.: "a utilização não entra na receita, a demanda já está em transações"; "2.400 posições não são 2.400 parceiros").
C103: 2 | D103: Nomeia uma premissa, sem dizer o que fez com ela.
C104: 1 | D104: Não nomeia nenhuma, mas os cálculos mostram que tratou certo.
C105: 0 | D105: Construiu a análise sobre a leitura errada: aplicou utilização à receita, usou 52 semanas, cobrou bancos dos parceiros ou trocou o índice de complexidade.
D106: TESTE OPERACIONAL: Procure a FRASE. Sem frase, o teto é 1 — mesmo com todos os números certos. Lista de armadilhas na aba Gabarito.
B109: ENTREGA (CHECKLIST) — 10 pontos de 100
B110: E1 | C110: 3 pts | D110: Enviou planilha com a memória de cálculo. | E110: col. U (era 'Excel = 0,5')
C111: 1 / 0 | D111: Item binário: enviou = 1, não enviou = 0.
D112: TESTE OPERACIONAL: Sim = 1, Não = 0. Sem julgamento.
B114: E2 | C114: 2 pts | D114: Enviou apresentação fechada (PPT ou relatório). | E114: col. U (era 'PPT = 0,5')
C115: 1 / 0 | D115: Item binário: enviou = 1, não enviou = 0.
D116: TESTE OPERACIONAL: Sim = 1, Não = 0.
B118: E3 | C118: 2 pts | D118: Gravou o vídeo da entrega. | E118: col. AE (era 'Mandou vídeo = 1 ponto')
C119: 1 / 0 | D119: Item binário: enviou = 1, não enviou = 0.
D120: TESTE OPERACIONAL: Sim = 1, Não = 0.
B122: E4 | C122: 3 pts | D122: O trabalho apresenta recursos textuais e visuais (gráficos, tabelas de DRE). | E122: col. AF (era 2 pts)
...

Sheet Avaliação
B2: AVALIAÇÃO — uma linha por candidato POR AVALIADOR. Cada candidato deve aparecer 2 vezes.
B4: Cada nome aparece 2 vezes pra terem 2 avaliadores por pessoa! | K4: COMUNICAÇÃO & ESTRUTURA (30) | P4: RACIOCÍNIO DE NEGÓCIO (25) | U4: ACURÁCIA TÉCNICA (25) | AB4: ENTREGA (CHECKLIST) (10) | AF4: VÍDEO DO FORMULÁRIO (10)
A5: # | B5: E-mail | C5: Candidato(a) | D5: Avaliador | E5: NOTA FINAL | F5: Comunic. /30 | G5: Racioc. /25 | H5: Acurácia /25 | I5: Entrega /10 | J5: Vídeo /10 | K5: C1 | L5: C2 | M5: C3 | N5: C4 | O5: Evidência — Comunicação | P5: R1 | Q5: R2 | R5: R3 | S5: R4 | T5: Evidência — Raciocínio | U5: A1 | V5: A2 | W5: A3 | X5: A4 | Y5: A5 | Z5: A6 | AA5: Evidência — Acurácia | AB5: E1 | AC5: E2 | AD5: E3 | AE5: E4 | AF5: V1 | AG5: V2 | AH5: Evidência — Vídeo | AI5: Comentário geral
C6: Modelo (entrega nota máxima) | E6: =IF(COUNT(K6:AG6)=0,"",ROUND((F6+G6+H6+I6+J6)/10,2)) | F6: =IF(COUNT(K6:AG6)=0,"",(K6*10+L6*8+M6*7+N6*5)/3) | G6: =IF(COUNT(K6:AG6)=0,"",(P6*8+Q6*7+R6*5+S6*5)/3) | H6: =IF(COUNT(K6:AG6)=0,"",(U6*6+V6*6+W6*4+X6*3+Y6*3+Z6*3)/3) | I6: =IF(COUNT(K6:AG6)=0,"",AB6*3+AC6*2+AD6*2+AE6*1) | J6: =IF(COUNT(K6:AG6)=0,"",(AF6*5+AG6*5)/3) | K6: 3 | L6: 3 | M6: 3 | N6: 3 | O6: C1=3: recomendação em uma frase no slide 2, com os 27,84 mi · C2=3: documento fechado, com apêndice de cálculo · C3=3: só os títulos já contam a história · C4=3: padrão único | P6: 3 | Q6: 3 | R6: 3 | S6: 3 | T6: R1=3: liga os 27,84 mi à baixa complexidade e ao fluxo do terminal · R2=3: compara armários e parceiros nos 4 bairros e justifica o descarte · R3=3: traz a margem como leitura complementar · R4=3: explica por que a utilização baixa da Arena não permite cortar posições | U6: 3 | V6: 3 | W6: 3 | X6: 3 | Y6: 3 | Z6: 3 | AA6: A1=3: aba "Armários", 4 bairros conferem, Arena com 23 bancos · A2=3: aba "Parceiros" · A3=3: ganho líquido 2,76 no slide 6 e o mesmo número na recomendação · A4=3: CH como 2º, 24,50 mi · A5=3: risco de pico com mitigação · A6=3: slide 4 diz que a utilização não entra na receita | AB6: 1 | AC6: 1 | AD6: 1 | AE6: 3 | AF6: 3 | AG6: 3 | AH6: V1=3: fala solta o vídeo inteiro, sem ler · V2=3: cita um projeto ou área do CCU e conecta com o que quer desenvolver
B7: g278083@dac.unicamp.br | C7: Gabrielle Cristofani do Rosario | D7: victor | E7: =IF(COUNT(K7:AG7)=0,"",ROUND((F7+G7+H7+I7+J7)/10,2)) | F7: =IF(COUNT(K7:AG7)=0,"",(K7*10+L7*8+M7*7+N7*5)/3) | G7: =IF(COUNT(K7:AG7)=0,"",(P7*8+Q7*7+R7*5+S7*5)/3) | H7: =IF(COUNT(K7:AG7)=0,"",(U7*6+V7*6+W7*4+X7*3+Y7*3+Z7*3)/3) | I7: =IF(COUNT(K7:AG7)=0,"",AB7*3+AC7*2+AD7*2+AE7*1) | J7: =IF(COUNT(K7:AG7)=0,"",(AF7*5+AG7*5)/3) | K7: 2 | L7: 2 | M7: 2 | N7: 2 | O7: Slide feito por IA, provavelmente | P7: 2 | Q7: 2 | R7: 1 | S7: 1 | T7: Contas no papel, parece q n fez IA | U7: 3 | V7: 3 | W7: 2 | X7: 2 | Y7: 2 | AB7: 1 | AC7: 1 | AD7: 0 | AE7: 3 | AF7: 2 | AG7: 2 | AI7: v2 talvez seja 3
B8: b309603@dac.unicamp.br | C8: Bruno Heberth Oliveira Bastos | D8: victor | E8: =IF(COUNT(K8:AG8)=0,"",ROUND((F8+G8+H8+I8+J8)/10,2)) | F8: =IF(COUNT(K8:AG8)=0,"",(K8*10+L8*8+M8*7+N8*5)/3) | G8: =IF(COUNT(K8:AG8)=0,"",(P8*8+Q8*7+R8*5+S8*5)/3) | H8: =IF(COUNT(K8:AG8)=0,"",(U8*6+V8*6+W8*4+X8*3+Y8*3+Z8*3)/3) | I8: =IF(COUNT(K8:AG8)=0,"",AB8*3+AC8*2+AD8*2+AE8*1) | J8: =IF(COUNT(K8:AG8)=0,"",(AF8*5+AG8*5)/3) | K8: 3 | L8: 1 | M8: 1 | N8: 2 | O8: Me sinto um idiota corrigindo bagulho 100% feito por IA. Pior é que cumpriu os requisitos. | P8: 2 | Q8: 1 | R8: 1 | S8: 0 | U8: 3 | V8: 3 | W8: 3 | X8: 2 | Y8: 0 | AB8: 1 | AC8: 1 | AD8: 0 | AF8: 3 | AG8: 1 | AI8: É da Adm n dá
B9: j309764@dac.unicamp.br | C9: João Pedro Mendes Stama | D9: victor | E9: =IF(COUNT(K9:AG9)=0,"",ROUND((F9+G9+H9+I9+J9)/10,2)) | F9: =IF(COUNT(K9:AG9)=0,"",(K9*10+L9*8+M9*7+N9*5)/3) | G9: =IF(COUNT(K9:AG9)=0,"",(P9*8+Q9*7+R9*5+S9*5)/3) | H9: =IF(COUNT(K9:AG9)=0,"",(U9*6+V9*6+W9*4+X9*3+Y9*3+Z9*3)/3) | I9: =IF(COUNT(K9:AG9)=0,"",AB9*3+AC9*2+AD9*2+AE9*1) | J9: =IF(COUNT(K9:AG9)=0,"",(AF9*5+AG9*5)/3) | AF9: 3 | AG9: 2 | AI9: N passaria fez o gmat na cama mas parece legal
B10: r238449@dac.unicamp.br | C10: Rafael Ponciano Rodrigues dos Santos | D10: Matteo | E10: 4.17 | F10: 7.33 | G10: 5.67 | H10: 16.33 | I10: 4 | J10: 8.33 | K10: 1 | L10: 0 | M10: 1 | N10: 1 | O10: Não há recomendação escrita. Entregou seis fotos de caderno e um print de planilha, sem documento fechado. Os quatro blocos de bairro são independentes e não levam a conclusão. | P10: 0 | Q10: 1 | R10: 0 | S10: 2 | T10: Comparou os dois modelos nos quatro bairros e projetou cinco anos, mas não escolheu bairro nem modelo. Boa observação própria: anotou que uma conexão dura 1h30 a 2h e que isso não dá tempo de passear, o que põe em dúvida a demanda da Estação. | U10: 3 | V10: 3 | W10: 1 | X10: 2 | Y10: 1 | AA10: Oito cenários conferem com o gabarito, com a Arena em 23 bancos. A projeção de cinco anos remove o custo do banco a partir do Ano 2, e o Anexo E diz que é anual. Sem riscos e sem próximos passos. | AB10: 1 | AC10: 0 | AD10: 0 | AE10: 1 | AF10: 3 | AG10: 2 | AI10: A entrega mais frustrante do grupo: a parte difícil está certa e a fácil não foi feita. Os oito cenários estão corretos à mão, aplicou os 3C's e projetou cinco anos. E fez a melhor observação qualitativa que eu vi, sobre a conexão de 1h30 não dar tempo de passear. E então não recomendou nada, sem bairro, sem modelo, sem riscos. Na entrevista a pergunta é a que falta: qual bairro e qual modelo você escolhe?
B11: enzo.gag17@gmail.com | C11: Enzo Chofakian Gagliardi | D11: victor | E11: =IF(COUNT(K11:AG11)=0,"",ROUND((F11+G11+H11+I11+J11)/10,2)) | F11: =IF(COUNT(K11:AG11)=0,"",(K11*10+L11*8+M11*7+N11*5)/3) | G11: =IF(COUNT(K11:AG11)=0,"",(P11*8+Q11*7+R11*5+S11*5)/3) | H11: =IF(COUNT(K11:AG11)=0,"",(U11*6+V11*6+W11*4+X11*3+Y11*3+Z11*3)/3) | I11: =IF(COUNT(K11:AG11)=0,"",AB11*3+AC11*2+AD11*2+AE11*1) | J11: =IF(COUNT(K11:AG11)=0,"",(AF11*5+AG11*5)/3) | K11: 3 | L11: 2 | M11: 2 | N11: 2 | O11: Slide de IA. | U11: 3 | V11: 3 | W11: 3 | X11: 0 | Y11: 3 | AB11: 1 | AC11: 1 | AD11: 0 | AE11: 0 | AF11: 2 | AG11: 2 | AI11: ok
B12: e278588@dac.unicamp.br | C12: Enrico Tristão e Mello de Oliveira | D12: victor | E12: =IF(COUNT(K12:AG12)=0,"",ROUND((F12+G12+H12+I12+J12)/10,2)) | F12: =IF(COUNT(K12:AG12)=0,"",(K12*10+L12*8+M12*7+N12*5)/3) | G12: =IF(COUNT(K12:AG12)=0,"",(P12*8+Q12*7+R12*5+S12*5)/3) | H12: =IF(COUNT(K12:AG12)=0,"",(U12*6+V12*6+W12*4+X12*3+Y12*3+Z12*3)/3) | I12: =IF(COUNT(K12:AG12)=0,"",AB12*3+AC12*2+AD12*2+AE12*1) | J12: =IF(COUNT(K12:AG12)=0,"",(AF12*5+AG12*5)/3) | K12: 3 | L12: 2 | M12: 2 | N12: 2 | O12: Slide de IA. | P12: 3 | Q12: 3 | R12: 2 | S12: 2 | U12: 3 | V12: 3 | W12: 3 | X12: 2 | Y12: 2 | AB12: 1 | AC12: 1 | AD12: 1 | AE12: 3 | AF12: 2 | AG12: 1 | AI12: N falou nada do clube só do mercado
B13: e221509@dac.unicamp.br | C13: Eduardo Alves Henrique | D13: victor | E13: =IF(COUNT(K13:AG13)=0,"",ROUND((F13+G13+H13+I13+J13)/10,2)) | F13: =IF(COUNT(K13:AG13)=0,"",(K13*10+L13*8+M13*7+N13*5)/3) | G13: =IF(COUNT(K13:AG13)=0,"",(P13*8+Q13*7+R13*5+S13*5)/3) | H13: =IF(COUNT(K13:AG13)=0,"",(U13*6+V13*6+W13*4+X13*3+Y13*3+Z13*3)/3) | I13: =IF(COUNT(K13:AG13)=0,"",AB13*3+AC13*2+AD13*2+AE13*1) | J13: =IF(COUNT(K13:AG13)=0,"",(AF13*5+AG13*5)/3) | K13: 3 | L13: 2 | M13: 3 | N13: 2 | P13: 3 | Q13: 2 | R13: 1 | S13: 1 | W13: 2 | X13: 2 | Y13: 0 | AC13: 1 | AD13: 1 | AE13: 3 | AF13: 2 | AG13: 0 | AI13: Só falou que queria o CCU pra pegar cargo e ter no currículo
B14: l304532@dac.unicamp.br | C14: Leandra Cunha de Souza | D14: victor | E14: =IF(COUNT(K14:AG14)=0,"",ROUND((F14+G14+H14+I14+J14)/10,2)) | F14: =IF(COUNT(K14:AG14)=0,"",(K14*10+L14*8+M14*7+N14*5)/3) | G14: =IF(COUNT(K14:AG14)=0,"",(P14*8+Q14*7+R14*5+S14*5)/3) | H14: =IF(COUNT(K14:AG14)=0,"",(U14*6+V14*6+W14*4+X14*3+Y14*3+Z14*3)/3) | I14: =IF(COUNT(K14:AG14)=0,"",AB14*3+AC14*2+AD14*2+AE14*1) | J14: =IF(COUNT(K14:AG14)=0,"",(AF14*5+AG14*5)/3) | K14: 2 | L14: 1 | M14: 1 | N14: 1 | O14: Slide de IA, tabela cheia de contas, bem ruim | P14: 2 | Q14: 2 | R14: 2 | S14: 1 | U14: 2 | V14: 2 | W14: 2 | X14: 2 | Y14: 1 | AA14: Contas todas soltas, bem ruim | AB14: 0 | AC14: 1 | AD14: 0 | AE14: 1 | AF14: 2 | AG14: 2 | AI14: Mid, muitas experiencias mas todas na escola, achei confusa a resposta só saiu citando coisas q fez
B15: v188630@dac.unicamp.br | C15: Vagner Ássimos Gomes Carlos Filho | D15: victor | E15: =IF(COUNT(K15:AG15)=0,"",ROUND((F15+G15+H15+I15+J15)/10,2)) | F15: =IF(COUNT(K15:AG15)=0,"",(K15*10+L15*8+M15*7+N15*5)/3) | G15: =IF(COUNT(K15:AG15)=0,"",(P15*8+Q15*7+R15*5+S15*5)/3) | H15: =IF(COUNT(K15:AG15)=0,"",(U15*6+V15*6+W15*4+X15*3+Y15*3+Z15*3)/3) | I15: =IF(COUNT(K15:AG15)=0,"",AB15*3+AC15*2+AD15*2+AE15*1) | J15: =IF(COUNT(K15:AG15)=0,"",(AF15*5+AG15*5)/3) | K15: 2 | L15: 2 | M15: 3 | N15: 2 | O15: Slide de ia, muito texto mas parece q escreveu um pouco | P15: 1 | Q15: 2 | R15: 1 | S15: 2 | U15: 2 | V15: 2 | W15: 2 | X15: 2 | Y15: 2 | AB15: 0 | AC15: 1 | AD15: 0 | AE15: 2 | AF15: 2 | AG15: 3 | AI15: Falou das palestras, n sei se tava lendo ou só olhado pra camera mas falou bem ent talvez seja 3
B16: m277865@dac.unicamp.br | C16: Mariana Nunes Galvão Sant'Anna | D16: luis | E16: =IF(COUNT(K16:AG16)=0,"",ROUND((F16+G16+H16+I16+J16)/10,2)) | F16: =IF(COUNT(K16:AG16)=0,"",(K16*10+L16*8+M16*7+N16*5)/3) | G16: =IF(COUNT(K16:AG16)=0,"",(P16*8+Q16*7+R16*5+S16*5)/3) | H16: =IF(COUNT(K16:AG16)=0,"",(U16*6+V16*6+W16*4+X16*3+Y16*3+Z16*3)/3) | I16: =IF(COUNT(K16:AG16)=0,"",AB16*3+AC16*2+AD16*2+AE16*1) | J16: =IF(COUNT(K16:AG16)=0,"",(AF16*5+AG16*5)/3) | K16: 3 | L16: 2 | M16: 3 | N16: 3 | P16: 3 | Q16: 3 | R16: 2 | S16: 3 | U16: 3 | V16: 3 | W16: 3 | X16: 2 | Y16: 3 | AB16: 1 | AC16: 1 | AD16: 0 | AE16: 3 | AF16: 3 | AG16: 2 | AI16: motivo genérico
B17: a266739@dac.unicamp.br | C17: Aslan Rodrigues Maia | D17: Ferro | E17: =IF(COUNT(K17:AG17)=0,"",ROUND((F17+G17+H17+I17+J17)/10,2)) | F17: =IF(COUNT(K17:AG17)=0,"",(K17*10+L17*8+M17*7+N17*5)/3) | G17: =IF(COUNT(K17:AG17)=0,"",(P17*8+Q17*7+R17*5+S17*5)/3) | H17: =IF(COUNT(K17:AG17)=0,"",(U17*6+V17*6+W17*4+X17*3+Y17*3+Z17*3)/3) | I17: =IF(COUNT(K17:AG17)=0,"",AB17*3+AC17*2+AD17*2+AE17*1) | J17: =IF(COUNT(K17:AG17)=0,"",(AF17*5+AG17*5)/3) | K17: 2 | L17: 2 | M17: 3 | N17: 3 | O17: Slide de IA, mas parece q se esforçou mais | P17: 2 | Q17: 2 | R17: 2 | S17: 3 | U17: 3 | V17: 2 | W17: 2 | X17: 2 | Y17: 2 | AB17: 1 | AC17: 1 | AD17: 0 | AE17: 2 | AF17: 1 | AG17: 2 | AI17: TIrou 2/3 do Gmat, e falou um pouco travado no vídeo, mas foi bem (não é bixo)
B18: j278641@dac.unicamp.br | C18: João Gabriel de Oliveira Morcelli | D18: Ferro | E18: =IF(COUNT(K18:AG18)=0,"",ROUND((F18+G18+H18+I18+J18)/10,2)) | F18: =IF(COUNT(K18:AG18)=0,"",(K18*10+L18*8+M18*7+N18*5)/3) | G18: =IF(COUNT(K18:AG18)=0,"",(P18*8+Q18*7+R18*5+S18*5)/3) | H18: =IF(COUNT(K18:AG18)=0,"",(U18*6+V18*6+W18*4+X18*3+Y18*3+Z18*3)/3) | I18: =IF(COUNT(K18:AG18)=0,"",AB18*3+AC18*2+AD18*2+AE18*1) | J18: =IF(COUNT(K18:AG18)=0,"",(AF18*5+AG18*5)/3) | K18: 3 | L18: 3 | M18: 2 | N18: 2 | O18: Fez uma analise bem legal de critérios ficou muito bom mas usou MUITA ia com certeza. | P18: 3 | Q18: 2 | R18: 3 | S18: 3 | U18: 3 | V18: 3 | W18: 3 | X18: 2 | Y18: 3 | AB18: 1 | AC18: 1 | AD18: 1 | AE18: 3 | AF18: 3 | AG18: 2 | AI18: 2/3 Gmat, fez no final sem energia, cara foi resiliente, falou muito bem no vídeo
B19: r278709@dac.unicamp.br | C19: Raphael Negrini Saggioro | D19: Ferro | E19: =IF(COUNT(K19:AG19)=0,"",ROUND((F19+G19+H19+I19+J19)/10,2)) | F19: =IF(COUNT(K19:AG19)=0,"",(K19*10+L19*8+M19*7+N19*5)/3) | G19: =IF(COUNT(K19:AG19)=0,"",(P19*8+Q19*7+R19*5+S19*5)/3) | H19: =IF(COUNT(K19:AG19)=0,"",(U19*6+V19*6+W19*4+X19*3+Y19*3+Z19*3)/3) | I19: =IF(COUNT(K19:AG19)=0,"",AB19*3+AC19*2+AD19*2+AE19*1) | J19: =IF(COUNT(K19:AG19)=0,"",(AF19*5+AG19*5)/3) | K19: 2 | L19: 1 | M19: 1 | N19: 1 | O19: O cara só fez o vídeo e rascunho, meio estilo case interview | P19: 2 | Q19: 2 | R19: 1 | S19: 1 | W19: 3 | X19: 3 | Y19: 0 | AB19: 0 | AC19: 0 | AD19: 1 | AE19: 0 | AF19: 2 | AG19: 3 | AI19: 2/3 Gmat na média, vídeo foi muito bem, citou todos projetos
B20: g278107@dac.unicamp.br | C20: Gustavo Daher Pereira | D20: Ferro | E20: =IF(COUNT(K20:AG20)=0,"",ROUND((F20+G20+H20+I20+J20)/10,2)) | F20: =IF(COUNT(K20:AG20)=0,"",(K20*10+L20*8+M20*7+N20*5)/3) | G20: =IF(COUNT(K20:AG20)=0,"",(P20*8+Q20*7+R20*5+S20*5)/3) | H20: =IF(COUNT(K20:AG20)=0,"",(U20*6+V20*6+W20*4+X20*3+Y20*3+Z20*3)/3) | I20: =IF(COUNT(K20:AG20)=0,"",AB20*3+AC20*2+AD20*2+AE20*1) | J20: =IF(COUNT(K20:AG20)=0,"",(AF20*5+AG20*5)/3) | AF20: 2 | AG20: 2 | AI20: 2/3 Gmat. Mano esse cara é a definição de estar na média
B21: rickfilho2007@gmail.com | C21: Ricardo Augusto Schmitt Filho | D21: Ferro | E21: =IF(COUNT(K21:AG21)=0,"",ROUND((F21+G21+H21+I21+J21)/10,2)) | F21: =IF(COUNT(K21:AG21)=0,"",(K21*10+L21*8+M21*7+N21*5)/3) | G21: =IF(COUNT(K21:AG21)=0,"",(P21*8+Q21*7+R21*5+S21*5)/3) | H21: =IF(COUNT(K21:AG21)=0,"",(U21*6+V21*6+W21*4+X21*3+Y21*3+Z21*3)/3) | I21: =IF(COUNT(K21:AG21)=0,"",AB21*3+AC21*2+AD21*2+AE21*1) | J21: =IF(COUNT(K21:AG21)=0,"",(AF21*5+AG21*5)/3) | K21: 3 | L21: 2 | M21: 2 | N21: 2 | O21: Acho q fez na moral o slide, sem ia | P21: 3 | Q21: 2 | R21: 1 | S21: 3 | U21: 3 | V21: 3 | W21: 3 | X21: 3 | Y21: 3 | AB21: 1 | AC21: 1 | AD21: 1 | AE21: 1 | AF21: 2 | AG21: 2 | AI21: 2/3 Gmat, falou bem, mas parecia ler as vezes
B22: m306365@dac.unicamp.br | C22: Matheus Dias Freitas | D22: Ferro | E22: =IF(COUNT(K22:AG22)=0,"",ROUND((F22+G22+H22+I22+J22)/10,2)) | F22: =IF(COUNT(K22:AG22)=0,"",(K22*10+L22*8+M22*7+N22*5)/3) | G22: =IF(COUNT(K22:AG22)=0,"",(P22*8+Q22*7+R22*5+S22*5)/3) | H22: =IF(COUNT(K22:AG22)=0,"",(U22*6+V22*6+W22*4+X22*3+Y22*3+Z22*3)/3) | I22: =IF(COUNT(K22:AG22)=0,"",AB22*3+AC22*2+AD22*2+AE22*1) | J22: =IF(COUNT(K22:AG22)=0,"",(AF22*5+AG22*5)/3) | AF22: 0 | AG22: 0 | AI22: (BIXO) Vídeo de toca e perguntou se o gmat era em inglês mesmo, reportado
B23: k267983@dac.unicamp.br | C23: Klaus Augusto Santos da Silva | D23: Ferro | E23: =IF(COUNT(K23:AG23)=0,"",ROUND((F23+G23+H23+I23+J23)/10,2)) | F23: =IF(COUNT(K23:AG23)=0,"",(K23*10+L23*8+M23*7+N23*5)/3) | G23: =IF(COUNT(K23:AG23)=0,"",(P23*8+Q23*7+R23*5+S23*5)/3) | H23: =IF(COUNT(K23:AG23)=0,"",(U23*6+V23*6+W23*4+X23*3+Y23*3+Z23*3)/3) | I23: =IF(COUNT(K23:AG23)=0,"",AB23*3+AC23*2+AD23*2+AE23*1) | J23: =IF(COUNT(K23:AG23)=0,"",(AF23*5+AG23*5)/3) | K23: 0 | L23: 1 | M23: 1 | N23: 1 | O23: Do mesmo jeito que ele usou IA pra tudo, podemos usar IA no lugar dele. | P23: 1 | Q23: 0 | R23: 1 | S23: 0 | U23: 3 | V23: 3 | W23: 1 | X23: 0 | Y23: 0 | AB23: 0 | AC23: 1 | AD23: 0 | AE23: 0 | AF23: 2 | AG23: 1 | AI23: Achei o vídeo meio merda, ele fala bem, mas achei q falou umas coisas nada a ver
B24: r302729@dac.unicamp.br | C24: Rafael Rodrigues Moreira | D24: Ferro | E24: =IF(COUNT(K24:AG24)=0,"",ROUND((F24+G24+H24+I24+J24)/10,2)) | F24: =IF(COUNT(K24:AG24)=0,"",(K24*10+L24*8+M24*7+N24*5)/3) | G24: =IF(COUNT(K24:AG24)=0,"",(P24*8+Q24*7+R24*5+S24*5)/3) | H24: =IF(COUNT(K24:AG24)=0,"",(U24*6+V24*6+W24*4+X24*3+Y24*3+Z24*3)/3) | I24: =IF(COUNT(K24:AG24)=0,"",AB24*3+AC24*2+AD24*2+AE24*1) | J24: =IF(COUNT(K24:AG24)=0,"",(AF24*5+AG24*5)/3) | K24: 2 | L24: 3 | M24: 2 | N24: 3 | O24: Fez vídeo, diferencial ótimo, e falou bem no vídeo | P24: 3 | Q24: 2 | R24: 2 | S24: 2 | U24: 2 | V24: 3 | W24: 2 | X24: 2 | Y24: 1 | AA24: Faltou risco e próximos passos mesmo | AB24: 0 | AC24: 1 | AD24: 1 | AE24: 3 | AF24: 2 | AG24: 3 | AH24: Slide com IA, mas fez vídeo, estudou pro case | AI24: (BIXO) Mas falou bem, tava lendo, mas sempre cola nas palestras
B25: c258388@dac.unicamp.br | C25: Caio Augusto Saab | D25: luis | E25: =IF(COUNT(K25:AG25)=0,"",ROUND((F25+G25+H25+I25+J25)/10,2)) | F25: =IF(COUNT(K25:AG25)=0,"",(K25*10+L25*8+M25*7+N25*5)/3) | G25: =IF(COUNT(K25:AG25)=0,"",(P25*8+Q25*7+R25*5+S25*5)/3) | H25: =IF(COUNT(K25:AG25)=0,"",(U25*6+V25*6+W25*4+X25*3+Y25*3+Z25*3)/3) | I25: =IF(COUNT(K25:AG25)=0,"",AB25*3+AC25*2+AD25*2+AE25*1) | J25: =IF(COUNT(K25:AG25)=0,"",(AF25*5+AG25*5)/3) | K25: 1 | L25: 1 | M25: 1 | N25: 0 | P25: 1 | Q25: 0 | R25: 0 | S25: 0 | U25: 3 | V25: 3 | W25: 1 | X25: 0 | Y25: 0 | AB25: 0 | AC25: 1 | AD25: 0 | AE25: 0 | AF25: 2 | AG25: 2 | AI25: fala com pouca naturalidade e sem motivo concreto
B26: j260826@dac.unicamp.br | C26: José Vitor Dias Tutu | D26: luis | E26: =IF(COUNT(K26:AG26)=0,"",ROUND((F26+G26+H26+I26+J26)/10,2)) | F26: =IF(COUNT(K26:AG26)=0,"",(K26*10+L26*8+M26*7+N26*5)/3) | G26: =IF(COUNT(K26:AG26)=0,"",(P26*8+Q26*7+R26*5+S26*5)/3) | H26: =IF(COUNT(K26:AG26)=0,"",(U26*6+V26*6+W26*4+X26*3+Y26*3+Z26*3)/3) | I26: =IF(COUNT(K26:AG26)=0,"",AB26*3+AC26*2+AD26*2+AE26*1) | J26: =IF(COUNT(K26:AG26)=0,"",(AF26*5+AG26*5)/3) | K26: 1 | L26: 1 | M26: 1 | N26: 1 | O26: Esse cara nem se deu o trabalho de mudar o que a ia fez já ta reprovado | P26: 1 | Q26: 1 | R26: 1 | S26: 1 | U26: 1 | V26: 1 | W26: 1 | X26: 1 | Y26: 1 | Z26: 1 | AB26: 0 | AC26: 1 | AD26: 0 | AE26: 1 | AF26: 3 | AG26: 2 | AI26: n falou nada do CCU
B27: i253464@dac.unicamp.br | C27: Isadora Kluge Dorigan | D27: Proc | E27: =IF(COUNT(K27:AG27)=0,"",ROUND((F27+G27+H27+I27+J27)/10,2)) | F27: =IF(COUNT(K27:AG27)=0,"",(K27*10+L27*8+M27*7+N27*5)/3) | G27: =IF(COUNT(K27:AG27)=0,"",(P27*8+Q27*7+R27*5+S27*5)/3) | H27: =IF(COUNT(K27:AG27)=0,"",(U27*6+V27*6+W27*4+X27*3+Y27*3+Z27*3)/3) | I27: =IF(COUNT(K27:AG27)=0,"",AB27*3+AC27*2+AD27*2+AE27*1) | J27: =IF(COUNT(K27:AG27)=0,"",(AF27*5+AG27*5)/3) | K27: 1 | L27: 3 | M27: 2 | N27: 2 | O27: Gravou vídeo também, falou bem, slide IA, acho | P27: 3 | Q27: 2 | R27: 2 | S27: 2 | U27: 3 | V27: 3 | W27: 2 | X27: 2 | Y27: 3 | AB27: 0 | AC27: 0 | AD27: 1 | AE27: 2 | AF27: 2 | AG27: 3 | AI27: 43% do GMAT. Senti que lia. Falou bem. Trajetória sólida.
B28: SEGUNDO AVALIADOR | C28: SEGUNDO AVALIADOR | E28: =IF(COUNT(K28:AG28)=0,"",ROUND((F28+G28+H28+I28+J28)/10,2)) | F28: =IF(COUNT(K28:AG28)=0,"",(K28*10+L28*8+M28*7+N28*5)/3) | G28: =IF(COUNT(K28:AG28)=0,"",(P28*8+Q28*7+R28*5+S28*5)/3) | H28: =IF(COUNT(K28:AG28)=0,"",(U28*6+V28*6+W28*4+X28*3+Y28*3+Z28*3)/3) | I28: =IF(COUNT(K28:AG28)=0,"",AB28*3+AC28*2+AD28*2+AE28*1) | J28: =IF(COUNT(K28:AG28)=0,"",(AF28*5+AG28*5)/3)
B29: g278083@dac.unicamp.br | C29: Gabrielle Cristofani do Rosario | D29: Fred | E29: =IF(COUNT(K29:AG29)=0,"",ROUND((F29+G29+H29+I29+J29)/10,2)) | F29: =IF(COUNT(K29:AG29)=0,"",(K29*10+L29*8+M29*7+N29*5)/3) | G29: =IF(COUNT(K29:AG29)=0,"",(P29*8+Q29*7+R29*5+S29*5)/3) | H29: =IF(COUNT(K29:AG29)=0,"",(U29*6+V29*6+W29*4+X29*3+Y29*3+Z29*3)/3) | I29: =IF(COUNT(K29:AG29)=0,"",AB29*3+AC29*2+AD29*2+AE29*1) | J29: =IF(COUNT(K29:AG29)=0,"",(AF29*5+AG29*5)/3) | K29: 2 | L29: 2 | M29: 2 | N29: 2 | P29: 3 | Q29: 2 | R29: 1 | S29: 1 | U29: 3 | V29: 3 | W29: 2 | X29: 2 | Y29: 2 | AB29: 1 | AC29: 1 | AD29: 0 | AE29: 3 | AF29: 3 | AG29: 2 | AI29: feagri 3° ano de curso, falou bem, mas foi generica em falar de consultoria
B30: b309603@dac.unicamp.br | C30: Bruno Heberth Oliveira Bastos | D30: Fred | E30: =IF(COUNT(K30:AG30)=0,"",ROUND((F30+G30+H30+I30+J30)/10,2)) | F30: =IF(COUNT(K30:AG30)=0,"",(K30*10+L30*8+M30*7+N30*5)/3) | G30: =IF(COUNT(K30:AG30)=0,"",(P30*8+Q30*7+R30*5+S30*5)/3) | H30: =IF(COUNT(K30:AG30)=0,"",(U30*6+V30*6+W30*4+X30*3+Y30*3+Z30*3)/3) | I30: =IF(COUNT(K30:AG30)=0,"",AB30*3+AC30*2+AD30*2+AE30*1) | J30: =IF(COUNT(K30:AG30)=0,"",(AF30*5+AG30*5)/3) | K30: 3 | L30: 2 | M30: 1 | N30: 1 | O30: Bagulho inteiro de ia | P30: 2 | Q30: 1 | R30: 1 | S30: 1 | U30: 3 | V30: 3 | W30: 2 | X30: 2 | Y30: 0 | AB30: 1 | AC30: 0 | AD30: 0 | AE30: 0 | AF30: 3 | AG30: 1
B31: j309764@dac.unicamp.br | C31: JOÃO PEDRO STAMA | D31: Fred | E31: =IF(COUNT(K31:AG31)=0,"",ROUND((F31+G31+H31+I31+J31)/10,2)) | F31: =IF(COUNT(K31:AG31)=0,"",(K31*10+L31*8+M31*7+N31*5)/3) | G31: =IF(COUNT(K31:AG31)=0,"",(P31*8+Q31*7+R31*5+S31*5)/3) | H31: =IF(COUNT(K31:AG31)=0,"",(U31*6+V31*6+W31*4+X31*3+Y31*3+Z31*3)/3) | I31: =IF(COUNT(K31:AG31)=0,"",AB31*3+AC31*2+AD31*2+AE31*1) | J31: =IF(COUNT(K31:AG31)=0,"",(AF31*5+AG31*5)/3) | AF31: 1 | AG31: 2 | AI31: colou no gmat
B32: r238449@dac.unicamp.br | C32: Rafael Ponciano Rodrigues dos Santos | D32: Fred | E32: =IF(COUNT(K32:AG32)=0,"",ROUND((F32+G32+H32+I32+J32)/10,2)) | F32: =IF(COUNT(K32:AG32)=0,"",(K32*10+L32*8+M32*7+N32*5)/3) | G32: =IF(COUNT(K32:AG32)=0,"",(P32*8+Q32*7+R32*5+S32*5)/3) | H32: =IF(COUNT(K32:AG32)=0,"",(U32*6+V32*6+W32*4+X32*3+Y32*3+Z32*3)/3) | I32: =IF(COUNT(K32:AG32)=0,"",AB32*3+AC32*2+AD32*2+AE32*1) | J32: =IF(COUNT(K32:AG32)=0,"",(AF32*5+AG32*5)/3) | K32: 3 | L32: 2 | M32: 2 | N32: 2 | O32: slides feitos por IA, mas no geral foi bem feito. falou bem no video e foi claro, o melhor dos que eu corrigi | P32: 3 | Q32: 3 | R32: 3 | S32: 3 | U32: 3 | V32: 3 | W32: 2 | X32: 3 | Y32: 2 | AB32: 1 | AC32: 1 | AD32: 1 | AE32: 2 | AF32: 3 | AG32: 2 | AI32: Falou bem no vídeo (levemente robótico) e mandou bem no gmat
B33: enzo.gag17@gmail.com | C33: Enzo Chofakian Gagliardi | D33: Ferro | E33: =IF(COUNT(K33:AG33)=0,"",ROUND((F33+G33+H33+I33+J33)/10,2)) | F33: =IF(COUNT(K33:AG33)=0,"",(K33*10+L33*8+M33*7+N33*5)/3) | G33: =IF(COUNT(K33:AG33)=0,"",(P33*8+Q33*7+R33*5+S33*5)/3) | H33: =IF(COUNT(K33:AG33)=0,"",(U33*6+V33*6+W33*4+X33*3+Y33*3+Z33*3)/3) | I33: =IF(COUNT(K33:AG33)=0,"",AB33*3+AC33*2+AD33*2+AE33*1) | J33: =IF(COUNT(K33:AG33)=0,"",(AF33*5+AG33*5)/3) | K33: 3 | L33: 2 | M33: 2 | N33: 2 | O33: Slide feito por IA | P33: 2 | Q33: 2 | R33: 2 | S33: 1 | T33: Excel feito por IA também | U33: 3 | V33: 3 | W33: 2 | X33: 1 | Y33: 2 | AB33: 1 | AC33: 1 | AD33: 0 | AE33: 3 | AF33: 2 | AG33: 2 | AI33: Acho q da pra passar, foi bem até
B34: e278588@dac.unicamp.br | C34: Enrico Tristão e Mello de Oliveira | D34: Matteo | E34: 8.83 | F34: 27.33 | G34: 25 | H34: 21 | I34: 10 | J34: 5 | K34: 3 | L34: 2 | M34: 3 | N34: 3 | O34: Recomendação no slide 2 com R$ 27,84 mi. O arco fecha lendo só os títulos. Arquivo enviado como Enrico hhh.pptx e numeração das seções trocada entre os slides 7 e 8. | P34: 3 | Q34: 3 | R34: 3 | S34: 3 | T34: Calculou de quanto o banco teria de cair para os armários empatarem: R$ 24 mil na Estação e R$ 56 mil em Noite Alta. Viu que o case não modela custo de coordenação e calculou que R$ 1,15 mil por posição zeraria a vantagem dos parceiros, virando gate do piloto. | U34: 3 | V34: 3 | W34: 3 | X34: 3 | Y34: 2 | AA34: Oito cenários conferem com o gabarito. Planilha com ROUNDUP, IF de complexidade e uma coluna de reconciliação que ele montou para conferir a própria economia. Cinco riscos com mitigação e KPI, sem prazo. | AB34: 1 | AC34: 1 | AD34: 1 | AE34: 3 | AF34: 2 | AG34: 1 | AI34: Tecnicamente a mais completa, e o que separa é o que ele faz depois da conta. Publicou o breakeven do banco nos quatro bairros e, melhor, percebeu que o case não modela custo de coordenação e calculou quanto de overhead zeraria a vantagem dos parceiros, virando gate do piloto. Os riscos são os melhores do grupo. Os reparos são de acabamento: nome do arquivo e numeração trocada. Na entrevista eu pergunto de onde vem o 23 no denominador do breakeven da Arena. O vídeo de entrega está na pasta do Drive, então E3 vale 1.
B35: e221509@dac.unicamp.br | C35: Eduardo Alves Henrique | D35: Proc | E35: =IF(COUNT(K35:AG35)=0,"",ROUND((F35+G35+H35+I35+J35)/10,2)) | F35: =IF(COUNT(K35:AG35)=0,"",(K35*10+L35*8+M35*7+N35*5)/3) | G35: =IF(COUNT(K35:AG35)=0,"",(P35*8+Q35*7+R35*5+S35*5)/3) | H35: =IF(COUNT(K35:AG35)=0,"",(U35*6+V35*6+W35*4+X35*3+Y35*3+Z35*3)/3) | I35: =IF(COUNT(K35:AG35)=0,"",AB35*3+AC35*2+AD35*2+AE35*1) | J35: =IF(COUNT(K35:AG35)=0,"",(AF35*5+AG35*5)/3) | K35: 2 | L35: 2 | M35: 1 | N35: 2 | O35: só gravou vídeo com contas a mao enviadas uma por uma e a apresentação nao ficou tao boa | P35: 2 | Q35: 3 | R35: 0 | S35: 1 | U35: 2 | V35: 3 | W35: 2 | X35: 2 | Y35: 1 | AB35: 0 | AC35: 1 | AD35: 1 | AE35: 1 | AF35: 2 | AG35: 1 | AI35: 80% no GMAT. Ao mesmo tempo fala que pode não se interessar pelo CCU, como pode se tornar liderança (???).
B36: l304532@dac.unicamp.br | C36: Leandra Cunha de Souza | D36: Proc | E36: =IF(COUNT(K36:AG36)=0,"",ROUND((F36+G36+H36+I36+J36)/10,2)) | F36: =IF(COUNT(K36:AG36)=0,"",(K36*10+L36*8+M36*7+N36*5)/3) | G36: =IF(COUNT(K36:AG36)=0,"",(P36*8+Q36*7+R36*5+S36*5)/3) | H36: =IF(COUNT(K36:AG36)=0,"",(U36*6+V36*6+W36*4+X36*3+Y36*3+Z36*3)/3) | I36: =IF(COUNT(K36:AG36)=0,"",AB36*3+AC36*2+AD36*2+AE36*1) | J36: =IF(COUNT(K36:AG36)=0,"",(AF36*5+AG36*5)/3) | K36: 2 | L36: 1 | M36: 1 | N36: 1 | O36: muito básico e entregou apenas uma apresentação em slides | P36: 2 | Q36: 1 | R36: 1 | S36: 1 | U36: 2 | V36: 2 | W36: 2 | X36: 2 | Y36: 1 | AB36: 0 | AC36: 1 | AD36: 0 | AE36: 1 | AF36: 2 | AG36: 2 | AI36: GMAT inconclusivo se ela colou. Nada de especial.
B37: v188630@dac.unicamp.br | C37: Vagner Ássimos Gomes Carlos Filho | D37: Proc | E37: =IF(COUNT(K37:AG37)=0,"",ROUND((F37+G37+H37+I37+J37)/10,2)) | F37: =IF(COUNT(K37:AG37)=0,"",(K37*10+L37*8+M37*7+N37*5)/3) | G37: =IF(COUNT(K37:AG37)=0,"",(P37*8+Q37*7+R37*5+S37*5)/3) | H37: =IF(COUNT(K37:AG37)=0,"",(U37*6+V37*6+W37*4+X37*3+Y37*3+Z37*3)/3) | I37: =IF(COUNT(K37:AG37)=0,"",AB37*3+AC37*2+AD37*2+AE37*1) | J37: =IF(COUNT(K37:AG37)=0,"",(AF37*5+AG37*5)/3) | K37: 2 | L37: 2 | M37: 1 | N37: 1 | O37: Totalmente feito por IA | P37: 2 | Q37: 3 | R37: 1 | S37: 2 | T37: meio controverso | U37: 2 | V37: 2 | W37: 2 | X37: 3 | Y37: 2 | AB37: 0 | AC37: 1 | AD37: 0 | AE37: 2 | AF37: 3 | AG37: 1 | AI37: Mais de 80% no GMAT. Falou quer CCU e ia nas palestras mas NÃO falou sobre ele, haviam mais 30s para falar.
B38: m277865@dac.unicamp.br | C38: Mariana Nunes Galvão Sant'Anna | D38: Matteo | E38: 8.67 | F38: 25 | G38: 23.33 | H38: 22 | I38: 8 | J38: 8.33 | K38: 3 | L38: 2 | M38: 2 | N38: 3 | O38: O deck abre pela recomendação, no slide 4, com o número. Três slides seguidos têm título e subtítulo idênticos. | P38: 3 | Q38: 3 | R38: 3 | S38: 2 | T38: Única a usar o mapa do Anexo A: contou as cinco fronteiras da Estação e virou critério. A matriz do slide 13 ordena as oito combinações certo por lucro. Usou a vantagem percentual por bairro para mostrar que o fosso entre os modelos é estreito. | U38: 3 | V38: 3 | W38: 3 | X38: 3 | Y38: 3 | AA38: Oito cenários conferem com o gabarito, bancos certos incluindo a Arena com 23. Piloto com prazo de três meses. Erra ao propor aproveitar as horas ociosas como ganho, quando o case diz que a demanda já está dada. | AB38: 1 | AC38: 1 | AD38: 0 | AE38: 3 | AF38: 2 | AG38: 3 | AI38: Entrega muito boa, e o que distingue é ter lido o que todos ignoraram. Foi a única a usar o mapa do anexo, contando as fronteiras da Estação e virando isso em critério. A matriz ordena as oito combinações certo e marca a incerteza de Noite Alta em vez de simular precisão. O erro que eu cobraria é propor aproveitar as horas ociosas como ganho, quando a demanda já está dada. Na entrevista eu pergunto como as horas vazias virariam lucro.
B39: a266739@dac.unicamp.br | C39: Aslan Rodrigues Maia | D39: Matteo | E39: 8.47 | F39: 27.33 | G39: 23.33 | H39: 18.67 | I39: 7 | J39: 8.33 | K39: 3 | L39: 2 | M39: 3 | N39: 3 | O39: Recomendação na pág. 2, uma frase com o número. Dois documentos fechados, com capa e rodapé numerado. Lendo só os títulos a história fecha. | P39: 3 | Q39: 3 | R39: 2 | S39: 3 | T39: Pág. 5 compara Estação e Centro em cinco métricas e a pág. 7 diz por escrito por que descartou o Centro. Provou que parceiros ganham sempre: o banco rateado dá R$ 1.750 por posição e o prêmio do parceiro nunca passa de R$ 1.400. | U39: 3 | V39: 3 | W39: 2 | X39: 2 | Y39: 2 | AA39: Oito cenários conferem com o gabarito. Bancos 60, 25, 23 e 45, com a Arena certa. Memória de cálculo no anexo, com a Estação feita por extenso. Riscos têm mitigação mas nenhum tem prazo. | AB39: 1 | AC39: 1 | AD39: 0 | AE39: 2 | AF39: 2 | AG39: 3 | AI39: Melhor entrega do grupo, e o que separa é ter provado por que parceiros ganham em vez de só reportar. O banco rateado dá R$ 1.750 por posição e o prêmio do parceiro vai de R$ 400 a R$ 1.400, então a escolha do modelo não depende do bairro. Achou a tensão do case e resolveu. Falta prazo nos riscos e não fez sensibilidade numérica. Na entrevista eu pergunto: se o banco custasse R$ 50.000, o que muda? Quem montou a seção 5.1 responde em um minuto.
B40: j278641@dac.unicamp.br | C40: João Gabriel de Oliveira Morcelli | D40: victor | E40: =IF(COUNT(K40:AG40)=0,"",ROUND((F40+G40+H40+I40+J40)/10,2)) | F40: =IF(COUNT(K40:AG40)=0,"",(K40*10+L40*8+M40*7+N40*5)/3) | G40: =IF(COUNT(K40:AG40)=0,"",(P40*8+Q40*7+R40*5+S40*5)/3) | H40: =IF(COUNT(K40:AG40)=0,"",(U40*6+V40*6+W40*4+X40*3+Y40*3+Z40*3)/3) | I40: =IF(COUNT(K40:AG40)=0,"",AB40*3+AC40*2+AD40*2+AE40*1) | J40: =IF(COUNT(K40:AG40)=0,"",(AF40*5+AG40*5)/3) | K40: 3 | L40: 2 | M40: 3 | N40: 2 | P40: 3 | Q40: 3 | R40: 2 | S40: 2 | U40: 2 | V40: 2 | W40: 3 | X40: 2 | Y40: 2 | AB40: 1 | AC40: 1 | AD40: 0 | AE40: 3 | AF40: 2 | AG40: 2 | AI40: motivos bons mas não falou do clube, tinha roteiro claramente no vídeo
B41: r278709@dac.unicamp.br | C41: Raphael Negrini Saggioro | D41: Matteo | E41: 3.67 | F41: 7.33 | G41: 4 | H41: 14 | I41: 3 | J41: 8.33 | K41: 1 | L41: 0 | M41: 1 | N41: 1 | O41: Não há recomendação. Oito páginas manuscritas digitalizadas e um arquivo chamado rascunho. Sem tabela e sem gráfico. | P41: 0 | Q41: 1 | R41: 0 | S41: 1 | T41: Comparou os dois modelos com lista de prós e contras, incluindo uma observação própria: nos pontos parceiros o cliente pode ter dificuldade de achar o serviço. Não comparou bairros e não escolheu nada. | U41: 3 | V41: 3 | W41: 0 | X41: 1 | Y41: 1 | AA41: Oito cenários conferem com o gabarito. Na Arena riscou o primeiro resultado e anotou arredondando para 23, ou seja, corrigiu sozinho na página. Das quatro tarefas do enunciado, só a rentabilidade foi entregue. | AB41: 1 | AC41: 0 | AD41: 0 | AE41: 0 | AF41: 3 | AG41: 2 | AI41: O cálculo está perfeito e é quase tudo o que existe. A Arena está não só certa como autocorrigida na página, com o valor riscado e o arredondamento anotado ao lado, que é a melhor prova de domínio que eu vi. Mas a entrega para aí: das quatro tarefas, uma foi entregue, e um dos arquivos se chama rascunho. O que há de qualitativo está no rascunho e é melhor do que parece. Na entrevista a pergunta é direta: qual bairro e qual modelo você recomenda?
B42: g278107@dac.unicamp.br | C42: Gustavo Daher Pereira | D42: victor | E42: =IF(COUNT(K42:AG42)=0,"",ROUND((F42+G42+H42+I42+J42)/10,2)) | F42: =IF(COUNT(K42:AG42)=0,"",(K42*10+L42*8+M42*7+N42*5)/3) | G42: =IF(COUNT(K42:AG42)=0,"",(P42*8+Q42*7+R42*5+S42*5)/3) | H42: =IF(COUNT(K42:AG42)=0,"",(U42*6+V42*6+W42*4+X42*3+Y42*3+Z42*3)/3) | I42: =IF(COUNT(K42:AG42)=0,"",AB42*3+AC42*2+AD42*2+AE42*1) | J42: =IF(COUNT(K42:AG42)=0,"",(AF42*5+AG42*5)/3) | AF42: 2 | AG42: 2 | AI42: Falou de palestras, achei prolixo e video demorado
B43: rickfilho2007@gmail.com | C43: Ricardo Augusto Schmitt Filho | D43: victor | E43: =IF(COUNT(K43:AG43)=0,"",ROUND((F43+G43+H43+I43+J43)/10,2)) | F43: =IF(COUNT(K43:AG43)=0,"",(K43*10+L43*8+M43*7+N43*5)/3) | G43: =IF(COUNT(K43:AG43)=0,"",(P43*8+Q43*7+R43*5+S43*5)/3) | H43: =IF(COUNT(K43:AG43)=0,"",(U43*6+V43*6+W43*4+X43*3+Y43*3+Z43*3)/3) | I43: =IF(COUNT(K43:AG43)=0,"",AB43*3+AC43*2+AD43*2+AE43*1) | J43: =IF(COUNT(K43:AG43)=0,"",(AF43*5+AG43*5)/3) | K43: 3 | L43: 3 | M43: 3 | N43: 3 | O43: Esse cara fez na moral e fez muito bem | P43: 3 | Q43: 3 | R43: 2 | S43: 3 | U43: 3 | V43: 3 | W43: 3 | X43: 3 | Y43: 3 | AB43: 1 | AC43: 1 | AD43: 1 | AE43: 3 | AF43: 2 | AG43: 2 | AI43: Fez u desafio foda mas n falou nada do ccu
B44: m306365@dac.unicamp.br | C44: Matheus Dias Freitas | D44: victor | E44: =IF(COUNT(K44:AG44)=0,"",ROUND((F44+G44+H44+I44+J44)/10,2)) | F44: =IF(COUNT(K44:AG44)=0,"",(K44*10+L44*8+M44*7+N44*5)/3) | G44: =IF(COUNT(K44:AG44)=0,"",(P44*8+Q44*7+R44*5+S44*5)/3) | H44: =IF(COUNT(K44:AG44)=0,"",(U44*6+V44*6+W44*4+X44*3+Y44*3+Z44*3)/3) | I44: =IF(COUNT(K44:AG44)=0,"",AB44*3+AC44*2+AD44*2+AE44*1) | J44: =IF(COUNT(K44:AG44)=0,"",(AF44*5+AG44*5)/3) | AF44: 2 | AG44: 1 | AI44: fez o video de touca, falou tudo muito genérico
B45: k267983@dac.unicamp.br | C45: Klaus Augusto Santos da Silva | D45: victor | E45: =IF(COUNT(K45:AG45)=0,"",ROUND((F45+G45+H45+I45+J45)/10,2)) | F45: =IF(COUNT(K45:AG45)=0,"",(K45*10+L45*8+M45*7+N45*5)/3) | G45: =IF(COUNT(K45:AG45)=0,"",(P45*8+Q45*7+R45*5+S45*5)/3) | H45: =IF(COUNT(K45:AG45)=0,"",(U45*6+V45*6+W45*4+X45*3+Y45*3+Z45*3)/3) | I45: =IF(COUNT(K45:AG45)=0,"",AB45*3+AC45*2+AD45*2+AE45*1) | J45: =IF(COUNT(K45:AG45)=0,"",(AF45*5+AG45*5)/3) | K45: 2 | L45: 1 | M45: 2 | N45: 1 | P45: 2 | Q45: 1 | R45: 1 | S45: 1 | U45: 1 | V45: 2 | W45: 2 | X45: 1 | Y45: 1 | AB45: 1 | AC45: 1 | AD45: 0 | AE45: 0 | AF45: 2 | AG45: 1 | AI45: Foi um dos unicos que falou q queria entrar pra ajudar o clube e falou q queria fazer amigo kkkkkkk, mas n achei q sabe muito de consultoria ou o q quer com o clube
B46: r302729@dac.unicamp.br | C46: Rafael Rodrigues Moreira | D46: Proc | E46: =IF(COUNT(K46:AG46)=0,"",ROUND((F46+G46+H46+I46+J46)/10,2)) | F46: =IF(COUNT(K46:AG46)=0,"",(K46*10+L46*8+M46*7+N46*5)/3) | G46: =IF(COUNT(K46:AG46)=0,"",(P46*8+Q46*7+R46*5+S46*5)/3) | H46: =IF(COUNT(K46:AG46)=0,"",(U46*6+V46*6+W46*4+X46*3+Y46*3+Z46*3)/3) | I46: =IF(COUNT(K46:AG46)=0,"",AB46*3+AC46*2+AD46*2+AE46*1) | J46: =IF(COUNT(K46:AG46)=0,"",(AF46*5+AG46*5)/3) | AF46: 0 | AG46: 1 | AI46: 60% no GMAT; falou bem do nosso instagram, falou pouco sobre ele. 1min30 de vídeo.
B47: c258388@dac.unicamp.br | C47: Caio Augusto Saab | D47: victor | E47: =IF(COUNT(K47:AG47)=0,"",ROUND((F47+G47+H47+I47+J47)/10,2)) | F47: =IF(COUNT(K47:AG47)=0,"",(K47*10+L47*8+M47*7+N47*5)/3) | G47: =IF(COUNT(K47:AG47)=0,"",(P47*8+Q47*7+R47*5+S47*5)/3) | H47: =IF(COUNT(K47:AG47)=0,"",(U47*6+V47*6+W47*4+X47*3+Y47*3+Z47*3)/3) | I47: =IF(COUNT(K47:AG47)=0,"",AB47*3+AC47*2+AD47*2+AE47*1) | J47: =IF(COUNT(K47:AG47)=0,"",(AF47*5+AG47*5)/3) | K47: 1 | L47: 1 | M47: 1 | N47: 0 | O47: só um documento com nenhuma análise aprofundada | P47: 2 | Q47: 0 | R47: 1 | S47: 0 | U47: 3 | V47: 3 | W47: 1 | X47: 0 | Y47: 0 | AB47: 0 | AC47: 0 | AD47: 0 | AE47: 0 | AF47: 2 | AG47: 1 | AI47: muito generico
B48: j260826@dac.unicamp.br | C48: José Vitor Dias Tutu | D48: Proc | E48: =IF(COUNT(K48:AG48)=0,"",ROUND((F48+G48+H48+I48+J48)/10,2)) | F48: =IF(COUNT(K48:AG48)=0,"",(K48*10+L48*8+M48*7+N48*5)/3) | G48: =IF(COUNT(K48:AG48)=0,"",(P48*8+Q48*7+R48*5+S48*5)/3) | H48: =IF(COUNT(K48:AG48)=0,"",(U48*6+V48*6+W48*4+X48*3+Y48*3+Z48*3)/3) | I48: =IF(COUNT(K48:AG48)=0,"",AB48*3+AC48*2+AD48*2+AE48*1) | J48: =IF(COUNT(K48:AG48)=0,"",(AF48*5+AG48*5)/3) | K48: 1 | L48: 1 | M48: 1 | N48: 1 | O48: Como ja dito pelo outro, ja está reprovado, ruim. | P48: 1 | Q48: 1 | R48: 1 | S48: 1 | U48: 1 | V48: 1 | W48: 1 | X48: 1 | Y48: 1 | AB48: 0 | AC48: 0 | AD48: 0 | AE48: 0 | AF48: 2 | AG48: 1 | AI48: Tentou traduzir a página e foi mal no GMAT. Vídeo ruim. Motivos ruins.
B49: i253464@dac.unicamp.br | C49: Isadora Kluge Dorigan | D49: Fred | E49: =IF(COUNT(K49:AG49)=0,"",ROUND((F49+G49+H49+I49+J49)/10,2)) | F49: =IF(COUNT(K49:AG49)=0,"",(K49*10+L49*8+M49*7+N49*5)/3) | G49: =IF(COUNT(K49:AG49)=0,"",(P49*8+Q49*7+R49*5+S49*5)/3) | H49: =IF(COUNT(K49:AG49)=0,"",(U49*6+V49*6+W49*4+X49*3+Y49*3+Z49*3)/3) | I49: =IF(COUNT(K49:AG49)=0,"",AB49*3+AC49*2+AD49*2+AE49*1) | J49: =IF(COUNT(K49:AG49)=0,"",(AF49*5+AG49*5)/3) | K49: 1 | L49: 3 | M49: 3 | N49: 3 | P49: 3 | Q49: 3 | R49: 2 | S49: 2 | U49: 3 | V49: 3 | W49: 2 | X49: 2 | Y49: 3 | AB49: 0 | AC49: 1 | AD49: 1 | AE49: 3 | AF49: 3 | AG49: 3 | AI49: Mandou bem no vídeo e vai ser a próxima ana bia + verena
B50: TERCEIRO AVALIADOR | C50: TERCEIRO AVALIADOR | E50: =IF(COUNT(K50:AG50)=0,"",ROUND((F50+G50+H50+I50+J50)/10,2)) | F50: =IF(COUNT(K50:AG50)=0,"",(K50*10+L50*8+M50*7+N50*5)/3) | G50: =IF(COUNT(K50:AG50)=0,"",(P50*8+Q50*7+R50*5+S50*5)/3) | H50: =IF(COUNT(K50:AG50)=0,"",(U50*6+V50*6+W50*4+X50*3+Y50*3+Z50*3)/3) | I50: =IF(COUNT(K50:AG50)=0,"",AB50*3+AC50*2+AD50*2+AE50*1) | J50: =IF(COUNT(K50:AG50)=0,"",(AF50*5+AG50*5)/3)
B51: g278083@dac.unicamp.br | C51: Gabrielle Cristofani do Rosario | D51: Matteo | E51: 7.45 | F51: 20 | G51: 19.33 | H51: 18.67 | I51: 9 | J51: 7.5 | K51: 2 | L51: 2 | M51: 2 | N51: 2 | O51: Recomendação só no slide 8 de 10. O slide 4 traz a complexidade do Centro e de Noite Alta invertida. O slide 9 cita um relatório escrito que não está na pasta. | P51: 3 | Q51: 2 | R51: 2 | S51: 2 | T51: Achou sozinha por que parceiros ganham: o banco rateado dá R$ 1.750 por posição e supera a economia de operação. Reconhece que o Centro tem margem maior e o coloca como segunda onda. | U51: 3 | V51: 3 | W51: 2 | X51: 2 | Y51: 2 | AA51: Resultados conferem com o gabarito. Memória de cálculo manuscrita, com o arredondamento escrito como 22,5 vira 23. As contas usam a complexidade certa, então o erro do slide 4 é de transcrição. Os riscos não têm mitigação que os enderece. | AB51: 1 | AC51: 1 | AD51: 1 | AE51: 2 | AF51: 2.5 | AG51: 2 | AI51: Entrega sólida, com a conta certa e memória de cálculo verificável à mão, inclusive o arredondamento da Arena. Achou sozinha a causa de os parceiros ganharem e tratou a tensão do case de frente. Três reparos, todos de execução: a complexidade invertida no slide 4, a recomendação chegando só no slide 8 e a promessa de um relatório que não está na pasta. Na entrevista eu pergunto qual é a complexidade certa do Centro, já que o slide e as contas divergem. O vídeo de entrega está na pasta do Drive, então E3 vale 1.
B52: b309603@dac.unicamp.br | C52: Bruno Heberth Oliveira Bastos | D52: Matteo | E52: 6.83 | F52: 21 | G52: 15 | H52: 17.67 | I52: 8 | J52: 6.67 | K52: 3 | L52: 2 | M52: 1 | N52: 2 | O52: Recomendação na pág. 1 com o número. Os títulos são rótulos de seção, então quem folheia não acha a resposta. Texto em primeira pessoa com ressalva a cada parágrafo. | P52: 2 | Q52: 2 | R52: 1 | S52: 2 | T52: Compara os oito cenários e descarta Arena e Noite Alta por escrito. Não quis generalizar a vantagem dos parceiros, disse que dependia dos custos do case, e a generalização era possível. | U52: 3 | V52: 3 | W52: 2 | X52: 2 | Y52: 1 | AA52: Oito cenários conferem com o gabarito. Melhor memória de cálculo do grupo: planilha com ROUNDUP e fórmulas ligadas entre abas. Riscos sem mitigação e sem prazo. | AB52: 1 | AC52: 1 | AD52: 0 | AE52: 3 | AF52: 3 | AG52: 1 | AI52: Entrega honesta, com o melhor artefato do grupo: planilha que funciona de verdade, com fórmulas ligadas entre abas. Gostei de ele separar o que a conta mostra do que a conta não mostra, e de apontar lacuna em vez de inventar estimativa. Onde deixou valor na mesa foi ao se recusar a generalizar a vantagem dos parceiros. O custo maior é de forma: títulos sem mensagem e texto com ressalva a cada parágrafo. Na entrevista eu peço a conta que ele não quis fazer: a partir de que custo de banco os armários ganham na Estação?
B53: j260826@dac.unicamp.br | C53: José Vitor Dias Tutu | D53: Matteo | E53: 8.43 | F53: 27.33 | G53: 23.33 | H53: 22 | I53: 5 | J53: 6.67 | K53: 3 | L53: 2 | M53: 3 | N53: 3 | O53: Recomendação na primeira página e no slide 2, já com o número. O slide 7 mostra seis dos oito cenários, faltam Noite Alta e Arena nos armários. Padrão visual igual nos dois arquivos. | P53: 3 | Q53: 3 | R53: 2 | S53: 3 | T53: Compara os quatro bairros nos dois modelos e justifica por escrito o descarte do Centro. Trouxe giro por posição, mas não fez sensibilidade nem payback. | U53: 3 | V53: 3 | W53: 3 | X53: 3 | Y53: 3 | AA53: Oito cenários conferem com o gabarito, Arena com 23 bancos. Memória de cálculo na pág. 2, com as cinco equações. Quatro riscos com mitigação e piloto de 30 dias. | AB53: 0 | AC53: 1 | AD53: 0 | AE53: 3 | AF53: 2.5 | AG53: 1.5 | AI53: REPROVADO POR USO DE IA. Entrega boa e bem conferida. Os oito cenários fecham, inclusive o arredondamento da Arena. O que me incomodou foi o critério do rollout mudar no meio: começa priorizando caixa, na fase 2 muda para margem e depois volta. Não fez sensibilidade. O deck inteiro é imagem e o relatório é HTML exportado, o que me fez desconfiar de IA. Na entrevista eu perguntaria por que Noite Alta vem antes da Arena se a margem da Arena é maior.
B54: enzo.gag17@gmail.com | C54: Enzo Chofakian Gagliardi | D54: Matteo | E54: 7.47 | F54: 23.33 | G54: 16.67 | H54: 20 | I54: 8 | J54: 6.67 | K54: 3 | L54: 2 | M54: 2 | N54: 2 | O54: Recomendação no título do slide 2, com o número. Os títulos são frases completas e a história fecha só com eles. Apêndice com os oito cenários abertos. | P54: 2 | Q54: 2 | R54: 2 | S54: 2 | T54: O slide 6 compara Estação e Centro com os números do trade-off e diz por que o Centro é o segundo. O slide 7 mede duas robustezas: 77% de queda até zerar o resultado e 9,3% até perder a liderança. | U54: 3 | V54: 3 | W54: 3 | X54: 1 | Y54: 3 | AA54: Oito cenários conferem com o gabarito. Planilha com bloco de conferências que tem de dar zero e validador de capacidade. Único a registrar por escrito que o banco é custo anual e não investimento. | AB54: 1 | AC54: 1 | AD54: 0 | AE54: 3 | AF54: 2 | AG54: 2 | AI54: Melhor nota, e o que decide é disciplina de modelagem somada à pergunta certa. A planilha tem autoconferência e validador de capacidade, e ele é o único que modela a sobra do arredondamento e que antecipa por escrito que o banco é custo anual. O slide 7 mede duas robustezas, e a segunda, os 9,3% até perder a liderança, é a pergunta que importa. Discordo de ele chamar isso de risco baixo, é margem estreita. Na entrevista eu pergunto por que a queda até zerar dá exatamente a margem operacional.
B55: e221509@dac.unicamp.br | C55: Eduardo Alves Henrique | D55: Matteo | E55: 6.55 | F55: 20 | G55: 16.67 | H55: 17.67 | I55: 7 | J55: 4.17 | K55: 2 | L55: 2 | M55: 2 | N55: 2 | O55: Decisão no slide 2, mas sem número na frase. O bairro Noite Alta aparece como Alta Noite em todas as tabelas. Dois slides são o anexo do próprio case colado. | P55: 2 | Q55: 2 | R55: 2 | S55: 2 | T55: Escolheu o Centro Histórico, que é o segundo maior lucro, e assumiu isso por escrito. O breakeven do slide 12 está certo nos quatro bairros, mas trata o banco como investimento de primeiro ano e o Anexo E diz que é custo anual. Não justificou o descarte da Estação. | U55: 3 | V55: 3 | W55: 2 | X55: 2 | Y55: 1 | AA55: Oito cenários conferem com o gabarito. Memória de cálculo em nove fotos de caderno, com a conta de Noite Alta passo a passo. Não há seção de riscos. | AB55: 1 | AC55: 1 | AD55: 0 | AE55: 2 | AF55: 2 | AG55: 0.5 | AI55: Conta impecável e decisão deliberadamente contra o número, o que torna interessante de corrigir. Escolheu o segundo maior lucro e assumiu, com argumento de complexidade e eficiência de capital. O problema é a premissa do breakeven: trata o banco como investimento e o Anexo E diz que é anual, e isso não aparece em nenhum slide. Não há riscos e o descarte da Estação não é justificado. Na entrevista eu pergunto por que o banco vale só no primeiro ano.
B56: l304532@dac.unicamp.br | C56: Leandra Cunha de Souza | D56: Matteo | E56: 5 | F56: 13.33 | G56: 13.33 | H56: 13.67 | I56: 3 | J56: 6.67 | K56: 2 | L56: 1 | M56: 1 | N56: 1 | O56: Recomendação no slide 11 de 13. Nome da empresa errado na capa, Bag Huby. Utilização de Noite Alta e Arena trocada no slide 3, contra o slide 12. Texto de template esquecido no slide 4. Com esse volume de erros não é arquivo que se manda ao cliente. | P56: 2 | Q56: 2 | R56: 1 | S56: 1 | T56: Enfrenta o contra-argumento por escrito: diz que a Estação tem o maior resultado e explica por que escolhe o Centro. O slide 12 justifica uma a uma as posições do ranking. Mas lê os 54% de utilização como prova de demanda consistente, e o case diz que a capacidade foi dimensionada para picos, então a leitura do indicador para em cima. | U56: 2 | V56: 2 | W56: 2 | X56: 2 | Y56: 1 | AA56: Oito cenários conferem com o gabarito e as margens fecham. As tabelas dos slides 6 a 9 decompõem cada linha de custo, mas a do slide 3 carrega a utilização trocada. Os dois riscos não têm mitigação. | AB56: 0 | AC56: 1 | AD56: 0 | AE56: 1 | AF56: 2 | AG56: 2 | AI56: REPROVADA. A análise está certa e a comunicação derruba a nota, o que é uma pena porque os dois problemas são baratos. Os oito cenários fecham e as tabelas de custo são um modelo de memória de cálculo. Ela também faz a coisa certa de enfrentar o contra-argumento em vez de esconder. O que custa é o acabamento: nome da empresa errado na capa, utilização trocada, texto de template esquecido, e a recomendação no slide 11 de 13. Na entrevista eu pergunto se a utilização da Arena é 31% ou 33%.
B57: v188630@dac.unicamp.br | C57: Vagner Ássimos Gomes Carlos Filho | D57: Matteo | E57: 6.62 | F57: 20 | G57: 19 | H57: 14.67 | I57: 5 | J57: 7.5 | K57: 2 | L57: 2 | M57: 2 | N57: 2 | O57: Recomendação no slide 9 de 13. Tem capa, estrutura e anexo com as premissas declaradas uma a uma. Três slides são parágrafo corrido. A numeração da expansão recomeça no slide 10. | P57: 2 | Q57: 3 | R57: 2 | S57: 2 | T57: Questiona a própria demanda do case: observa que quem vai a bar não carrega mala, o que põe em dúvida as 20 mil transações de Noite Alta. Recomenda parceiros e lista o que se perde com isso. | U57: 2 | V57: 2 | W57: 2 | X57: 2 | Y57: 2 | AA57: Oito cenários conferem com o gabarito, com a Arena em 23 bancos. Fórmulas nos slides 6 e 7 e premissas no anexo. Dois riscos, com as mitigações mais concretas do grupo, mas sem prazo. | AB57: 0 | AC57: 1 | AD57: 0 | AE57: 3 | AF57: 2.5 | AG57: 2 | AI57: Entrega madura, e o que distingue é fazer a pergunta que o case não faz. Questiona a própria demanda projetada, observando que quem vai a bar não carrega mala, o que derruba Noite Alta apesar do volume. E recomenda parceiros listando o que se perde com isso, que é sinal de maturidade. As mitigações são as mais concretas do grupo. Os reparos são a recomendação chegar no slide 9 e três slides de prosa corrida. Na entrevista eu pergunto o que ele faz com as 20 mil transações de Noite Alta.
B58: j278641@dac.unicamp.br | C58: João Gabriel de Oliveira Morcelli | D58: Matteo | E58: 8.68 | F58: 30 | G58: 21.67 | H58: 19.67 | I58: 8 | J58: 7.5 | K58: 3 | L58: 3 | M58: 3 | N58: 3 | O58: Recomendação na capa e no slide 2, com score, margem e resultado. Os títulos são frases que carregam a mensagem, inclusive o contra-argumento no slide 4. | P58: 3 | Q58: 3 | R58: 2 | S58: 2 | T58: Score com pesos publicados comparando as oito alternativas na mesma régua. Descobriu que o ranking se inverte no Ano 2 e montou um roadmap em duas fases em cima disso. | U58: 3 | V58: 3 | W58: 2 | X58: 3 | Y58: 2 | AA58: Oito cenários do Ano 1 conferem com o gabarito. Na Arena fixou 23 bancos à mão, contra a fórmula que daria 22,5. Do Ano 2 em diante remove o custo do banco, e o Anexo E diz que é anual, o que derruba a projeção de cinco anos. | AB58: 1 | AC58: 1 | AD58: 0 | AE58: 3 | AF58: 2.5 | AG58: 2 | AI58: Alto nível com um erro que atravessa metade da entrega. O score é o método mais transparente do grupo, com pesos publicados, e os action titles são exemplares. Mas do slide 8 em diante tudo se apoia em remover o custo do banco no Ano 2, e o Anexo E diz que é anual. Sob a premissa certa, cai o roadmap inteiro, que é a parte mais original. Na entrevista eu faço uma pergunta só: por que o custo do banco desaparece a partir do Ano 2?
B59: k267983@dac.unicamp.br | C59: Klaus Augusto Santos da Silva | D59: Matteo | E59: 4.8 | F59: 13.33 | G59: 11 | H59: 16.67 | I59: 2 | J59: 5 | K59: 2 | L59: 1 | M59: 1 | N59: 1 | O59: Relatório final bem estruturado, com sete seções e nota de procedência. Recomendação na seção 6 de 7. Enviou o rascunho junto, com separadores de hashtag. | P59: 2 | Q59: 1 | R59: 1 | S59: 1 | T59: Precifica o que abdica: R$ 3,39 mi por ano ao trocar rentabilidade por mitigação de risco. Mas soma os quatro bairros como se abrissem juntos, e na decisão real da Estação a abdicação é R$ 2,76 mi. Listou só os riscos da opção que descartou. | U59: 3 | V59: 3 | W59: 2 | X59: 1 | Y59: 1 | AA59: Oito cenários conferem com o gabarito, com a Arena marcada como cerca de 23 bancos. Memória de cálculo completa nas quatro tabelas de custo. Não há próximos passos. | AB59: 0 | AC59: 1 | AD59: 0 | AE59: 0 | AF59: 2 | AG59: 1 | AI59: A melhor ideia do grupo está na seção 7: em vez de justificar a escolha com adjetivos, ele precifica o que está abdicando. Isso transforma julgamento em algo que a diretoria aceita ou recusa com número na mão. Dois reparos de peso: somou os quatro bairros como se abrissem juntos, e listou só os riscos da opção que descartou. Faltam próximos passos. Na entrevista eu pergunto quanto ele abdica de fato se a decisão é só sobre a Estação.
B60: r302729@dac.unicamp.br | C60: Rafael Rodrigues Moreira | D60: Matteo | E60: 6.37 | F60: 17.67 | G60: 20.67 | H60: 14.33 | I60: 6 | J60: 5 | K60: 2 | L60: 2 | M60: 1 | N60: 2 | O60: Não escolhe bairro nem modelo. O índice promete uma seção de recomendação que não existe. Slides 7 e 8 repetem título e numeração, e o mesmo acontece em 10 e 11. | P60: 2 | Q60: 3 | R60: 2 | S60: 3 | T60: Quatro critérios declarados e todos operacionalizados, com regra de robustez em limiares numéricos. Classifica os bairros em origem, corredor e destino pela jornada do cliente. Mas a tabela dele mostra o Centro ganhando em três dos quatro critérios e a contradição fica sem resposta. | U60: 2 | V60: 3 | W60: 1 | X60: 2 | Y60: 1 | AA60: Sete cenários conferem com o gabarito. Tirou o tempo de permanência das malas da utilização, cerca de 7 horas na Estação, e o valor confere. Na Arena aplicou o custo por posição a 920 posições em vez de 900, contra o Anexo E, e usou 900 na coluna ao lado. | AB60: 0 | AC60: 1 | AD60: 1 | AE60: 2 | AF60: 1 | AG60: 2 | AI60: Tem a melhor análise e a pior conclusão, e isso foi difícil de pontuar. Tirou o tempo de permanência das malas da utilização, cerca de 7 horas na Estação, o que ninguém mais fez, e a regra de robustez dele é a mais rigorosa do grupo. E então não recomenda nada, com o índice prometendo uma seção que não existe. Pior: a tabela dele mostra o Centro ganhando em três dos quatro critérios e a contradição fica em aberto. Na entrevista eu pergunto como ele chegou nas 7 horas e qual bairro recomenda.
B61: c258388@dac.unicamp.br | C61: Caio Augusto Saab | D61: Matteo | E61: 3.45 | F61: 13.33 | G61: 6.33 | H61: 7 | I61: 2 | J61: 5.83 | K61: 2 | L61: 1 | M61: 1 | N61: 1 | O61: Recomendação só na última frase da pág. 5. Texto corrido, sem capa, sem numeração e sem uma única tabela em cinco páginas. | P61: 0 | Q61: 2 | R61: 0 | S61: 1 | T61: Contradiz o próprio critério: disse que a métrica é margem e escolheu armários com 85,7% em vez de parceiros com 90,7% no mesmo bairro. Descarta a Estação por complexidade alta depois de escrever que era moderada na pág. 1. Não fez riscos nem próximos passos. | U61: 2 | V61: 1 | W61: 0 | X61: 1 | Y61: 0 | AA61: Sete dos oito cenários conferem. Na Arena usou 22,5 bancos em vez de arredondar para 23. Os custos aparecem só como total, sem decomposição, então a memória de cálculo não fica visível. | AB61: 0 | AC61: 1 | AD61: 0 | AE61: 0 | AF61: 2 | AG61: 1.5 | AI61: O problema não é a conta, é a decisão. Sete dos oito cenários estão certos, mas a conclusão vai contra os números: disse que a métrica é margem e escolheu a pior opção pela própria régua. Tem duas contradições factuais sobre complexidade e margem da Arena. Faltam riscos e próximos passos, e não há uma tabela em cinco páginas. Na entrevista eu pergunto por que armários a 85,7% e não parceiros a 90,7% no mesmo bairro.
E62: =IF(COUNT(K62:AG62)=0,"",ROUND((F62+G62+H62+I62+J62)/10,2)) | F62: =IF(COUNT(K62:AG62)=0,"",(K62*10+L62*8+M62*7+N62*5)/3) | G62: =IF(COUNT(K62:AG62)=0,"",(P62*8+Q62*7+R62*5+S62*5)/3) | H62: =IF(COUNT(K62:AG62)=0,"",(U62*6+V62*6+W62*4+X62*3+Y62*3+Z62*3)/3) | I62: =IF(COUNT(K62:AG62)=0,"",AB62*3+AC62*2+AD62*2+AE62*1) | J62: =IF(COUNT(K62:AG62)=0,"",(AF62*5+AG62*5)/3)
E63: =IF(COUNT(K63:AG63)=0,"",ROUND((F63+G63+H63+I63+J63)/10,2)) | F63: =IF(COUNT(K63:AG63)=0,"",(K63*10+L63*8+M63*7+N63*5)/3) | G63: =IF(COUNT(K63:AG63)=0,"",(P63*8+Q63*7+R63*5+S63*5)/3) | H63: =IF(COUNT(K63:AG63)=0,"",(U63*6+V63*6+W63*4+X63*3+Y63*3+Z63*3)/3) | I63: =IF(COUNT(K63:AG63)=0,"",AB63*3+AC63*2+AD63*2+AE63*1) | J63: =IF(COUNT(K63:AG63)=0,"",(AF63*5+AG63*5)/3)
E64: =IF(COUNT(K64:AG64)=0,"",ROUND((F64+G64+H64+I64+J64)/10,2)) | F64: =IF(COUNT(K64:AG64)=0,"",(K64*10+L64*8+M64*7+N64*5)/3) | G64: =IF(COUNT(K64:AG64)=0,"",(P64*8+Q64*7+R64*5+S64*5)/3) | H64: =IF(COUNT(K64:AG64)=0,"",(U64*6+V64*6+W64*4+X64*3+Y64*3+Z64*3)/3) | I64: =IF(COUNT(K64:AG64)=0,"",AB64*3+AC64*2+AD64*2+AE64*1) | J64: =IF(COUNT(K64:AG64)=0,"",(AF64*5+AG64*5)/3)
E65: =IF(COUNT(K65:AG65)=0,"",ROUND((F65+G65+H65+I65+J65)/10,2)) | F65: =IF(COUNT(K65:AG65)=0,"",(K65*10+L65*8+M65*7+N65*5)/3) | G65: =IF(COUNT(K65:AG65)=0,"",(P65*8+Q65*7+R65*5+S65*5)/3) | H65: =IF(COUNT(K65:AG65)=0,"",(U65*6+V65*6+W65*4+X65*3+Y65*3+Z65*3)/3) | I65: =IF(COUNT(K65:AG65)=0,"",AB65*3+AC65*2+AD65*2+AE65*1) | J65: =IF(COUNT(K65:AG65)=0,"",(AF65*5+AG65*5)/3)
E66: =IF(COUNT(K66:AG66)=0,"",ROUND((F66+G66+H66+I66+J66)/10,2)) | F66: =IF(COUNT(K66:AG66)=0,"",(K66*10+L66*8+M66*7+N66*5)/3) | G66: =IF(COUNT(K66:AG66)=0,"",(P66*8+Q66*7+R66*5+S66*5)/3) | H66: =IF(COUNT(K66:AG66)=0,"",(U66*6+V66*6+W66*4+X66*3+Y66*3+Z66*3)/3) | I66: =IF(COUNT(K66:AG66)=0,"",AB66*3+AC66*2+AD66*2+AE66*1) | J66: =IF(COUNT(K66:AG66)=0,"",(AF66*5+AG66*5)/3)
E67: =IF(COUNT(K67:AG67)=0,"",ROUND((F67+G67+H67+I67+J67)/10,2)) | F67: =IF(COUNT(K67:AG67)=0,"",(K67*10+L67*8+M67*7+N67*5)/3) | G67: =IF(COUNT(K67:AG67)=0,"",(P67*8+Q67*7+R67*5+S67*5)/3) | H67: =IF(COUNT(K67:AG67)=0,"",(U67*6+V67*6+W67*4+X67*3+Y67*3+Z67*3)/3) | I67: =IF(COUNT(K67:AG67)=0,"",AB67*3+AC67*2+AD67*2+AE67*1) | J67: =IF(COUNT(K67:AG67)=0,"",(AF67*5+AG67*5)/3)
E68: =IF(COUNT(K68:AG68)=0,"",ROUND((F68+G68+H68+I68+J68)/10,2)) | F68: =IF(COUNT(K68:AG68)=0,"",(K68*10+L68*8+M68*7+N68*5)/3) | G68: =IF(COUNT(K68:AG68)=0,"",(P68*8+Q68*7+R68*5+S68*5)/3) | H68: =IF(COUNT(K68:AG68)=0,"",(U68*6+V68*6+W68*4+X68*3+Y68*3+Z68*3)/3) | I68: =IF(COUNT(K68:AG68)=0,"",AB68*3+AC68*2+AD68*2+AE68*1) | J68: =IF(COUNT(K68:AG68)=0,"",(AF68*5+AG68*5)/3)
E69: =IF(COUNT(K69:AG69)=0,"",ROUND((F69+G69+H69+I69+J69)/10,2)) | F69: =IF(COUNT(K69:AG69)=0,"",(K69*10+L69*8+M69*7+N69*5)/3) | G69: =IF(COUNT(K69:AG69)=0,"",(P69*8+Q69*7+R69*5+S69*5)/3) | H69: =IF(COUNT(K69:AG69)=0,"",(U69*6+V69*6+W69*4+X69*3+Y69*3+Z69*3)/3) | I69: =IF(COUNT(K69:AG69)=0,"",AB69*3+AC69*2+AD69*2+AE69*1) | J69: =IF(COUNT(K69:AG69)=0,"",(AF69*5+AG69*5)/3)
E70: =IF(COUNT(K70:AG70)=0,"",ROUND((F70+G70+H70+I70+J70)/10,2)) | F70: =IF(COUNT(K70:AG70)=0,"",(K70*10+L70*8+M70*7+N70*5)/3) | G70: =IF(COUNT(K70:AG70)=0,"",(P70*8+Q70*7+R70*5+S70*5)/3) | H70: =IF(COUNT(K70:AG70)=0,"",(U70*6+V70*6+W70*4+X70*3+Y70*3+Z70*3)/3) | I70: =IF(COUNT(K70:AG70)=0,"",AB70*3+AC70*2+AD70*2+AE70*1) | J70: =IF(COUNT(K70:AG70)=0,"",(AF70*5+AG70*5)/3)
E71: =IF(COUNT(K71:AG71)=0,"",ROUND((F71+G71+H71+I71+J71)/10,2)) | F71: =IF(COUNT(K71:AG71)=0,"",(K71*10+L71*8+M71*7+N71*5)/3) | G71: =IF(COUNT(K71:AG71)=0,"",(P71*8+Q71*7+R71*5+S71*5)/3) | H71: =IF(COUNT(K71:AG71)=0,"",(U71*6+V71*6+W71*4+X71*3+Y71*3+Z71*3)/3) | I71: =IF(COUNT(K71:AG71)=0,"",AB71*3+AC71*2+AD71*2+AE71*1) | J71: =IF(COUNT(K71:AG71)=0,"",(AF71*5+AG71*5)/3)
E72: =IF(COUNT(K72:AG72)=0,"",ROUND((F72+G72+H72+I72+J72)/10,2)) | F72: =IF(COUNT(K72:AG72)=0,"",(K72*10+L72*8+M72*7+N72*5)/3) | G72: =IF(COUNT(K72:AG72)=0,"",(P72*8+Q72*7+R72*5+S72*5)/3) | H72: =IF(COUNT(K72:AG72)=0,"",(U72*6+V72*6+W72*4+X72*3+Y72*3+Z72*3)/3) | I72: =IF(COUNT(K72:AG72)=0,"",AB72*3+AC72*2+AD72*2+AE72*1) | J72: =IF(COUNT(K72:AG72)=0,"",(AF72*5+AG72*5)/3)
E73: =IF(COUNT(K73:AG73)=0,"",ROUND((F73+G73+H73+I73+J73)/10,2)) | F73: =IF(COUNT(K73:AG73)=0,"",(K73*10+L73*8+M73*7+N73*5)/3) | G73: =IF(COUNT(K73:AG73)=0,"",(P73*8+Q73*7+R73*5+S73*5)/3) | H73: =IF(COUNT(K73:AG73)=0,"",(U73*6+V73*6+W73*4+X73*3+Y73*3+Z73*3)/3) | I73: =IF(COUNT(K73:AG73)=0,"",AB73*3+AC73*2+AD73*2+AE73*1) | J73: =IF(COUNT(K73:AG73)=0,"",(AF73*5+AG73*5)/3)
... E206: =IF(COUNT(K206:AG206)=0,"",ROUND((F206+G206+H206+I206+J206)/10,2)) | F206: =IF(COUNT(K206:AG206)=0,"",(K206*10+L206*8+M206*7+N206*5)/3) | G206: =IF(COUNT(K206:AG206)=0,"",(P206*8+Q206*7+R206*5+S206*5)/3) | H206: =IF(COUNT(K206:AG206)=0,"",(U206*6+V206*6+W206*4+X206*3+Y206*3+Z206*3)/3) | I206: =IF(COUNT(K206:AG206)=0,"",AB206*3+AC206*2+AD206*2+AE206*1) | J206: =IF(COUNT(K206:AG206)=0,"",(AF206*5+AG206*5)/3)

Sheet Quem corrige
A1: # | B1: Candidato | C1: Correção 1 | D1: Correção 2
A2: 1 | B2: Gabrielle Cristofani do Rosario | C2: Ferro | D2: Victor
A3: 2 | B3: Bruno Heberth Oliveira Bastos | C3: Proc | D3: Fred
A4: 3 | B4: Rafael Ponciano Rodrigues dos Santos | C4: Matteo | D4: Luis
A5: 4 | B5: Enzo Chofakian Gagliardi | C5: Ferro | D5: Proc
A6: 5 | B6: Enrico Tristão e Mello de Oliveira | C6: Victor | D6: Matteo
A7: 6 | B7: Eduardo Alves Henrique | C7: Fred | D7: Luis
A8: 7 | B8: Leandra Cunha de Souza | C8: Ferro | D8: Fred
A9: 8 | B9: Vagner Ássimos Gomes Carlos Filho | C9: Victor | D9: Luis
A10: 9 | B10: Mariana Nunes Galvão Sant'Anna | C10: Proc | D10: Matteo
A11: 10 | B11: Aslan Rodrigues Maia | C11: Ferro | D11: Matteo
A12: 11 | B12: João Gabriel de Oliveira Morcelli | C12: Victor | D12: Proc
A13: 12 | B13: Raphael Negrini Saggioro | C13: Fred | D13: Matteo
A14: 13 | B14: Gustavo Daher Pereira | C14: Ferro | D14: Luis | E14: Esse mano nem enviou o case
A15: 14 | B15: Ricardo Augusto Schmitt Filho | C15: Victor | D15: Fred
A16: 15 | B16: Klaus Augusto Santos da Silva | C16: Proc | D16: Luis
A17: 16 | B17: Rafael Rodrigues Moreira | C17: Ferro | D17: Victor
A18: 17 | B18: Caio Augusto Saab | C18: Proc | D18: Fred
A19: 18 | B19: José Vitor Dias Tutu | C19: Matteo | D19: Luis
A20: 19 | B20: Isadora Kluge Dorigan | C20: Ferro | D20: Proc

Sheet Consolidado
B2: CONSOLIDADO — cole os nomes na coluna B; o resto se calcula sozinho.
B3: =IF(COUNTA($B$5:$B$64)=0,"Cole os nomes dos candidatos na coluna B para começar.","Avaliações completas: "&COUNTIF($D$5:$D$64,">=2")&" de "&COUNTA($B$5:$B$64)&" candidatos ("&TEXT(COUNTIF($D$5:$D$64,">=2")/COUNTA($B$5:$B$64),"0%")&") • Ainda com 1 avaliador só: "&COUNTIF($D$5:$D$64,1)&" • Sem nenhuma nota: "&COUNTIF($D$5:$D$64,0))
A4: # | B4: Candidato(a) | C4: Nome | D4: Nº aval. | E4: NOTA FINAL | F4: Nota aval. 1 | G4: Nota aval. 2 | H4: Diverg. | I4: Alerta | J4: Flag | K4: Horas/sem | L4: Motivo da flag / o que perguntar na entrevista | M4: Ranking | N4: Entrevista: refez a conta? | O4: Decisão final
A5: =IF($B5="","",ROW()-4) | B5: g278083@dac.unicamp.br | C5: Gabrielle Cristofani do Rosario | D5: =IF($B5="","",COUNTIFS('Avaliação'!$C$7:$C$206,$B5,'Avaliação'!$E$7:$E$206,">=0")) | E5: =IF($B5="","",IFERROR(ROUND(AVERAGEIF('Avaliação'!$C$7:$C$206,$B5,'Avaliação'!$E$7:$E$206),2),"")) | F5: {=IF($B5="","",IFERROR(INDEX('Avaliação'!$E$7:$E$206,MATCH($B5,'Avaliação'!$C$7:$C$206,0)),""))} | G5: =IF($B5="","",IF($D5<>2,"",IF($F5="","",ROUND(SUMIF('Avaliação'!$C$7:$C$206,$B5,'Avaliação'!$E$7:$E$206)-$F5,2)))) | H5: =IF($B5="","",IF(OR($F5="",$G5=""),"",ROUND(ABS($F5-$G5),2))) | I5: =IF($B5="","",IF($D5<2,"⚠ falta 2º avaliador",IF($D5>2,"⚠ mais de 2 avaliações — conferir",IF(AND(ISNUMBER($H5),$H5>1),"⚠ divergência > 1,0 — média suspensa, calibrar","OK")))) | M5: =IF($E5="","",COUNTIF($E$5:$E$64,">"&$E5)+1) | N5: =IF($B5="","",IF(Entrevista!$H5="","",Entrevista!$H5)) | O5: =IF($B5="","",IF(Entrevista!$L5="","",Entrevista!$L5))
A6: =IF($B6="","",ROW()-4) | B6: b309603@dac.unicamp.br | C6: Bruno Heberth Oliveira Bastos | D6: =IF($B6="","",COUNTIFS('Avaliação'!$C$7:$C$206,$B6,'Avaliação'!$E$7:$E$206,">=0")) | E6: =IF($B6="","",IFERROR(ROUND(AVERAGEIF('Avaliação'!$C$7:$C$206,$B6,'Avaliação'!$E$7:$E$206),2),"")) | F6: {=IF($B6="","",IFERROR(INDEX('Avaliação'!$E$7:$E$206,MATCH($B6,'Avaliação'!$C$7:$C$206,0)),""))} | G6: =IF($B6="","",IF($D6<>2,"",IF($F6="","",ROUND(SUMIF('Avaliação'!$C$7:$C$206,$B6,'Avaliação'!$E$7:$E$206)-$F6,2)))) | H6: =IF($B6="","",IF(OR($F6="",$G6=""),"",ROUND(ABS($F6-$G6),2))) | I6: =IF($B6="","",IF($D6<2,"⚠ falta 2º avaliador",IF($D6>2,"⚠ mais de 2 avaliações — conferir",IF(AND(ISNUMBER($H6),$H6>1),"⚠ divergência > 1,0 — média suspensa, calibrar","OK")))) | M6: =IF($E6="","",COUNTIF($E$5:$E$64,">"&$E6)+1) | N6: =IF($B6="","",IF(Entrevista!$H6="","",Entrevista!$H6)) | O6: =IF($B6="","",IF(Entrevista!$L6="","",Entrevista!$L6))
A7: =IF($B7="","",ROW()-4) | B7: j309764@dac.unicamp.br | C7: João Pedro Mendes Stama | D7: =IF($B7="","",COUNTIFS('Avaliação'!$C$7:$C$206,$B7,'Avaliação'!$E$7:$E$206,">=0")) | E7: =IF($B7="","",IFERROR(ROUND(AVERAGEIF('Avaliação'!$C$7:$C$206,$B7,'Avaliação'!$E$7:$E$206),2),"")) | F7: {=IF($B7="","",IFERROR(INDEX('Avaliação'!$E$7:$E$206,MATCH($B7,'Avaliação'!$C$7:$C$206,0)),""))} | G7: =IF($B7="","",IF($D7<>2,"",IF($F7="","",ROUND(SUMIF('Avaliação'!$C$7:$C$206,$B7,'Avaliação'!$E$7:$E$206)-$F7,2)))) | H7: =IF($B7="","",IF(OR($F7="",$G7=""),"",ROUND(ABS($F7-$G7),2))) | I7: =IF($B7="","",IF($D7<2,"⚠ falta 2º avaliador",IF($D7>2,"⚠ mais de 2 avaliações — conferir",IF(AND(ISNUMBER($H7),$H7>1),"⚠ divergência > 1,0 — média suspensa, calibrar","OK")))) | M7: =IF($E7="","",COUNTIF($E$5:$E$64,">"&$E7)+1) | N7: =IF($B7="","",IF(Entrevista!$H7="","",Entrevista!$H7)) | O7: =IF($B7="","",IF(Entrevista!$L7="","",Entrevista!$L7))
A8: =IF($B8="","",ROW()-4) | B8: r238449@dac.unicamp.br | C8: Rafael Ponciano Rodrigues dos Santos | D8: =IF($B8="","",COUNTIFS('Avaliação'!$C$7:$C$206,$B8,'Avaliação'!$E$7:$E$206,">=0")) | E8: =IF($B8="","",IFERROR(ROUND(AVERAGEIF('Avaliação'!$C$7:$C$206,$B8,'Avaliação'!$E$7:$E$206),2),"")) | F8: {=IF($B8="","",IFERROR(INDEX('Avaliação'!$E$7:$E$206,MATCH($B8,'Avaliação'!$C$7:$C$206,0)),""))} | G8: =IF($B8="","",IF($D8<>2,"",IF($F8="","",ROUND(SUMIF('Avaliação'!$C$7:$C$206,$B8,'Avaliação'!$E$7:$E$206)-$F8,2)))) | H8: =IF($B8="","",IF(OR($F8="",$G8=""),"",ROUND(ABS($F8-$G8),2))) | I8: =IF($B8="","",IF($D8<2,"⚠ falta 2º avaliador",IF($D8>2,"⚠ mais de 2 avaliações — conferir",IF(AND(ISNUMBER($H8),$H8>1),"⚠ divergência > 1,0 — média suspensa, calibrar","OK")))) | M8: =IF($E8="","",COUNTIF($E$5:$E$64,">"&$E8)+1) | N8: =IF($B8="","",IF(Entrevista!$H8="","",Entrevista!$H8)) | O8: =IF($B8="","",IF(Entrevista!$L8="","",Entrevista!$L8))
A9: =IF($B9="","",ROW()-4) | B9: enzo.gag17@gmail.com | C9: Enzo Chofakian Gagliardi | D9: =IF($B9="","",COUNTIFS('Avaliação'!$C$7:$C$206,$B9,'Avaliação'!$E$7:$E$206,">=0")) | E9: =IF($B9="","",IFERROR(ROUND(AVERAGEIF('Avaliação'!$C$7:$C$206,$B9,'Avaliação'!$E$7:$E$206),2),"")) | F9: {=IF($B9="","",IFERROR(INDEX('Avaliação'!$E$7:$E$206,MATCH($B9,'Avaliação'!$C$7:$C$206,0)),""))} | G9: =IF($B9="","",IF($D9<>2,"",IF($F9="","",ROUND(SUMIF('Avaliação'!$C$7:$C$206,$B9,'Avaliação'!$E$7:$E$206)-$F9,2)))) | H9: =IF($B9="","",IF(OR($F9="",$G9=""),"",ROUND(ABS($F9-$G9),2))) | I9: =IF($B9="","",IF($D9<2,"⚠ falta 2º avaliador",IF($D9>2,"⚠ mais de 2 avaliações — conferir",IF(AND(ISNUMBER($H9),$H9>1),"⚠ divergência > 1,0 — média suspensa, calibrar","OK")))) | M9: =IF($E9="","",COUNTIF($E$5:$E$64,">"&$E9)+1) | N9: =IF($B9="","",IF(Entrevista!$H9="","",Entrevista!$H9)) | O9: =IF($B9="","",IF(Entrevista!$L9="","",Entrevista!$L9))
A10: =IF($B10="","",ROW()-4) | B10: e278588@dac.unicamp.br | C10: Enrico Tristão e Mello de Oliveira | D10: =IF($B10="","",COUNTIFS('Avaliação'!$C$7:$C$206,$B10,'Avaliação'!$E$7:$E$206,">=0")) | E10: =IF($B10="","",IFERROR(ROUND(AVERAGEIF('Avaliação'!$C$7:$C$206,$B10,'Avaliação'!$E$7:$E$206),2),"")) | F10: {=IF($B10="","",IFERROR(INDEX('Avaliação'!$E$7:$E$206,MATCH($B10,'Avaliação'!$C$7:$C$206,0)),""))} | G10: =IF($B10="","",IF($D10<>2,"",IF($F10="","",ROUND(SUMIF('Avaliação'!$C$7:$C$206,$B10,'Avaliação'!$E$7:$E$206)-$F10,2)))) | H10: =IF($B10="","",IF(OR($F10="",$G10=""),"",ROUND(ABS($F10-$G10),2))) | I10: =IF($B10="","",IF($D10<2,"⚠ falta 2º avaliador",IF($D10>2,"⚠ mais de 2 avaliações — conferir",IF(AND(ISNUMBER($H10),$H10>1),"⚠ divergência > 1,0 — média suspensa, calibrar","OK")))) | M10: =IF($E10="","",COUNTIF($E$5:$E$64,">"&$E10)+1) | N10: =IF($B10="","",IF(Entrevista!$H10="","",Entrevista!$H10)) | O10: =IF($B10="","",IF(Entrevista!$L10="","",Entrevista!$L10))
A11: =IF($B11="","",ROW()-4) | B11: e221509@dac.unicamp.br | C11: Eduardo Alves Henrique | D11: =IF($B11="","",COUNTIFS('Avaliação'!$C$7:$C$206,$B11,'Avaliação'!$E$7:$E$206,">=0")) | E11: =IF($B11="","",IFERROR(ROUND(AVERAGEIF('Avaliação'!$C$7:$C$206,$B11,'Avaliação'!$E$7:$E$206),2),"")) | F11: {=IF($B11="","",IFERROR(INDEX('Avaliação'!$E$7:$E$206,MATCH($B11,'Avaliação'!$C$7:$C$206,0)),""))} | G11: =IF($B11="","",IF($D11<>2,"",IF($F11="","",ROUND(SUMIF('Avaliação'!$C$7:$C$206,$B11,'Avaliação'!$E$7:$E$206)-$F11,2)))) | H11: =IF($B11="","",IF(OR($F11="",$G11=""),"",ROUND(ABS($F11-$G11),2))) | I11: =IF($B11="","",IF($D11<2,"⚠ falta 2º avaliador",IF($D11>2,"⚠ mais de 2 avaliações — conferir",IF(AND(ISNUMBER($H11),$H11>1),"⚠ divergência > 1,0 — média suspensa, calibrar","OK")))) | M11: =IF($E11="","",COUNTIF($E$5:$E$64,">"&$E11)+1) | N11: =IF($B11="","",IF(Entrevista!$H11="","",Entrevista!$H11)) | O11: =IF($B11="","",IF(Entrevista!$L11="","",Entrevista!$L11))
A12: =IF($B12="","",ROW()-4) | B12: l304532@dac.unicamp.br | C12: Leandra Cunha de Souza | D12: =IF($B12="","",COUNTIFS('Avaliação'!$C$7:$C$206,$B12,'Avaliação'!$E$7:$E$206,">=0")) | E12: =IF($B12="","",IFERROR(ROUND(AVERAGEIF('Avaliação'!$C$7:$C$206,$B12,'Avaliação'!$E$7:$E$206),2),"")) | F12: {=IF($B12="","",IFERROR(INDEX('Avaliação'!$E$7:$E$206,MATCH($B12,'Avaliação'!$C$7:$C$206,0)),""))} | G12: =IF($B12="","",IF($D12<>2,"",IF($F12="","",ROUND(SUMIF('Avaliação'!$C$7:$C$206,$B12,'Avaliação'!$E$7:$E$206)-$F12,2)))) | H12: =IF($B12="","",IF(OR($F12="",$G12=""),"",ROUND(ABS($F12-$G12),2))) | I12: =IF($B12="","",IF($D12<2,"⚠ falta 2º avaliador",IF($D12>2,"⚠ mais de 2 avaliações — conferir",IF(AND(ISNUMBER($H12),$H12>1),"⚠ divergência > 1,0 — média suspensa, calibrar","OK")))) | M12: =IF($E12="","",COUNTIF($E$5:$E$64,">"&$E12)+1) | N12: =IF($B12="","",IF(Entrevista!$H12="","",Entrevista!$H12)) | O12: =IF($B12="","",IF(Entrevista!$L12="","",Entrevista!$L12))
A13: =IF($B13="","",ROW()-4) | B13: v188630@dac.unicamp.br | C13: Vagner Ássimos Gomes Carlos Filho | D13: =IF($B13="","",COUNTIFS('Avaliação'!$C$7:$C$206,$B13,'Avaliação'!$E$7:$E$206,">=0")) | E13: =IF($B13="","",IFERROR(ROUND(AVERAGEIF('Avaliação'!$C$7:$C$206,$B13,'Avaliação'!$E$7:$E$206),2),"")) | F13: {=IF($B13="","",IFERROR(INDEX('Avaliação'!$E$7:$E$206,MATCH($B13,'Avaliação'!$C$7:$C$206,0)),""))} | G13: =IF($B13="","",IF($D13<>2,"",IF($F13="","",ROUND(SUMIF('Avaliação'!$C$7:$C$206,$B13,'Avaliação'!$E$7:$E$206)-$F13,2)))) | H13: =IF($B13="","",IF(OR($F13="",$G13=""),"",ROUND(ABS($F13-$G13),2))) | I13: =IF($B13="","",IF($D13<2,"⚠ falta 2º avaliador",IF($D13>2,"⚠ mais de 2 avaliações — conferir",IF(AND(ISNUMBER($H13),$H13>1),"⚠ divergência > 1,0 — média suspensa, calibrar","OK")))) | M13: =IF($E13="","",COUNTIF($E$5:$E$64,">"&$E13)+1) | N13: =IF($B13="","",IF(Entrevista!$H13="","",Entrevista!$H13)) | O13: =IF($B13="","",IF(Entrevista!$L13="","",Entrevista!$L13))
A14: =IF($B14="","",ROW()-4) | B14: m277865@dac.unicamp.br | C14: Mariana Nunes Galvão Sant'Anna | D14: =IF($B14="","",COUNTIFS('Avaliação'!$C$7:$C$206,$B14,'Avaliação'!$E$7:$E$206,">=0")) | E14: =IF($B14="","",IFERROR(ROUND(AVERAGEIF('Avaliação'!$C$7:$C$206,$B14,'Avaliação'!$E$7:$E$206),2),"")) | F14: {=IF($B14="","",IFERROR(INDEX('Avaliação'!$E$7:$E$206,MATCH($B14,'Avaliação'!$C$7:$C$206,0)),""))} | G14: =IF($B14="","",IF($D14<>2,"",IF($F14="","",ROUND(SUMIF('Avaliação'!$C$7:$C$206,$B14,'Avaliação'!$E$7:$E$206)-$F14,2)))) | H14: =IF($B14="","",IF(OR($F14="",$G14=""),"",ROUND(ABS($F14-$G14),2))) | I14: =IF($B14="","",IF($D14<2,"⚠ falta 2º avaliador",IF($D14>2,"⚠ mais de 2 avaliações — conferir",IF(AND(ISNUMBER($H14),$H14>1),"⚠ divergência > 1,0 — média suspensa, calibrar","OK")))) | M14: =IF($E14="","",COUNTIF($E$5:$E$64,">"&$E14)+1) | N14: =IF($B14="","",IF(Entrevista!$H14="","",Entrevista!$H14)) | O14: =IF($B14="","",IF(Entrevista!$L14="","",Entrevista!$L14))
A15: =IF($B15="","",ROW()-4) | B15: a266739@dac.unicamp.br | C15: Aslan Rodrigues Maia | D15: =IF($B15="","",COUNTIFS('Avaliação'!$C$7:$C$206,$B15,'Avaliação'!$E$7:$E$206,">=0")) | E15: =IF($B15="","",IFERROR(ROUND(AVERAGEIF('Avaliação'!$C$7:$C$206,$B15,'Avaliação'!$E$7:$E$206),2),"")) | F15: {=IF($B15="","",IFERROR(INDEX('Avaliação'!$E$7:$E$206,MATCH($B15,'Avaliação'!$C$7:$C$206,0)),""))} | G15: =IF($B15="","",IF($D15<>2,"",IF($F15="","",ROUND(SUMIF('Avaliação'!$C$7:$C$206,$B15,'Avaliação'!$E$7:$E$206)-$F15,2)))) | H15: =IF($B15="","",IF(OR($F15="",$G15=""),"",ROUND(ABS($F15-$G15),2))) | I15: =IF($B15="","",IF($D15<2,"⚠ falta 2º avaliador",IF($D15>2,"⚠ mais de 2 avaliações — conferir",IF(AND(ISNUMBER($H15),$H15>1),"⚠ divergência > 1,0 — média suspensa, calibrar","OK")))) | M15: =IF($E15="","",COUNTIF($E$5:$E$64,">"&$E15)+1) | N15: =IF($B15="","",IF(Entrevista!$H15="","",Entrevista!$H15)) | O15: =IF($B15="","",IF(Entrevista!$L15="","",Entrevista!$L15))
A16: =IF($B16="","",ROW()-4) | B16: j278641@dac.unicamp.br | C16: João Gabriel de Oliveira Morcelli | D16: =IF($B16="","",COUNTIFS('Avaliação'!$C$7:$C$206,$B16,'Avaliação'!$E$7:$E$206,">=0")) | E16: =IF($B16="","",IFERROR(ROUND(AVERAGEIF('Avaliação'!$C$7:$C$206,$B16,'Avaliação'!$E$7:$E$206),2),"")) | F16: {=IF($B16="","",IFERROR(INDEX('Avaliação'!$E$7:$E$206,MATCH($B16,'Avaliação'!$C$7:$C$206,0)),""))} | G16: =IF($B16="","",IF($D16<>2,"",IF($F16="","",ROUND(SUMIF('Avaliação'!$C$7:$C$206,$B16,'Avaliação'!$E$7:$E$206)-$F16,2)))) | H16: =IF($B16="","",IF(OR($F16="",$G16=""),"",ROUND(ABS($F16-$G16),2))) | I16: =IF($B16="","",IF($D16<2,"⚠ falta 2º avaliador",IF($D16>2,"⚠ mais de 2 avaliações — conferir",IF(AND(ISNUMBER($H16),$H16>1),"⚠ divergência > 1,0 — média suspensa, calibrar","OK")))) | M16: =IF($E16="","",COUNTIF($E$5:$E$64,">"&$E16)+1) | N16: =IF($B16="","",IF(Entrevista!$H16="","",Entrevista!$H16)) | O16: =IF($B16="","",IF(Entrevista!$L16="","",Entrevista!$L16))
... A25: =IF($B25="","",ROW()-4) | B25: i253464@dac.unicamp.br | C25: Isadora Kluge Dorigan | D25: =IF($B25="","",COUNTIFS('Avaliação'!$C$7:$C$206,$B25,'Avaliação'!$E$7:$E$206,">=0")) | E25: =IF($B25="","",IFERROR(ROUND(AVERAGEIF('Avaliação'!$C$7:$C$206,$B25,'Avaliação'!$E$7:$E$206),2),"")) | F25: {=IF($B25="","",IFERROR(INDEX('Avaliação'!$E$7:$E$206,MATCH($B25,'Avaliação'!$C$7:$C$206,0)),""))} | G25: =IF($B25="","",IF($D25<>2,"",IF($F25="","",ROUND(SUMIF('Avaliação'!$C$7:$C$206,$B25,'Avaliação'!$E$7:$E$206)-$F25,2)))) | H25: =IF($B25="","",IF(OR($F25="",$G25=""),"",ROUND(ABS($F25-$G25),2))) | I25: =IF($B25="","",IF($D25<2,"⚠ falta 2º avaliador",IF($D25>2,"⚠ mais de 2 avaliações — conferir",IF(AND(ISNUMBER($H25),$H25>1),"⚠ divergência > 1,0 — média suspensa, calibrar","OK")))) | M25: =IF($E25="","",COUNTIF($E$5:$E$64,">"&$E25)+1) | N25: =IF($B25="","",IF(Entrevista!$H25="","",Entrevista!$H25)) | O25: =IF($B25="","",IF(Entrevista!$L25="","",Entrevista!$L25))
A26: =IF($B26="","",ROW()-4) | D26: =IF($B26="","",COUNTIFS('Avaliação'!$C$7:$C$206,$B26,'Avaliação'!$E$7:$E$206,">=0")) | E26: =IF($B26="","",IFERROR(ROUND(AVERAGEIF('Avaliação'!$C$7:$C$206,$B26,'Avaliação'!$E$7:$E$206),2),"")) | F26: {=IF($B26="","",IFERROR(INDEX('Avaliação'!$E$7:$E$206,MATCH($B26,'Avaliação'!$C$7:$C$206,0)),""))} | G26: =IF($B26="","",IF($D26<>2,"",IF($F26="","",ROUND(SUMIF('Avaliação'!$C$7:$C$206,$B26,'Avaliação'!$E$7:$E$206)-$F26,2)))) | H26: =IF($B26="","",IF(OR($F26="",$G26=""),"",ROUND(ABS($F26-$G26),2))) | I26: =IF($B26="","",IF($D26<2,"⚠ falta 2º avaliador",IF($D26>2,"⚠ mais de 2 avaliações — conferir",IF(AND(ISNUMBER($H26),$H26>1),"⚠ divergência > 1,0 — média suspensa, calibrar","OK")))) | M26: =IF($E26="","",COUNTIF($E$5:$E$64,">"&$E26)+1) | N26: =IF($B26="","",IF(Entrevista!$H26="","",Entrevista!$H26)) | O26: =IF($B26="","",IF(Entrevista!$L26="","",Entrevista!$L26))
A27: =IF($B27="","",ROW()-4) | D27: =IF($B27="","",COUNTIFS('Avaliação'!$C$7:$C$206,$B27,'Avaliação'!$E$7:$E$206,">=0")) | E27: =IF($B27="","",IFERROR(ROUND(AVERAGEIF('Avaliação'!$C$7:$C$206,$B27,'Avaliação'!$E$7:$E$206),2),"")) | F27: {=IF($B27="","",IFERROR(INDEX('Avaliação'!$E$7:$E$206,MATCH($B27,'Avaliação'!$C$7:$C$206,0)),""))} | G27: =IF($B27="","",IF($D27<>2,"",IF($F27="","",ROUND(SUMIF('Avaliação'!$C$7:$C$206,$B27,'Avaliação'!$E$7:$E$206)-$F27,2)))) | H27: =IF($B27="","",IF(OR($F27="",$G27=""),"",ROUND(ABS($F27-$G27),2))) | I27: =IF($B27="","",IF($D27<2,"⚠ falta 2º avaliador",IF($D27>2,"⚠ mais de 2 avaliações — conferir",IF(AND(ISNUMBER($H27),$H27>1),"⚠ divergência > 1,0 — média suspensa, calibrar","OK")))) | M27: =IF($E27="","",COUNTIF($E$5:$E$64,">"&$E27)+1) | N27: =IF($B27="","",IF(Entrevista!$H27="","",Entrevista!$H27)) | O27: =IF($B27="","",IF(Entrevista!$L27="","",Entrevista!$L27))
A28: =IF($B28="","",ROW()-4) | D28: =IF($B28="","",COUNTIFS('Avaliação'!$C$7:$C$206,$B28,'Avaliação'!$E$7:$E$206,">=0")) | E28: =IF($B28="","",IFERROR(ROUND(AVERAGEIF('Avaliação'!$C$7:$C$206,$B28,'Avaliação'!$E$7:$E$206),2),"")) | F28: {=IF($B28="","",IFERROR(INDEX('Avaliação'!$E$7:$E$206,MATCH($B28,'Avaliação'!$C$7:$C$206,0)),""))} | G28: =IF($B28="","",IF($D28<>2,"",IF($F28="","",ROUND(SUMIF('Avaliação'!$C$7:$C$206,$B28,'Avaliação'!$E$7:$E$206)-$F28,2)))) | H28: =IF($B28="","",IF(OR($F28="",$G28=""),"",ROUND(ABS($F28-$G28),2))) | I28: =IF($B28="","",IF($D28<2,"⚠ falta 2º avaliador",IF($D28>2,"⚠ mais de 2 avaliações — conferir",IF(AND(ISNUMBER($H28),$H28>1),"⚠ divergência > 1,0 — média suspensa, calibrar","OK")))) | M28: =IF($E28="","",COUNTIF($E$5:$E$64,">"&$E28)+1) | N28: =IF($B28="","",IF(Entrevista!$H28="","",Entrevista!$H28)) | O28: =IF($B28="","",IF(Entrevista!$L28="","",Entrevista!$L28))
A29: =IF($B29="","",ROW()-4) | D29: =IF($B29="","",COUNTIFS('Avaliação'!$C$7:$C$206,$B29,'Avaliação'!$E$7:$E$206,">=0")) | E29: =IF($B29="","",IFERROR(ROUND(AVERAGEIF('Avaliação'!$C$7:$C$206,$B29,'Avaliação'!$E$7:$E$206),2),"")) | F29: {=IF($B29="","",IFERROR(INDEX('Avaliação'!$E$7:$E$206,MATCH($B29,'Avaliação'!$C$7:$C$206,0)),""))} | G29: =IF($B29="","",IF($D29<>2,"",IF($F29="","",ROUND(SUMIF('Avaliação'!$C$7:$C$206,$B29,'Avaliação'!$E$7:$E$206)-$F29,2)))) | H29: =IF($B29="","",IF(OR($F29="",$G29=""),"",ROUND(ABS($F29-$G29),2))) | I29: =IF($B29="","",IF($D29<2,"⚠ falta 2º avaliador",IF($D29>2,"⚠ mais de 2 avaliações — conferir",IF(AND(ISNUMBER($H29),$H29>1),"⚠ divergência > 1,0 — média suspensa, calibrar","OK")))) | M29: =IF($E29="","",COUNTIF($E$5:$E$64,">"&$E29)+1) | N29: =IF($B29="","",IF(Entrevista!$H29="","",Entrevista!$H29)) | O29: =IF($B29="","",IF(Entrevista!$L29="","",Entrevista!$L29))
A30: =IF($B30="","",ROW()-4) | D30: =IF($B30="","",COUNTIFS('Avaliação'!$C$7:$C$206,$B30,'Avaliação'!$E$7:$E$206,">=0")) | E30: =IF($B30="","",IFERROR(ROUND(AVERAGEIF('Avaliação'!$C$7:$C$206,$B30,'Avaliação'!$E$7:$E$206),2),"")) | F30: {=IF($B30="","",IFERROR(INDEX('Avaliação'!$E$7:$E$206,MATCH($B30,'Avaliação'!$C$7:$C$206,0)),""))} | G30: =IF($B30="","",IF($D30<>2,"",IF($F30="","",ROUND(SUMIF('Avaliação'!$C$7:$C$206,$B30,'Avaliação'!$E$7:$E$206)-$F30,2)))) | H30: =IF($B30="","",IF(OR($F30="",$G30=""),"",ROUND(ABS($F30-$G30),2))) | I30: =IF($B30="","",IF($D30<2,"⚠ falta 2º avaliador",IF($D30>2,"⚠ mais de 2 avaliações — conferir",IF(AND(ISNUMBER($H30),$H30>1),"⚠ divergência > 1,0 — média suspensa, calibrar","OK")))) | M30: =IF($E30="","",COUNTIF($E$5:$E$64,">"&$E30)+1) | N30: =IF($B30="","",IF(Entrevista!$H30="","",Entrevista!$H30)) | O30: =IF($B30="","",IF(Entrevista!$L30="","",Entrevista!$L30))
A31: =IF($B31="","",ROW()-4) | D31: =IF($B31="","",COUNTIFS('Avaliação'!$C$7:$C$206,$B31,'Avaliação'!$E$7:$E$206,">=0")) | E31: =IF($B31="","",IFERROR(ROUND(AVERAGEIF('Avaliação'!$C$7:$C$206,$B31,'Avaliação'!$E$7:$E$206),2),"")) | F31: {=IF($B31="","",IFERROR(INDEX('Avaliação'!$E$7:$E$206,MATCH($B31,'Avaliação'!$C$7:$C$206,0)),""))} | G31: =IF($B31="","",IF($D31<>2,"",IF($F31="","",ROUND(SUMIF('Avaliação'!$C$7:$C$206,$B31,'Avaliação'!$E$7:$E$206)-$F31,2)))) | H31: =IF($B31="","",IF(OR($F31="",$G31=""),"",ROUND(ABS($F31-$G31),2))) | I31: =IF($B31="","",IF($D31<2,"⚠ falta 2º avaliador",IF($D31>2,"⚠ mais de 2 avaliações — conferir",IF(AND(ISNUMBER($H31),$H31>1),"⚠ divergência > 1,0 — média suspensa, calibrar","OK")))) | M31: =IF($E31="","",COUNTIF($E$5:$E$64,">"&$E31)+1) | N31: =IF($B31="","",IF(Entrevista!$H31="","",Entrevista!$H31)) | O31: =IF($B31="","",IF(Entrevista!$L31="","",Entrevista!$L31))
A32: =IF($B32="","",ROW()-4) | D32: =IF($B32="","",COUNTIFS('Avaliação'!$C$7:$C$206,$B32,'Avaliação'!$E$7:$E$206,">=0")) | E32: =IF($B32="","",IFERROR(ROUND(AVERAGEIF('Avaliação'!$C$7:$C$206,$B32,'Avaliação'!$E$7:$E$206),2),"")) | F32: {=IF($B32="","",IFERROR(INDEX('Avaliação'!$E$7:$E$206,MATCH($B32,'Avaliação'!$C$7:$C$206,0)),""))} | G32: =IF($B32="","",IF($D32<>2,"",IF($F32="","",ROUND(SUMIF('Avaliação'!$C$7:$C$206,$B32,'Avaliação'!$E$7:$E$206)-$F32,2)))) | H32: =IF($B32="","",IF(OR($F32="",$G32=""),"",ROUND(ABS($F32-$G32),2))) | I32: =IF($B32="","",IF($D32<2,"⚠ falta 2º avaliador",IF($D32>2,"⚠ mais de 2 avaliações — conferir",IF(AND(ISNUMBER($H32),$H32>1),"⚠ divergência > 1,0 — média suspensa, calibrar","OK")))) | M32: =IF($E32="","",COUNTIF($E$5:$E$64,">"&$E32)+1) | N32: =IF($B32="","",IF(Entrevista!$H32="","",Entrevista!$H32)) | O32: =IF($B32="","",IF(Entrevista!$L32="","",Entrevista!$L32))
A33: =IF($B33="","",ROW()-4) | D33: =IF($B33="","",COUNTIFS('Avaliação'!$C$7:$C$206,$B33,'Avaliação'!$E$7:$E$206,">=0")) | E33: =IF($B33="","",IFERROR(ROUND(AVERAGEIF('Avaliação'!$C$7:$C$206,$B33,'Avaliação'!$E$7:$E$206),2),"")) | F33: {=IF($B33="","",IFERROR(INDEX('Avaliação'!$E$7:$E$206,MATCH($B33,'Avaliação'!$C$7:$C$206,0)),""))} | G33: =IF($B33="","",IF($D33<>2,"",IF($F33="","",ROUND(SUMIF('Avaliação'!$C$7:$C$206,$B33,'Avaliação'!$E$7:$E$206)-$F33,2)))) | H33: =IF($B33="","",IF(OR($F33="",$G33=""),"",ROUND(ABS($F33-$G33),2))) | I33: =IF($B33="","",IF($D33<2,"⚠ falta 2º avaliador",IF($D33>2,"⚠ mais de 2 avaliações — conferir",IF(AND(ISNUMBER($H33),$H33>1),"⚠ divergência > 1,0 — média suspensa, calibrar","OK")))) | M33: =IF($E33="","",COUNTIF($E$5:$E$64,">"&$E33)+1) | N33: =IF($B33="","",IF(Entrevista!$H33="","",Entrevista!$H33)) | O33: =IF($B33="","",IF(Entrevista!$L33="","",Entrevista!$L33))
A34: =IF($B34="","",ROW()-4) | D34: =IF($B34="","",COUNTIFS('Avaliação'!$C$7:$C$206,$B34,'Avaliação'!$E$7:$E$206,">=0")) | E34: =IF($B34="","",IFERROR(ROUND(AVERAGEIF('Avaliação'!$C$7:$C$206,$B34,'Avaliação'!$E$7:$E$206),2),"")) | F34: {=IF($B34="","",IFERROR(INDEX('Avaliação'!$E$7:$E$206,MATCH($B34,'Avaliação'!$C$7:$C$206,0)),""))} | G34: =IF($B34="","",IF($D34<>2,"",IF($F34="","",ROUND(SUMIF('Avaliação'!$C$7:$C$206,$B34,'Avaliação'!$E$7:$E$206)-$F34,2)))) | H34: =IF($B34="","",IF(OR($F34="",$G34=""),"",ROUND(ABS($F34-$G34),2))) | I34: =IF($B34="","",IF($D34<2,"⚠ falta 2º avaliador",IF($D34>2,"⚠ mais de 2 avaliações — conferir",IF(AND(ISNUMBER($H34),$H34>1),"⚠ divergência > 1,0 — média suspensa, calibrar","OK")))) | M34: =IF($E34="","",COUNTIF($E$5:$E$64,">"&$E34)+1) | N34: =IF($B34="","",IF(Entrevista!$H34="","",Entrevista!$H34)) | O34: =IF($B34="","",IF(Entrevista!$L34="","",Entrevista!$L34))
A35: =IF($B35="","",ROW()-4) | D35: =IF($B35="","",COUNTIFS('Avaliação'!$C$7:$C$206,$B35,'Avaliação'!$E$7:$E$206,">=0")) | E35: =IF($B35="","",IFERROR(ROUND(AVERAGEIF('Avaliação'!$C$7:$C$206,$B35,'Avaliação'!$E$7:$E$206),2),"")) | F35: {=IF($B35="","",IFERROR(INDEX('Avaliação'!$E$7:$E$206,MATCH($B35,'Avaliação'!$C$7:$C$206,0)),""))} | G35: =IF($B35="","",IF($D35<>2,"",IF($F35="","",ROUND(SUMIF('Avaliação'!$C$7:$C$206,$B35,'Avaliação'!$E$7:$E$206)-$F35,2)))) | H35: =IF($B35="","",IF(OR($F35="",$G35=""),"",ROUND(ABS($F35-$G35),2))) | I35: =IF($B35="","",IF($D35<2,"⚠ falta 2º avaliador",IF($D35>2,"⚠ mais de 2 avaliações — conferir",IF(AND(ISNUMBER($H35),$H35>1),"⚠ divergência > 1,0 — média suspensa, calibrar","OK")))) | M35: =IF($E35="","",COUNTIF($E$5:$E$64,">"&$E35)+1) | N35: =IF($B35="","",IF(Entrevista!$H35="","",Entrevista!$H35)) | O35: =IF($B35="","",IF(Entrevista!$L35="","",Entrevista!$L35))
A36: =IF($B36="","",ROW()-4) | D36: =IF($B36="","",COUNTIFS('Avaliação'!$C$7:$C$206,$B36,'Avaliação'!$E$7:$E$206,">=0")) | E36: =IF($B36="","",IFERROR(ROUND(AVERAGEIF('Avaliação'!$C$7:$C$206,$B36,'Avaliação'!$E$7:$E$206),2),"")) | F36: {=IF($B36="","",IFERROR(INDEX('Avaliação'!$E$7:$E$206,MATCH($B36,'Avaliação'!$C$7:$C$206,0)),""))} | G36: =IF($B36="","",IF($D36<>2,"",IF($F36="","",ROUND(SUMIF('Avaliação'!$C$7:$C$206,$B36,'Avaliação'!$E$7:$E$206)-$F36,2)))) | H36: =IF($B36="","",IF(OR($F36="",$G36=""),"",ROUND(ABS($F36-$G36),2))) | I36: =IF($B36="","",IF($D36<2,"⚠ falta 2º avaliador",IF($D36>2,"⚠ mais de 2 avaliações — conferir",IF(AND(ISNUMBER($H36),$H36>1),"⚠ divergência > 1,0 — média suspensa, calibrar","OK")))) | M36: =IF($E36="","",COUNTIF($E$5:$E$64,">"&$E36)+1) | N36: =IF($B36="","",IF(Entrevista!$H36="","",Entrevista!$H36)) | O36: =IF($B36="","",IF(Entrevista!$L36="","",Entrevista!$L36))
A37: =IF($B37="","",ROW()-4) | D37: =IF($B37="","",COUNTIFS('Avaliação'!$C$7:$C$206,$B37,'Avaliação'!$E$7:$E$206,">=0")) | E37: =IF($B37="","",IFERROR(ROUND(AVERAGEIF('Avaliação'!$C$7:$C$206,$B37,'Avaliação'!$E$7:$E$206),2),"")) | F37: {=IF($B37="","",IFERROR(INDEX('Avaliação'!$E$7:$E$206,MATCH($B37,'Avaliação'!$C$7:$C$206,0)),""))} | G37: =IF($B37="","",IF($D37<>2,"",IF($F37="","",ROUND(SUMIF('Avaliação'!$C$7:$C$206,$B37,'Avaliação'!$E$7:$E$206)-$F37,2)))) | H37: =IF($B37="","",IF(OR($F37="",$G37=""),"",ROUND(ABS($F37-$G37),2))) | I37: =IF($B37="","",IF($D37<2,"⚠ falta 2º avaliador",IF($D37>2,"⚠ mais de 2 avaliações — conferir",IF(AND(ISNUMBER($H37),$H37>1),"⚠ divergência > 1,0 — média suspensa, calibrar","OK")))) | M37: =IF($E37="","",COUNTIF($E$5:$E$64,">"&$E37)+1) | N37: =IF($B37="","",IF(Entrevista!$H37="","",Entrevista!$H37)) | O37: =IF($B37="","",IF(Entrevista!$L37="","",Entrevista!$L37))
... A64: =IF($B64="","",ROW()-4) | D64: =IF($B64="","",COUNTIFS('Avaliação'!$C$7:$C$206,$B64,'Avaliação'!$E$7:$E$206,">=0")) | E64: =IF($B64="","",IFERROR(ROUND(AVERAGEIF('Avaliação'!$C$7:$C$206,$B64,'Avaliação'!$E$7:$E$206),2),"")) | F64: {=IF($B64="","",IFERROR(INDEX('Avaliação'!$E$7:$E$206,MATCH($B64,'Avaliação'!$C$7:$C$206,0)),""))} | G64: =IF($B64="","",IF($D64<>2,"",IF($F64="","",ROUND(SUMIF('Avaliação'!$C$7:$C$206,$B64,'Avaliação'!$E$7:$E$206)-$F64,2)))) | H64: =IF($B64="","",IF(OR($F64="",$G64=""),"",ROUND(ABS($F64-$G64),2))) | I64: =IF($B64="","",IF($D64<2,"⚠ falta 2º avaliador",IF($D64>2,"⚠ mais de 2 avaliações — conferir",IF(AND(ISNUMBER($H64),$H64>1),"⚠ divergência > 1,0 — média suspensa, calibrar","OK")))) | M64: =IF($E64="","",COUNTIF($E$5:$E$64,">"&$E64)+1) | N64: =IF($B64="","",IF(Entrevista!$H64="","",Entrevista!$H64)) | O64: =IF($B64="","",IF(Entrevista!$L64="","",Entrevista!$L64))
B66: NOTA FINAL = média das notas dos dois avaliadores (6,0 e 7,0 -> 6,50). Se a diferença passar de 1,0, a média fica suspensa: conversem e refaçam o critério que divergiu.
B67: FLAG: não soma nem subtrai ponto e nunca elimina. Ela (i) obriga uma pergunta específica na entrevista e (ii) só desempata entre candidatos a menos de 0,3 ponto um do outro.
B68: HORAS/SEM: o que o candidato declarou no formulário. Em 2025.2 a mediana foi 8h (de 4 a 40). Abaixo de 6h acende vermelho — é conversa de entrevista, não corte.
B69: ENTREVISTA: as duas últimas colunas vêm da aba Entrevista, não se digita aqui. 'Não OK' na checagem de propriedade é VETO — derruba independentemente da nota.
B70: NOTA AMARELA = provisória: veio de UM avaliador só. Ela entra no ranking normalmente, mas não é comparável com as médias de dois — carrega inteira a severidade de quem corrigiu (0,89 pt de amplitude entre avaliadores no PS 2026-1S). Não feche corte com amarelo na lista.

Sheet Entrevista
B2: ENTREVISTA — nesta versão NÃO pontua. Ela veta, desempata e registra.
B3: ⚠ A entrevista não é formalidade. Em 2025.2 ela cortou 10 dos 23 convocados (43%): o 3º colocado (8,15) foi cortado e o 20º (5,42) foi aprovado. Em 2026.1 não sobrou registro nenhum do que ela decidiu. Preencher esta aba é o mínimo para a próxima gestão saber o que aconteceu aqui.
A4: # | B4: Candidato(a) | C4: Nome | D4: Nota do case | E4: Flag | F4: Entrevistador(es) | G4: Data | H4: Refez a conta ao vivo? | I4: Qual conta foi pedida | J4: Pergunta da flag + resposta | K4: Observações da entrevista | L4: Decisão | M4: Motivo da decisão
A5: =IF($B5="","",ROW()-4) | D5: =IF($B5="","",Consolidado!$E5) | E5: =IF($B5="","",Consolidado!$J5)
A6: =IF($B6="","",ROW()-4) | D6: =IF($B6="","",Consolidado!$E6) | E6: =IF($B6="","",Consolidado!$J6)
A7: =IF($B7="","",ROW()-4) | D7: =IF($B7="","",Consolidado!$E7) | E7: =IF($B7="","",Consolidado!$J7)
A8: =IF($B8="","",ROW()-4) | D8: =IF($B8="","",Consolidado!$E8) | E8: =IF($B8="","",Consolidado!$J8)
A9: =IF($B9="","",ROW()-4) | D9: =IF($B9="","",Consolidado!$E9) | E9: =IF($B9="","",Consolidado!$J9)
A10: =IF($B10="","",ROW()-4) | D10: =IF($B10="","",Consolidado!$E10) | E10: =IF($B10="","",Consolidado!$J10)
A11: =IF($B11="","",ROW()-4) | D11: =IF($B11="","",Consolidado!$E11) | E11: =IF($B11="","",Consolidado!$J11)
A12: =IF($B12="","",ROW()-4) | B12: l304532@dac.unicamp.br | C12: Leandra Cunha de Souza | D12: =IF($B12="","",Consolidado!$E12) | E12: =IF($B12="","",Consolidado!$J12) | L12: Reprovada | M12: Reprovada. Nota abaixo do corte nas tres correcoes: victor 5,17, Proc 4,77 e Matteo 5,00, media 4,98. A conta do case esta certa, os oito cenarios conferem com o gabarito. O que derrubou foi comunicacao e acabamento: nome da empresa errado na capa, utilizacao trocada no slide 3 contra o slide 12, texto de template esquecido, recomendacao so no slide 11 de 13 e riscos sem mitigacao.
A13: =IF($B13="","",ROW()-4) | D13: =IF($B13="","",Consolidado!$E13) | E13: =IF($B13="","",Consolidado!$J13)
A14: =IF($B14="","",ROW()-4) | D14: =IF($B14="","",Consolidado!$E14) | E14: =IF($B14="","",Consolidado!$J14)
A15: =IF($B15="","",ROW()-4) | D15: =IF($B15="","",Consolidado!$E15) | E15: =IF($B15="","",Consolidado!$J15)
A16: =IF($B16="","",ROW()-4) | D16: =IF($B16="","",Consolidado!$E16) | E16: =IF($B16="","",Consolidado!$J16)
A17: =IF($B17="","",ROW()-4) | D17: =IF($B17="","",Consolidado!$E17) | E17: =IF($B17="","",Consolidado!$J17)
A18: =IF($B18="","",ROW()-4) | D18: =IF($B18="","",Consolidado!$E18) | E18: =IF($B18="","",Consolidado!$J18)
A19: =IF($B19="","",ROW()-4) | D19: =IF($B19="","",Consolidado!$E19) | E19: =IF($B19="","",Consolidado!$J19)
A20: =IF($B20="","",ROW()-4) | D20: =IF($B20="","",Consolidado!$E20) | E20: =IF($B20="","",Consolidado!$J20)
A21: =IF($B21="","",ROW()-4) | D21: =IF($B21="","",Consolidado!$E21) | E21: =IF($B21="","",Consolidado!$J21)
A22: =IF($B22="","",ROW()-4) | D22: =IF($B22="","",Consolidado!$E22) | E22: =IF($B22="","",Consolidado!$J22)
A23: =IF($B23="","",ROW()-4) | D23: =IF($B23="","",Consolidado!$E23) | E23: =IF($B23="","",Consolidado!$J23)
A24: =IF($B24="","",ROW()-4) | B24: j260826@dac.unicamp.br | C24: José Vitor Dias Tutu | D24: =IF($B24="","",Consolidado!$E24) | E24: =IF($B24="","",Consolidado!$J24) | L24: Reprovado | M24: Reprovado por uso de IA na entrega. Os tres avaliadores registraram o mesmo indicio: o deck inteiro e imagem, sem texto selecionavel, e o relatorio e um HTML exportado em PDF, com o nome do arquivo trazendo "McKinsey Style". A decisao e de desqualificacao e nao reflete a qualidade tecnica: os oito cenarios do case conferem com o gabarito, inclusive o arredondamento de 23 bancos na Arena.
A25: =IF($B25="","",ROW()-4) | D25: =IF($B25="","",Consolidado!$E25) | E25: =IF($B25="","",Consolidado!$J25)
A26: =IF($B26="","",ROW()-4) | B26: =IF(Consolidado!$B26="","",Consolidado!$B26) | D26: =IF($B26="","",Consolidado!$E26) | E26: =IF($B26="","",Consolidado!$J26)
A27: =IF($B27="","",ROW()-4) | B27: =IF(Consolidado!$B27="","",Consolidado!$B27) | D27: =IF($B27="","",Consolidado!$E27) | E27: =IF($B27="","",Consolidado!$J27)
A28: =IF($B28="","",ROW()-4) | B28: =IF(Consolidado!$B28="","",Consolidado!$B28) | D28: =IF($B28="","",Consolidado!$E28) | E28: =IF($B28="","",Consolidado!$J28)
A29: =IF($B29="","",ROW()-4) | B29: =IF(Consolidado!$B29="","",Consolidado!$B29) | D29: =IF($B29="","",Consolidado!$E29) | E29: =IF($B29="","",Consolidado!$J29)
A30: =IF($B30="","",ROW()-4) | B30: =IF(Consolidado!$B30="","",Consolidado!$B30) | D30: =IF($B30="","",Consolidado!$E30) | E30: =IF($B30="","",Consolidado!$J30)
A31: =IF($B31="","",ROW()-4) | B31: =IF(Consolidado!$B31="","",Consolidado!$B31) | D31: =IF($B31="","",Consolidado!$E31) | E31: =IF($B31="","",Consolidado!$J31)
A32: =IF($B32="","",ROW()-4) | B32: =IF(Consolidado!$B32="","",Consolidado!$B32) | D32: =IF($B32="","",Consolidado!$E32) | E32: =IF($B32="","",Consolidado!$J32)
A33: =IF($B33="","",ROW()-4) | B33: =IF(Consolidado!$B33="","",Consolidado!$B33) | D33: =IF($B33="","",Consolidado!$E33) | E33: =IF($B33="","",Consolidado!$J33)
A34: =IF($B34="","",ROW()-4) | B34: =IF(Consolidado!$B34="","",Consolidado!$B34) | D34: =IF($B34="","",Consolidado!$E34) | E34: =IF($B34="","",Consolidado!$J34)
A35: =IF($B35="","",ROW()-4) | B35: =IF(Consolidado!$B35="","",Consolidado!$B35) | D35: =IF($B35="","",Consolidado!$E35) | E35: =IF($B35="","",Consolidado!$J35)
A36: =IF($B36="","",ROW()-4) | B36: =IF(Consolidado!$B36="","",Consolidado!$B36) | D36: =IF($B36="","",Consolidado!$E36) | E36: =IF($B36="","",Consolidado!$J36)
A37: =IF($B37="","",ROW()-4) | B37: =IF(Consolidado!$B37="","",Consolidado!$B37) | D37: =IF($B37="","",Consolidado!$E37) | E37: =IF($B37="","",Consolidado!$J37)
... A64: =IF($B64="","",ROW()-4) | B64: =IF(Consolidado!$B64="","",Consolidado!$B64) | D64: =IF($B64="","",Consolidado!$E64) | E64: =IF($B64="","",Consolidado!$J64)
B67: COMO FAZER A CHECAGEM DE PROPRIEDADE: nos primeiros 10 minutos, peça que o candidato refaça UMA conta da própria entrega, ao vivo, com um parâmetro alterado (o combinado na aba Gabarito). Quem montou o modelo resolve em 3 minutos. Anote em H qual conta foi pedida.
B68: Isso substitui tentar 'detectar IA' na entrega — que é injusto de errar e impossível de provar. Aqui não se acusa ninguém: ou defende o próprio trabalho, ou não defende.
B69: A coluna Decisão volta sozinha para o Consolidado. Não digite a decisão nos dois lugares.

Sheet Gabarito
B2: GABARITO E MONTAGEM DO CASE — preencher DEPOIS que o case do semestre existir.
B4: Só o bloco de ACURÁCIA (A1–A6) depende do case. Comunicação, Raciocínio, Entrega e Vídeo já estão prontos e valem para qualquer case — a rubrica pode ser aprovada antes do case ficar pronto. Aqui você faz duas coisas: (1) confere se o case tem o que a rubrica precisa medir e (2) preenche os valores do gabarito.
B6: PARTE 1 — O QUE O CASE PRECISA TER (conferir ao montar)
C7: O que o case precisa conter | D7: Alimenta | E7: Status | F7: Por quê / como fazer
B8: ☐ | C8: Duas contas centrais com UMA resposta certa cada | D8: A1, A2 | E8: OK — A1 armários / A2 parceiros | F8: Tem que ser conferível em 30 segundos, sem discussão. Se dois avaliadores podem chegar a números diferentes, não serve para este bloco — mande para Raciocínio.
B9: ☐ | C9: DIFICULDADE CALIBRADA: acerto médio perto de 50% do teto | D9: A1, A2 | E9: Conferir na correção | F9: Em 2025.2 os itens de gabarito ficaram entre 41% e 62% do teto e o bloco discriminou (Spearman 0,89 com o ranking final). Em 2026.1 ficaram entre 72% e 82% e viraram ruído (0,64). Se na correção um item passar de ~75% de acerto médio, ele não está separando ninguém — por mais peso que tenha.
B10: ☐ | C10: Uma projeção ou plano com meta numérica declarada no enunciado | D10: A3 | E10: FALTA — sem projeção | F10: A meta precisa estar escrita no case (ex.: crescer X%, atingir Y de margem), senão não há contra o que conferir.
B11: ☐ | C11: Um caminho alternativo que o candidato consiga dimensionar | D11: A4 | E11: OK — 2º bairro / outro modelo | F11: Precisa existir dado suficiente no material para ele estimar o impacto. Sem isso, todo mundo fica no nível 2.
B12: ☐ | C12: Pergunta explícita de riscos e próximos passos | D12: A5 | E12: OK — passo 04 do desafio | F12: Já está na rubrica e serve para qualquer case. Só garanta que o enunciado peça.
B13: ☐ | C13: UMA INCONSISTÊNCIA PLANTADA de propósito | D13: A6 | E13: FALTA — nada plantado | F13: Ex.: a DRE não fecha por um valor, ou o número do enunciado contradiz a tabela anexa. É o item que a IA erra e o melhor discriminador do bloco. Não conte para os candidatos, obviamente.
B14: ☐ | C14: UMA PREMISSA DEIXADA EM ABERTO de propósito | D14: R1, A4 | E14: OK — capacidade por ponto | F14: Ex.: não informar o critério de rateio de um custo entre unidades. Não pontua sozinha: aparece na qualidade da recomendação. Como não existe resposta certa, a IA não ajuda.
B15: ☐ | C15: Entregáveis obrigatórios declarados no enunciado | D15: E1, E2, E3 | E15: FALTA — case não declara | F15: Escrever no case: planilha com a memória de cálculo, apresentação fechada e vídeo. Se não estiver pedido, não dá para pontuar como checklist.
B16: ☐ | C16: Um parâmetro escolhido para a checagem ao vivo | D16: Entrevista | E16: Definir — sugestão abaixo | F16: Defina agora qual número o candidato terá de refazer na entrevista com valor alterado. É a verificação de propriedade que o take-home não consegue dar.
B18: PARTE 2 — GABARITO (preencher com o case pronto)
B19: Item | C19: Pergunta do case / o que se espera | D19: Valor esperado | E19: Tolerância | F19: Observação
B20: A1 | C20: Resultado operacional anual dos 4 bairros — modelo ARMÁRIOS (R$ milhões/ano) | D20: Estação Central 25,08 · Centro Histórico 23,15 · Arena 13,87 · Noite Alta 18,57 | E20: ±0,01 mi | F20: Todos os insumos estão no case: espera-se valor exato. Sem memória de cálculo visível, o teto é 2 mesmo com o valor certo. Arena: 900÷40=22,5 → 23 bancos.
B21: A2 | C21: Resultado operacional anual dos 4 bairros — modelo PARCEIROS (R$ milhões/ano) | D21: Estação Central 27,84 · Centro Histórico 24,50 · Arena 14,94 · Noite Alta 19,20 | E21: ±0,01 mi | F21: Receita e custo-base são idênticos aos dos armários. A diferença mora só em bancos × operação.
B22: A3 | C22: Ganho líquido dos parceiros = economia de bancos − acréscimo de operação (R$ mi/ano) | D22: Estação Central 2,76 · Centro Histórico 1,35 · Arena 1,07 · Noite Alta 0,63 | E22: ±0,01 mi | F22: Não há meta declarada neste case. Confira contra a tabela do próprio candidato: o número da recomendação tem de estar lá.
B23: A4 | C23: Ordem de prioridade dos demais bairros, ou defesa do modelo de armários | D23: Centro Histórico como 2º: 24,50 mi, 3,34 abaixo da Estação Central, margem 90,7% contra 77,3%. Armários: aceitar se reconhecer o resultado menor e justificar 24h/autosserviço, sem inventar receita. | E23: — | F23: Não existe resposta única: serve para calibrar o que é 'quantificado'.
B24: A6 | C24: Premissas em aberto (substituem a inconsistência plantada, ausente neste case) | D24: (1) A utilização não entra na receita — o enunciado avisa no Anexo C e nas Premissas. (2) A capacidade por estabelecimento não é informada: 2.400 posições não significam 2.400 parceiros. | E24: — | F24: ARMADILHAS que zeram A6: 52 semanas; utilização aplicada à receita; custos anuais multiplicados por 50; bancos cobrados dos parceiros; 920 posições na Arena; comissão inventada; índice de complexidade trocado.
B25: — | C25: [descrever a PREMISSA deixada em aberto] | D25: Capacidade por ponto parceiro. Entra em R1 (recomendação) e A4 (alternativa), não pontua sozinha. | E25: — | F25: Não pontua sozinha: entra em R1 (recomendação) e A4 (alternativa).
B26: — | C26: [parâmetro da checagem ao vivo na entrevista] | D26: Subir a operação dos parceiros na Estação Central de R$ 2.000 para R$ 3.400 por posição. Resposta: 36,00 − 3,36 − 8,16 = 24,48 mi — a Estação Central cai abaixo do Centro Histórico (24,50) e a recomendação vira. | E26: — | F26: Escolhido de propósito no ponto de virada: quem decorou o resultado não percebe que a conclusão muda.
B28: PARTE 3 — AUTOCORREÇÃO (opcional, mas é onde mora o maior ganho)
B29: Se vocês pedirem os números-chave em campos obrigatórios do formulário de entrega, A1 e A2 se corrigem sozinhos.
B30: Fórmula de exemplo, com a resposta do candidato em X2 e o valor esperado de A1 em D19:
B32: Resultado: 12 dos 25 pontos de acurácia deixam de depender de quem corrigiu, e a conferência cai para segundos.
B33: Atenção: o nível 3 exige memória de cálculo visível. A fórmula dá o teto; quem confere rebaixa para 2 se o Excel não veio.

Sheet Comentários
B2: COMENTÁRIOS — resuma o que achou da entrega (mesma estrutura da planilha antiga)
B4: # | C4: Candidato(a) | D4: Nome | E4: Avaliador | F4: Comentários | G4: Aprovaria?
B5: =IF($C5="","",ROW()-4) | C5: g278083@dac.unicamp.br | D5: Gabrielle Cristofani do Rosario | E5: Matteo | F5: Entrega sólida, com a conta certa e memória de cálculo verificável à mão, inclusive o arredondamento da Arena. Achou sozinha a causa de os parceiros ganharem e tratou a tensão do case de frente. Três reparos, todos de execução: a complexidade invertida no slide 4, a recomendação chegando só no slide 8 e a promessa de um relatório que não está na pasta. Na entrevista eu pergunto qual é a complexidade certa do Centro, já que o slide e as contas divergem. O vídeo de entrega está na pasta do Drive, então E3 vale 1.
B6: =IF($C6="","",ROW()-4) | C6: b309603@dac.unicamp.br | D6: Bruno Heberth Oliveira Bastos | E6: Matteo | F6: Entrega honesta, com o melhor artefato do grupo: planilha que funciona de verdade, com fórmulas ligadas entre abas. Gostei de ele separar o que a conta mostra do que a conta não mostra, e de apontar lacuna em vez de inventar estimativa. Onde deixou valor na mesa foi ao se recusar a generalizar a vantagem dos parceiros. O custo maior é de forma: títulos sem mensagem e texto com ressalva a cada parágrafo. Na entrevista eu peço a conta que ele não quis fazer: a partir de que custo de banco os armários ganham na Estação?
B7: =IF($C7="","",ROW()-4) | C7: j309764@dac.unicamp.br | D7: João Pedro Mendes Stama
B8: =IF($C8="","",ROW()-4) | C8: r238449@dac.unicamp.br | D8: Rafael Ponciano Rodrigues dos Santos | E8: Matteo | F8: A entrega mais frustrante do grupo: a parte difícil está certa e a fácil não foi feita. Os oito cenários estão corretos à mão, aplicou os 3C's e projetou cinco anos. E fez a melhor observação qualitativa que eu vi, sobre a conexão de 1h30 não dar tempo de passear. E então não recomendou nada, sem bairro, sem modelo, sem riscos. Na entrevista a pergunta é a que falta: qual bairro e qual modelo você escolhe?
B9: =IF($C9="","",ROW()-4) | C9: enzo.gag17@gmail.com | D9: Enzo Chofakian Gagliardi | E9: Matteo | F9: Melhor nota, e o que decide é disciplina de modelagem somada à pergunta certa. A planilha tem autoconferência e validador de capacidade, e ele é o único que modela a sobra do arredondamento e que antecipa por escrito que o banco é custo anual. O slide 7 mede duas robustezas, e a segunda, os 9,3% até perder a liderança, é a pergunta que importa. Discordo de ele chamar isso de risco baixo, é margem estreita. Na entrevista eu pergunto por que a queda até zerar dá exatamente a margem operacional.
B10: =IF($C10="","",ROW()-4) | C10: e278588@dac.unicamp.br | D10: Enrico Tristão e Mello de Oliveira | E10: Matteo | F10: Tecnicamente a mais completa, e o que separa é o que ele faz depois da conta. Publicou o breakeven do banco nos quatro bairros e, melhor, percebeu que o case não modela custo de coordenação e calculou quanto de overhead zeraria a vantagem dos parceiros, virando gate do piloto. Os riscos são os melhores do grupo. Os reparos são de acabamento: nome do arquivo e numeração trocada. Na entrevista eu pergunto de onde vem o 23 no denominador do breakeven da Arena. O vídeo de entrega está na pasta do Drive, então E3 vale 1.
B11: =IF($C11="","",ROW()-4) | C11: e221509@dac.unicamp.br | D11: Eduardo Alves Henrique | E11: Matteo | F11: Conta impecável e decisão deliberadamente contra o número, o que torna interessante de corrigir. Escolheu o segundo maior lucro e assumiu, com argumento de complexidade e eficiência de capital. O problema é a premissa do breakeven: trata o banco como investimento e o Anexo E diz que é anual, e isso não aparece em nenhum slide. Não há riscos e o descarte da Estação não é justificado. Na entrevista eu pergunto por que o banco vale só no primeiro ano.
B12: =IF($C12="","",ROW()-4) | C12: l304532@dac.unicamp.br | D12: Leandra Cunha de Souza | E12: Matteo | F12: REPROVADA. A análise está certa e a comunicação derruba a nota, o que é uma pena porque os dois problemas são baratos. Os oito cenários fecham e as tabelas de custo são um modelo de memória de cálculo. Ela também faz a coisa certa de enfrentar o contra-argumento em vez de esconder. O que custa é o acabamento: nome da empresa errado na capa, utilização trocada, texto de template esquecido, e a recomendação no slide 11 de 13. Na entrevista eu pergunto se a utilização da Arena é 31% ou 33%. | G12: Não
B13: =IF($C13="","",ROW()-4) | C13: v188630@dac.unicamp.br | D13: Vagner Ássimos Gomes Carlos Filho | E13: Matteo | F13: Entrega madura, e o que distingue é fazer a pergunta que o case não faz. Questiona a própria demanda projetada, observando que quem vai a bar não carrega mala, o que derruba Noite Alta apesar do volume. E recomenda parceiros listando o que se perde com isso, que é sinal de maturidade. As mitigações são as mais concretas do grupo. Os reparos são a recomendação chegar no slide 9 e três slides de prosa corrida. Na entrevista eu pergunto o que ele faz com as 20 mil transações de Noite Alta.
B14: =IF($C14="","",ROW()-4) | C14: m277865@dac.unicamp.br | D14: Mariana Nunes Galvão Sant'Anna | E14: Matteo | F14: Entrega muito boa, e o que distingue é ter lido o que todos ignoraram. Foi a única a usar o mapa do anexo, contando as fronteiras da Estação e virando isso em critério. A matriz ordena as oito combinações certo e marca a incerteza de Noite Alta em vez de simular precisão. O erro que eu cobraria é propor aproveitar as horas ociosas como ganho, quando a demanda já está dada. Na entrevista eu pergunto como as horas vazias virariam lucro.
B15: =IF($C15="","",ROW()-4) | C15: a266739@dac.unicamp.br | D15: Aslan Rodrigues Maia | E15: Ferro | F15: TIrou 2/3 do Gmat, e falou um pouco travado no vídeo, mas foi bem (não é bixo) | G15: Passaria para ver o case
B16: =IF($C16="","",ROW()-4) | C16: j278641@dac.unicamp.br | D16: João Gabriel de Oliveira Morcelli | E16: Ferro | F16: Tirou 2/3 do Gmat tbm, e fez no final sem energia, cara foi resiliente, falou muito bem no vídeo | G16: Sim
B17: =IF($C17="","",ROW()-4) | C17: r278709@dac.unicamp.br | D17: Raphael Negrini Saggioro | E17: Ferro | F17: Foi bem no Gmat tbm, falou muito bem, e falou dos projetos do CCU, fez a pesquisa básica ali, mandou bem | G17: Sim
B18: =IF($C18="","",ROW()-4) | C18: g278107@dac.unicamp.br | D18: Gustavo Daher Pereira
B19: =IF($C19="","",ROW()-4) | C19: rickfilho2007@gmail.com | D19: Ricardo Augusto Schmitt Filho
B20: =IF($C20="","",ROW()-4) | C20: m306365@dac.unicamp.br | D20: Matheus Dias Freitas
B21: =IF($C21="","",ROW()-4) | C21: k267983@dac.unicamp.br | D21: Klaus Augusto Santos da Silva | E21: Matteo | F21: A melhor ideia do grupo está na seção 7: em vez de justificar a escolha com adjetivos, ele precifica o que está abdicando. Isso transforma julgamento em algo que a diretoria aceita ou recusa com número na mão. Dois reparos de peso: somou os quatro bairros como se abrissem juntos, e listou só os riscos da opção que descartou. Faltam próximos passos. Na entrevista eu pergunto quanto ele abdica de fato se a decisão é só sobre a Estação.
B22: =IF($C22="","",ROW()-4) | C22: r302729@dac.unicamp.br | D22: Rafael Rodrigues Moreira | E22: Matteo | F22: Tem a melhor análise e a pior conclusão, e isso foi difícil de pontuar. Tirou o tempo de permanência das malas da utilização, cerca de 7 horas na Estação, o que ninguém mais fez, e a regra de robustez dele é a mais rigorosa do grupo. E então não recomenda nada, com o índice prometendo uma seção que não existe. Pior: a tabela dele mostra o Centro ganhando em três dos quatro critérios e a contradição fica em aberto. Na entrevista eu pergunto como ele chegou nas 7 horas e qual bairro recomenda.
B23: =IF($C23="","",ROW()-4) | C23: c258388@dac.unicamp.br | D23: Caio Augusto Saab | E23: Matteo | F23: O problema não é a conta, é a decisão. Sete dos oito cenários estão certos, mas a conclusão vai contra os números: disse que a métrica é margem e escolheu a pior opção pela própria régua. Tem duas contradições factuais sobre complexidade e margem da Arena. Faltam riscos e próximos passos, e não há uma tabela em cinco páginas. Na entrevista eu pergunto por que armários a 85,7% e não parceiros a 90,7% no mesmo bairro.
B24: =IF($C24="","",ROW()-4) | C24: j260826@dac.unicamp.br | D24: José Vitor Dias Tutu | E24: Matteo | F24: REPROVADO POR USO DE IA. Entrega boa e bem conferida. Os oito cenários fecham, inclusive o arredondamento da Arena. O que me incomodou foi o critério do rollout mudar no meio: começa priorizando caixa, na fase 2 muda para margem e depois volta. Não fez sensibilidade. O deck inteiro é imagem e o relatório é HTML exportado, o que me fez desconfiar de IA. Na entrevista eu perguntaria por que Noite Alta vem antes da Arena se a margem da Arena é maior. | G24: Não
B25: =IF($C25="","",ROW()-4) | C25: i253464@dac.unicamp.br | D25: Isadora Kluge Dorigan
B26: =IF($C26="","",ROW()-4)
B27: =IF($C27="","",ROW()-4)
B28: =IF($C28="","",ROW()-4)
B29: =IF($C29="","",ROW()-4)
B30: =IF($C30="","",ROW()-4)
B31: =IF($C31="","",ROW()-4)
B32: =IF($C32="","",ROW()-4)
B33: =IF($C33="","",ROW()-4)
B34: =IF($C34="","",ROW()-4)
B35: =IF($C35="","",ROW()-4)
B36: =IF($C36="","",ROW()-4)
B37: =IF($C37="","",ROW()-4)
... B204: =IF($C204="","",ROW()-4)
