Workbook

Sheet Resumo
A1: BagHub | Decisão de lançamento em Porto Claro
A2: Objetivo: maior resultado operacional anual para sustentar a expansão.
A3: Bairro líder: | B3: Estação Central | D3: Modelo: | E3: Parceiros
A5: Resultado anual (R$) | B5: =MAX(E8:E11) -> 27840000
A7: Bairro | B7: Resultado armários | C7: Resultado parceiros | D7: Melhor modelo | E7: Melhor resultado | F7: Vantagem parceiros | G7: Ranking
A8: =Premissas!A12 -> Estação Central | B8: =Calculos!B28 -> 25080000 | C8: =Calculos!C28 -> 27840000 | D8: =IF(C8>B8,"Parceiros",IF(B8>C8,"Armários","Empate")) -> Parceiros | E8: =MAX(B8:C8) -> 27840000 | F8: =C8-B8 -> 2760000 | G8: =1+COUNTIFS($E$8:$E$11,">"&E8) -> 1
A9: =Premissas!A13 -> Centro Histórico | B9: =Calculos!D28 -> 23150000 | C9: =Calculos!E28 -> 24500000 | D9: =IF(C9>B9,"Parceiros",IF(B9>C9,"Armários","Empate")) -> Parceiros | E9: =MAX(B9:C9) -> 24500000 | F9: =C9-B9 -> 1350000 | G9: =1+COUNTIFS($E$8:$E$11,">"&E9) -> 2
A10: =Premissas!A14 -> Arena | B10: =Calculos!F28 -> 13870000 | C10: =Calculos!G28 -> 14940000 | D10: =IF(C10>B10,"Parceiros",IF(B10>C10,"Armários","Empate")) -> Parceiros | E10: =MAX(B10:C10) -> 14940000 | F10: =C10-B10 -> 1070000 | G10: =1+COUNTIFS($E$8:$E$11,">"&E10) -> 4
A11: =Premissas!A15 -> Noite Alta | B11: =Calculos!H28 -> 18570000 | C11: =Calculos!I28 -> 19200000 | D11: =IF(C11>B11,"Parceiros",IF(B11>C11,"Armários","Empate")) -> Parceiros | E11: =MAX(B11:C11) -> 19200000 | F11: =C11-B11 -> 630000 | G11: =1+COUNTIFS($E$8:$E$11,">"&E11) -> 3
A30: Indicadores para apoiar a decisão
A32: Indicador | B32: Estação + parceiros | C32: Centro + parceiros | D32: Diferença Estação - Centro
A33: Resultado anual (R$) | B33: =Calculos!C28 -> 27840000 | C33: =Calculos!E28 -> 24500000 | D33: =B33-C33 -> 3340000
A34: Margem operacional | B34: =Calculos!C29 -> 0.77333333 | C34: =Calculos!E29 -> 0.90740741 | D34: =(B34-C34)*100 -> -13.407407
A35: Resultado/posição/ano (R$) | B35: =Calculos!C32 -> 11600 | C35: =Calculos!E32 -> 24500 | D35: =B35-C35 -> -12900
A36: Custo/transação (R$) | B36: =Calculos!C31 -> 6.8 | C36: =Calculos!E31 -> 2.7777778 | D36: =B36-C36 -> 4.0222222
A37: Transações/semana no equilíbrio | B37: =Calculos!C33 -> 5440 | C37: =Calculos!E33 -> 1666.6667 | D37: =B37-C37 -> 3773.3333
A39: Queda da demanda da Estação que iguala seu resultado ao do Centro | D39: 0.0928
A40: Teste adicional: apenas a demanda da Estação cai; custos, capacidade e resultado do Centro ficam constantes.
A42: Conclusões da base original e implicações para o lançamento
A43: 1. Lançar na Estação Central com parceiros: maior resultado anual. Garantir cobertura nos horários das conexões.
A44: 2. Expandir ao Centro Histórico: segunda maior contribuição anual, maior margem e menor complexidade.
A45: 3. Noite Alta precede Arena. Parceiros geram R$ 630 mil a mais; armários 24h são alternativa se não houver cobertura noturna.
A46: 4. Parceiros vencem nos quatro bairros: a economia com bancos supera seu maior custo de operação.
A47: 5. Validar localização, horários e atendimento dos parceiros. Não alterar a demanda-base por limitações hipotéticas.
A48: 6. Acompanhar demanda, ocupação de pico, filas, incidentes e resultado por ponto antes de avançar.

Sheet Calculos
A1: BagHub | Rentabilidade anual por bairro e modelo
A2: Análise de oito possíveis cenários.
A3: Custos em valores positivos. Valores monetários em reais.
A4: Indicador | B4: Estação Central | C4: Estação Central | D4: Centro Histórico | E4: Centro Histórico | F4: Arena | G4: Arena | H4: Noite Alta | I4: Noite Alta
A5: Modelo | B5: Armários | C5: Parceiros | D5: Armários | E5: Parceiros | F5: Armários | G5: Parceiros | H5: Armários | I5: Parceiros
A6: Transações por semana | B6: =Premissas!B12 -> 24000 | C6: =Premissas!B12 -> 24000 | D6: =Premissas!B13 -> 18000 | E6: =Premissas!B13 -> 18000 | F6: =Premissas!B14 -> 12000 | G6: =Premissas!B14 -> 12000 | H6: =Premissas!B15 -> 20000 | I6: =Premissas!B15 -> 20000
A7: Semanas por ano | B7: =Premissas!$B$5 -> 50 | C7: =Premissas!$B$5 -> 50 | D7: =Premissas!$B$5 -> 50 | E7: =Premissas!$B$5 -> 50 | F7: =Premissas!$B$5 -> 50 | G7: =Premissas!$B$5 -> 50 | H7: =Premissas!$B$5 -> 50 | I7: =Premissas!$B$5 -> 50
A8: Tarifa por transação (R$) | B8: =Premissas!$B$4 -> 30 | C8: =Premissas!$B$4 -> 30 | D8: =Premissas!$B$4 -> 30 | E8: =Premissas!$B$4 -> 30 | F8: =Premissas!$B$4 -> 30 | G8: =Premissas!$B$4 -> 30 | H8: =Premissas!$B$4 -> 30 | I8: =Premissas!$B$4 -> 30
A9: Transações por ano | B9: =B6*B7 -> 1200000 | C9: =C6*C7 -> 1200000 | D9: =D6*D7 -> 900000 | E9: =E6*E7 -> 900000 | F9: =F6*F7 -> 600000 | G9: =G6*G7 -> 600000 | H9: =H6*H7 -> 1000000 | I9: =I6*I7 -> 1000000
A10: Receita anual (R$) | B10: =B9*B8 -> 36000000 | C10: =C9*C8 -> 36000000 | D10: =D9*D8 -> 27000000 | E10: =E9*E8 -> 27000000 | F10: =F9*F8 -> 18000000 | G10: =G9*G8 -> 18000000 | H10: =H9*H8 -> 30000000 | I10: =I9*I8 -> 30000000
A12: Posições necessárias | B12: =Premissas!C12 -> 2400 | C12: =Premissas!C12 -> 2400 | D12: =Premissas!C13 -> 1000 | E12: =Premissas!C13 -> 1000 | F12: =Premissas!C14 -> 900 | G12: =Premissas!C14 -> 900 | H12: =Premissas!C15 -> 1800 | I12: =Premissas!C15 -> 1800
A13: Utilização informada | B13: =Premissas!D12 -> 0.42 | C13: =Premissas!D12 -> 0.42 | D13: =Premissas!D13 -> 0.54 | E13: =Premissas!D13 -> 0.54 | F13: =Premissas!D14 -> 0.31 | G13: =Premissas!D14 -> 0.31 | H13: =Premissas!D15 -> 0.33 | I13: =Premissas!D15 -> 0.33
A14: Complexidade operacional | B14: =Premissas!E12 -> Moderada | C14: =Premissas!E12 -> Moderada | D14: =Premissas!E13 -> Baixa | E14: =Premissas!E13 -> Baixa | F14: =Premissas!E14 -> Moderada | G14: =Premissas!E14 -> Moderada | H14: =Premissas!E15 -> Alta | I14: =Premissas!E15 -> Alta
A15: Número de bancos | B15: =ROUNDUP(B12/Premissas!$B$6,0) -> 60 | C15: n.a. | D15: =ROUNDUP(D12/Premissas!$B$6,0) -> 25 | E15: n.a. | F15: =ROUNDUP(F12/Premissas!$B$6,0) -> 23 | G15: n.a. | H15: =ROUNDUP(H12/Premissas!$B$6,0) -> 45 | I15: n.a.
A16: Posições físicas disponíveis | B16: =B15*Premissas!$B$6 -> 2400 | C16: =C12 -> 2400 | D16: =D15*Premissas!$B$6 -> 1000 | E16: =E12 -> 1000 | F16: =F15*Premissas!$B$6 -> 920 | G16: =G12 -> 900 | H16: =H15*Premissas!$B$6 -> 1800 | I16: =I12 -> 1800
A17: Posições adicionais por arredondamento | B17: =B16-B12 -> 0 | C17: =C16-C12 -> 0 | D17: =D16-D12 -> 0 | E17: =E16-E12 -> 0 | F17: =F16-F12 -> 20 | G17: =G16-G12 -> 0 | H17: =H16-H12 -> 0 | I17: =I16-I12 -> 0
A19: Equipamento/seguro/manutenção por posição | B19: =Premissas!$B$8 -> 1400 | C19: =Premissas!$B$8 -> 1400 | D19: =Premissas!$B$8 -> 1400 | E19: =Premissas!$B$8 -> 1400 | F19: =Premissas!$B$8 -> 1400 | G19: =Premissas!$B$8 -> 1400 | H19: =Premissas!$B$8 -> 1400 | I19: =Premissas!$B$8 -> 1400
A20: Operação por posição (R$/ano) | B20: =VLOOKUP(B14,Premissas!$A$18:$C$20,2,FALSE) -> 1400 | C20: =VLOOKUP(C14,Premissas!$A$18:$C$20,3,FALSE) -> 2000 | D20: =VLOOKUP(D14,Premissas!$A$18:$C$20,2,FALSE) -> 700 | E20: =VLOOKUP(E14,Premissas!$A$18:$C$20,3,FALSE) -> 1100 | F20: =VLOOKUP(F14,Premissas!$A$18:$C$20,2,FALSE) -> 1400 | G20: =VLOOKUP(G14,Premissas!$A$18:$C$20,3,FALSE) -> 2000 | H20: =VLOOKUP(H14,Premissas!$A$18:$C$20,2,FALSE) -> 3200 | I20: =VLOOKUP(I14,Premissas!$A$18:$C$20,3,FALSE) -> 4600
A21: Custo por banco (R$/ano) | B21: =Premissas!$B$7 -> 70000 | C21: n.a. | D21: =Premissas!$B$7 -> 70000 | E21: n.a. | F21: =Premissas!$B$7 -> 70000 | G21: n.a. | H21: =Premissas!$B$7 -> 70000 | I21: n.a.
A23: Equipamento, seguro e manutenção (R$) | B23: =B12*B19 -> 3360000 | C23: =C12*C19 -> 3360000 | D23: =D12*D19 -> 1400000 | E23: =E12*E19 -> 1400000 | F23: =F12*F19 -> 1260000 | G23: =G12*G19 -> 1260000 | H23: =H12*H19 -> 2520000 | I23: =I12*I19 -> 2520000
A24: Operação (R$) | B24: =B12*B20 -> 3360000 | C24: =C12*C20 -> 4800000 | D24: =D12*D20 -> 700000 | E24: =E12*E20 -> 1100000 | F24: =F12*F20 -> 1260000 | G24: =G12*G20 -> 1800000 | H24: =H12*H20 -> 5760000 | I24: =I12*I20 -> 8280000
A25: Bancos de armários (R$) | B25: =B15*B21 -> 4200000 | C25: 0 | D25: =D15*D21 -> 1750000 | E25: 0 | F25: =F15*F21 -> 1610000 | G25: 0 | H25: =H15*H21 -> 3150000 | I25: 0
A26: Custos anuais totais (R$) | B26: =SUM(B23:B25) -> 10920000 | C26: =SUM(C23:C25) -> 8160000 | D26: =SUM(D23:D25) -> 3850000 | E26: =SUM(E23:E25) -> 2500000 | F26: =SUM(F23:F25) -> 4130000 | G26: =SUM(G23:G25) -> 3060000 | H26: =SUM(H23:H25) -> 11430000 | I26: =SUM(I23:I25) -> 10800000
A28: Resultado operacional anual (R$) | B28: =B10-B26 -> 25080000 | C28: =C10-C26 -> 27840000 | D28: =D10-D26 -> 23150000 | E28: =E10-E26 -> 24500000 | F28: =F10-F26 -> 13870000 | G28: =G10-G26 -> 14940000 | H28: =H10-H26 -> 18570000 | I28: =I10-I26 -> 19200000
A29: Margem operacional | B29: =B28/B10 -> 0.69666667 | C29: =C28/C10 -> 0.77333333 | D29: =D28/D10 -> 0.85740741 | E29: =E28/E10 -> 0.90740741 | F29: =F28/F10 -> 0.77055556 | G29: =G28/G10 -> 0.83 | H29: =H28/H10 -> 0.619 | I29: =I28/I10 -> 0.64
A31: Custo por transação (R$) | B31: =B26/B9 -> 9.1 | C31: =C26/C9 -> 6.8 | D31: =D26/D9 -> 4.2777778 | E31: =E26/E9 -> 2.7777778 | F31: =F26/F9 -> 6.8833333 | G31: =G26/G9 -> 5.1 | H31: =H26/H9 -> 11.43 | I31: =I26/I9 -> 10.8
A32: Resultado por posição/ano (R$) | B32: =B28/B12 -> 10450 | C32: =C28/C12 -> 11600 | D32: =D28/D12 -> 23150 | E32: =E28/E12 -> 24500 | F32: =F28/F12 -> 15411.111 | G32: =G28/G12 -> 16600 | H32: =H28/H12 -> 10316.667 | I32: =I28/I12 -> 10666.667
A33: Transações/semana no equilíbrio | B33: =B26/B8/B7 -> 7280 | C33: =C26/C8/C7 -> 5440 | D33: =D26/D8/D7 -> 2566.6667 | E33: =E26/E8/E7 -> 1666.6667 | F33: =F26/F8/F7 -> 2753.3333 | G33: =G26/G8/G7 -> 2040 | H33: =H26/H8/H7 -> 7620 | I33: =I26/I8/I7 -> 7200
A34: Demanda mínima / demanda projetada | B34: =B33/B6 -> 0.30333333 | C34: =C33/C6 -> 0.22666667 | D34: =D33/D6 -> 0.14259259 | E34: =E33/E6 -> 0.092592593 | F34: =F33/F6 -> 0.22944444 | G34: =G33/G6 -> 0.17 | H34: =H33/H6 -> 0.381 | I34: =I33/I6 -> 0.36
A35: Queda da demanda até resultado zero | B35: =1-B34 -> 0.69666667 | C35: =1-C34 -> 0.77333333 | D35: =1-D34 -> 0.85740741 | E35: =1-E34 -> 0.90740741 | F35: =1-F34 -> 0.77055556 | G35: =1-G34 -> 0.83 | H35: =1-H34 -> 0.619 | I35: =1-I34 -> 0.64
A37: Conferências: diferenças monetárias devem ser zero
A38: Receita menos custos menos resultado | B38: =B10-B26-B28 -> 0 | C38: =C10-C26-C28 -> 0 | D38: =D10-D26-D28 -> 0 | E38: =E10-E26-E28 -> 0 | F38: =F10-F26-F28 -> 0 | G38: =G10-G26-G28 -> 0 | H38: =H10-H26-H28 -> 0 | I38: =I10-I26-I28 -> 0
A39: Receita versus premissas originais | B39: =B10-Premissas!B12*Premissas!$B$5*Premissas!$B$4 -> 0 | C39: =C10-Premissas!B12*Premissas!$B$5*Premissas!$B$4 -> 0 | D39: =D10-Premissas!B13*Premissas!$B$5*Premissas!$B$4 -> 0 | E39: =E10-Premissas!B13*Premissas!$B$5*Premissas!$B$4 -> 0 | F39: =F10-Premissas!B14*Premissas!$B$5*Premissas!$B$4 -> 0 | G39: =G10-Premissas!B14*Premissas!$B$5*Premissas!$B$4 -> 0 | H39: =H10-Premissas!B15*Premissas!$B$5*Premissas!$B$4 -> 0 | I39: =I10-Premissas!B15*Premissas!$B$5*Premissas!$B$4 -> 0
A40: Posições físicas atendem à necessidade | B40: =IF(B16>=B12,"OK","REVER") -> OK | C40: =IF(C16>=C12,"OK","REVER") -> OK | D40: =IF(D16>=D12,"OK","REVER") -> OK | E40: =IF(E16>=E12,"OK","REVER") -> OK | F40: =IF(F16>=F12,"OK","REVER") -> OK | G40: =IF(G16>=G12,"OK","REVER") -> OK | H40: =IF(H16>=H12,"OK","REVER") -> OK | I40: =IF(I16>=I12,"OK","REVER") -> OK
A42: Equilíbrio: análise adicional c/ custos anuais da capacidade contratada mantidos cte.
A43: A queda admissível mede resultado zero, não a perda de liderança para outro bairro.

Sheet Bairros
A1: BagHub | Demanda, capacidade e implantação
A2: Indicador | B2: Estação Central | C2: Centro Histórico | D2: Arena | E2: Noite Alta
A3: Transações por semana | B3: =Premissas!B12 -> 24000 | C3: =Premissas!B13 -> 18000 | D3: =Premissas!B14 -> 12000 | E3: =Premissas!B15 -> 20000
A4: Posições necessárias | B4: =Premissas!C12 -> 2400 | C4: =Premissas!C13 -> 1000 | D4: =Premissas!C14 -> 900 | E4: =Premissas!C15 -> 1800
A5: Utilização | B5: =Premissas!D12 -> 0.42 | C5: =Premissas!D13 -> 0.54 | D5: =Premissas!D14 -> 0.31 | E5: =Premissas!D15 -> 0.33
A6: Transações/posição/semana | B6: =B3/B4 -> 10 | C6: =C3/C4 -> 18 | D6: =D3/D4 -> 13.333333 | E6: =E3/E4 -> 11.111111
A7: Transações/posição/dia (média) | B7: =B6/7 -> 1.4285714 | C7: =C6/7 -> 2.5714286 | D7: =D6/7 -> 1.9047619 | E7: =E6/7 -> 1.5873016
A8: Posições por 1.000 transações semanais | B8: =B4/B3*1000 -> 100 | C8: =C4/C3*1000 -> 55.555556 | D8: =D4/D3*1000 -> 75 | E8: =E4/E3*1000 -> 90
A9: Leitura dos bairros e hipóteses operacionais
A10: Âncora de demanda | B10: Terminal ferroviário e rodoviário. 110 mil embarques/dia são contexto de circulação. | C10: Hotéis, atrações e circulação turística. | D10: Estádio e centro de convenções. | E10: Bares e casas de show.
A11: Localização e conexões | B11: Área central no mapa, vizinha ao Centro Histórico. Distâncias e tempos não foram informados. | C11: Corredor turístico com a Orla, indicado no mapa. | D11: Polo de eventos distinto do corredor turístico. | E11: Bairro vizinho ao Centro Histórico no mapa.
A12: Picos e implicações | B12: Conexões podem concentrar chegadas e retiradas. Medir horários de maior movimento. | C12: Turismo pode gerar concentração entre check-out e saída da cidade. Hipótese a validar. | D12: Eventos concentram demanda em janelas curtas, com risco de filas simultâneas. | E12: Maior fluxo entre 19h e 2h. A média semanal não revela os picos noturnos.
A13: Complexidade | B13: =Premissas!E12 -> Moderada | C13: =Premissas!E13 -> Baixa | D13: =Premissas!E14 -> Moderada | E13: =Premissas!E15 -> Alta
A14: Condição para pontos parceiros | B14: Cobertura de horários compatível com as conexões, acesso com bagagem e controle de filas. | C14: Selecionar comércios próximos às atrações e verificar horários de retirada. | D14: Acesso compatível com restrições de eventos e equipe disponível antes e depois deles. | E14: Parceiros abertos até a retirada, identificação dos itens e suporte noturno.
A15: Critério de atratividade | B15: Maior demanda projetada e maior resultado absoluto. Exige a maior capacidade contratada. | C15: Maior utilização e giro por posição. Menor complexidade e maior margem no modelo parceiro. | D15: Menor demanda e menor utilização. Capacidade de pico não pode ser reduzida pela média. | E15: Segunda maior demanda e alta complexidade. Parceiros rendem R$ 630 mil a mais, menor vantagem entre bairros; armários 24h são alternativa se não houver cobertura noturna.
A17: Implantação e acompanhamento
A18: Próximo passo sugerido | B18: Mapear comércios próximos ao terminal, contratar capacidade e testar retirada em horários críticos. | C18: Prospectar pontos no corredor turístico e acompanhar o perfil de uso por horário. | D18: Cruzar a operação com o calendário de eventos e ensaiar recebimento e retirada em lote. | E18: Validar parceiros noturnos, segurança, suporte e regras claras para retirada.
A19: Indicadores a acompanhar | B19: Transações, ocupação de pico, fila, prazo de retirada, incidentes e resultado por ponto. | C19: Transações, ocupação de pico, fila, prazo de retirada, incidentes e resultado por ponto. | D19: Transações, ocupação de pico, fila, prazo de retirada, incidentes e resultado por ponto. | E19: Transações, ocupação de pico, fila, prazo de retirada, incidentes e resultado por ponto.
A21: Médias diárias usam 7 dias apenas como normalização; não representam picos ou horários efetivos.
A22: Análise qualitativa do caso. Horários específicos e efeitos de check-out são hipóteses a validar.
A23: Utilização baixa não indica capacidade dispensável: as posições foram dimensionadas para os picos.

Sheet Premissas
A1: BagHub | Premissas do case
A3: Premissa geral | B3: Valor | C3: Unidade
A4: Tarifa por transação | B4: 30 | C4: R$/item
A5: Semanas de operação no ano | B5: 50 | C5: semanas
A6: Posições por banco de armários | B6: 40 | C6: posições
A7: Custo anual por banco | B7: 70000 | C7: R$/banco/ano
A8: Equipamento, seguro e manutenção | B8: 1400 | C8: R$/posição/ano
A9: Embarques na Estação Central | B9: 110000 | C9: embarques/dia
A11: Bairro | B11: Transações/semana | C11: Posições necessárias | D11: Utilização | E11: Complexidade
A12: Estação Central | B12: 24000 | C12: 2400 | D12: 0.42 | E12: Moderada
A13: Centro Histórico | B13: 18000 | C13: 1000 | D13: 0.54 | E13: Baixa
A14: Arena | B14: 12000 | C14: 900 | D14: 0.31 | E14: Moderada
A15: Noite Alta | B15: 20000 | C15: 1800 | D15: 0.33 | E15: Alta
A17: Operação por posição/ano | B17: Armários | C17: Parceiros
A18: Baixa | B18: 700 | C18: 1100
A19: Moderada | B19: 1400 | C19: 2000
A20: Alta | B20: 3200 | C20: 4600
A22: Regras de cálculo e interpretação
A23: Receita = transações por semana x semanas de operação x tarifa. Não aplicar utilização.
A24: Todos os custos informados são anuais. O custo dos bancos não é tratado como CAPEX.
A25: Custos por posição usam as posições necessárias, mesmo com sobra física de armários.
A26: Bancos = posições necessárias / 40, arredondado para cima. Parceiros não têm bancos.
A27: Equipamento, seguro e manutenção de R$ 1.400 por posição se aplicam aos dois modelos.
A28: Resultado = receita menos custos diretos. Excluir impostos e despesas corporativas.
A29: Avaliar os bairros separadamente. Não somar cenários alternativos nem compartilhar capacidade.
A30: Preço e demanda são iguais nos dois modelos. A capacidade necessária é contratável.
A31: Licenças são padronizadas. Depósito e retirada ocorrem no mesmo ponto.
A32: Ponto de equilíbrio adicional mantém capacidade, tarifa e custos anuais constantes.
A33: As conclusões textuais descrevem a base original. Revise-as se alterar os dados.
A34: Azul: dados editáveis. Verde: vínculos entre abas. Preto: fórmulas na própria aba.
