Workbook

Sheet Rascunho
B3: comparação dos bairros | D3: demanda e capacidade | F3: rentabilidade
B4: criterio de atratividade | D4: volume de transações | F4: receita anula
B5: perfil do publico | D5: posições necessárias | F5: custo por categoria
B6: fontes de demanda | D6: utilização | F6: resultado operacional anual
B7: complexidade operacional | D7: infliencia de picos e ocasiões
Q11: M1: inteligente | U11: M2: parceiros
B12: fontes e demanda - densidade de circulação | F12: complexidade operacional | I12: demanda, capacidade, utilização | N12: obs: considera picos | Q12: O usuário reserva e abre o compartimento pelo celular. Cada banco tem 40 posições, com autosserviço e suporte remoto. | U12: Comércios verificados recebem e devolvem os itens em espaços reservados. A BagHub não instala bancos de armários.
B13: EC | C13: 4 | D13: terminais | F13: EC | G13: 2 | I13: bairro | J13: transações semanais | K13: receita | L13: posições necessarias | M13: utilização > perfil hrs ocupadas/disponíveis semana | Q13: 24h | U13: horário variável
B14: CH | C14: 4 | D14: hoteis | F14: CH | G14: 1 | I14: ec (conexões) | J14: 24000 | K14: =J14*30 -> 720000 | L14: 2400 | M14: 0.42 | Q14: custo anual/banco | U14: atendimento local
B15: A | C15: 2 | D15: eventos | F15: A | G15: 2 | I15: ch (turismo) | J15: 18000 | K15: =J15*30 -> 540000 | L15: 1000 | M15: 0.54
B16: NA | C16: 4 | D16: bares e show noite | F16: NA | G16: 3 | I16: a (eventos) | J16: 12000 | K16: =J16*30 -> 360000 | L16: 900 | M16: 0.31
I17: na (vida noturna) | J17: 20000 | K17: =J17*30 -> 600000 | L17: 1800 | M17: 0.33
B20: custos anuais projetados | F20: base de calculo
C21: M1 inteligente | D21: m2 parceiros | F21: 50 semanas/ano
B22: equipamento seguro e e manutenção por posição | C22: 1400 | D22: 1400 | F22: 30 reais
B23: banco 40 | C23: 70000
B24: operação complexdade 1 | C24: 700 | D24: 1100
B25: operação complexdade 2 | C25: 1400 | D25: 2000
B26: operação complexdade 3 | C26: 3200 | D26: 4600

Sheet modelo 1
C6: opex
C7: ec | D7: ch | E7: a | F7: na
C8: =(Rascunho!C22+Rascunho!C25)*2400+70000*60 -> 10920000 | D8: =(Rascunho!C22+Rascunho!C24)*1000+70000*25 -> 3850000 | E8: =(Rascunho!C22+Rascunho!C25)*900+70000*23 -> 4130000 | F8: =(Rascunho!C22+Rascunho!C26)*1800+70000*45 -> 11430000
C10: ganhos
C11: ec | D11: ch | E11: a | F11: na
C12: =24000*50*30 -> 36000000 | D12: =18000*50*30 -> 27000000 | E12: =12000* 50*30 -> 18000000 | F12: =20000*50*30 -> 30000000
C14: lucro anual
C15: =C12-C8 -> 25080000 | D15: =D12-D8 -> 23150000 | E15: =E12-E8 -> 13870000 | F15: =F12-F8 -> 18570000

Sheet modelo 2
B3: opex
B4: ec | C4: ch | D4: a | E4: na
B5: =(Rascunho!D22+Rascunho!D25)*2400 -> 8160000 | C5: =(Rascunho!D22+Rascunho!D24)*1000 -> 2500000 | D5: =(Rascunho!D22+Rascunho!D25)*900 -> 3060000 | E5: =(Rascunho!D22+Rascunho!D26)*1800 -> 10800000
B7: ganhos
B8: ='modelo 1'!C12 -> 36000000 | C8: ='modelo 1'!D12 -> 27000000 | D8: ='modelo 1'!E12 -> 18000000 | E8: ='modelo 1'!F12 -> 30000000
B10: lucro anual
B11: =B8-B5 -> 27840000 | C11: =C8-C5 -> 24500000 | D11: =D8-D5 -> 14940000 | E11: =E8-E5 -> 19200000

Sheet comparação
B5: opex | G5: opex
B6: ec | C6: ch | D6: a | E6: na | G6: ec | H6: ch | I6: a | J6: na
B7: 10920000 | C7: 3850000 | D7: 4130000 | E7: 11430000 | G7: 8160000 | H7: 2500000 | I7: 3060000 | J7: 10800000
B9: ganhos
B10: ec | C10: ch | D10: a | E10: na | G10: ganhos
B11: 36000000 | C11: 27000000 | D11: 18000000 | E11: 30000000 | G11: 36000000 | H11: 27000000 | I11: 18000000 | J11: 30000000
B13: lucro anual | G13: lucro anual
B14: 25080000 | C14: 23150000 | D14: 13870000 | E14: 18570000 | G14: 27840000 | H14: 24500000 | I14: 14940000 | J14: 19200000
G18: =(G14/B14)-1 -> 0.11004785 | H18: =(H14/C14)-1 -> 0.058315335 | I18: =(I14/D14)-1 -> 0.077144917 | J18: =(J14/E14)-1 -> 0.033925687
B22: comparação
B23: melhor bairro | C23: estação central

Sheet diagramas
N9: Densidade de circulação | O9: Potencial de fronteira | P9: Complexidade operacional | Q9: Sensibilidade à sazonalidade
M10: Estação central | N10: 4 | O10: 3 | P10: 2 | Q10: 1
M11: Centro histórico | N11: 4 | O11: 2 | P11: 1 | Q11: 2
M12: Arena | N12: 2 | O12: 1 | P12: 2 | Q12: 3
M13: Noite alta | N13: 4 | O13: 2 | P13: 3 | Q13: 2
C18: Custos operacionais - Modelo Armários Inteligentes | H18: Custos operacionais - Modelo Pontos Parceiros | N18: opex
C20: Estação Central | D20: Centro Histórico | E20: Arena | F20: Noite Alta | H20: Estação Central | I20: Centro Histórico | J20: Arena | K20: Noite Alta | N20: ec | O20: ch | P20: a | Q20: na
C21: 10920000 | D21: 3850000 | E21: 4130000 | F21: 11430000 | H21: 8160000 | I21: 2500000 | J21: 3060000 | K21: 10800000 | N21: 8160000 | O21: 2500000 | P21: 3060000 | Q21: 10800000
C23: Ganhos operacionais - Modelo Armários Inteligentes | H23: Ganhos operacionais - Modelo Pontos Parceiros
C25: Estação Central | D25: Centro Histórico | E25: Arena | F25: Noite Alta | H25: Estação Central | I25: Centro Histórico | J25: Arena | K25: Noite Alta | N25: ganhos
C26: 36000000 | D26: 27000000 | E26: 18000000 | F26: 30000000 | H26: 36000000 | I26: 27000000 | J26: 18000000 | K26: 30000000 | N26: 36000000 | O26: 27000000 | P26: 18000000 | Q26: 30000000
C28: Lucro anual - Modelo Armários Inteligentes | H28: Lucro anual - Modelo Pontos Parceiros | N28: lucro anual
C30: Estação Central | D30: Centro Histórico | E30: Arena | F30: Noite Alta | H30: Estação Central | I30: Centro Histórico | J30: Arena | K30: Noite Alta | N30: 27840000 | O30: 24500000 | P30: 14940000 | Q30: 19200000
C31: 25080000 | D31: 23150000 | E31: 13870000 | F31: 18570000 | H31: 27840000 | I31: 24500000 | J31: 14940000 | K31: 19200000
